Workbook
Name budget: Budget_Dashboard!$L1
Name budget_range: Budget_Dashboard!$Q1
Name budget_rank: Budget_Dashboard!$R1
Name cc_budget: Calculations!$K$54
Name cc_budget: Calculations!$K1
Name cc_delta: Calculations!$L1
Name cc_in_focus: Calculations!$G1
Name cc_month_no: Calculations!$F1
Name cc_show_remaining_budget: Calculations!$I1
Name cc_show_type: Calculations!$H1
Name cc_tracked: Calculations!$J1
Name cc_type: Calculations!$E1
Name comb_rank: Budget_Dashboard!$S1
Name comb_rank_norm: Budget_Dashboard!$U1
Name comb_rank_norm_run_range: Budget_Dashboard!$V1
Name comb_rank_range: Budget_Dashboard!$T1
Name comb_rank_unique: Budget_Dashboard!$W1
Name current_date: TODAY()
Name expenses_header_row: ROW(Expenses[[#Headers],[Expenses]])
Name expenses_max_row: MAX(ROW(Expenses[]))
Name expenses_min_row: MIN(ROW(Expenses[]))
Name expenses_total_row: ROW(Budget_Planning!$C$33)
Name header_row_id: Budget_Dashboard!$D1
Name income_header_row: ROW(Income[[#Headers],[Income]])
Name income_max_row: MAX(ROW(Income[]))
Name income_min_row: MIN(ROW(Income[]))
Name income_total_row: ROW(Budget_Planning!$C$20)
Name is_cat: Budget_Dashboard!$F1
Name is_empty: Budget_Dashboard!$H1
Name is_header: Budget_Dashboard!$E1
Name is_total: Budget_Dashboard!$G1
Name item: Budget_Dashboard!$J1
Name out_budget: Budget_Dashboard!$AA1
Name out_percentage_completed: Budget_Dashboard!$AB1
Name out_tracked: Budget_Dashboard!$Z1
Name row_id: Budget_Dashboard!$C1
Name Savings_header_row: ROW(Savings[[#Headers],[Savings]])
Name savings_max_row: MAX(ROW(Savings[]))
Name savings_min_row: MIN(ROW(Savings[]))
Name savings_rate_calculation_type: Settings!$E$22
Name savings_total_row: ROW(Budget_Planning!$C$46)
Name Selected_period: Calculations!$E$20
Name selected_period_display: Calculations!$E$21
Name Selected_Year: Calculations!$E$19
Name shift_late_income_starting_day: Settings!$E$17
Name shift_late_income_status: Settings!$E$15
Name sort_max_row: Budget_Dashboard!$N1
Name sort_min_row: Budget_Dashboard!$M1
Name starting_year: Budget_Planning!$E$5
Name tracked: Budget_Dashboard!$K1
Name tracked_range: Budget_Dashboard!$O1
Name tracked_rank: Budget_Dashboard!$P1
Name type: Budget_Dashboard!$I1

Sheet Settings
B2: Settings
D6: General
D8: Starting Year: | E8: 2022 | G8: set the starting year(yyyy) at the beginning and do not change it again.
D12: Budget Tracking & Dashboard
C14: Late monthly income
C15: Shift Late Income | E15: Active | G15: Activate this option to treate late income received on or after a certain day of a month as income for a next month.This specially recommended in case you receive your monthly paycheck at the end of the month and prefer to consider this income as the disposable income for next month.
C17: starting on day x in month: | E17: 20
D20: KPI Calculation in Dashboard
D22: Savings rate as % of income: | E22: % allocated to savings | G22: Choose how you want the savings rate(SR) to be calculated in the dashboard KPI tiles:
G23: 1.)Active Option(% allocated to savings): SR=Savings/Income
G24: 2.)Passive Option(% allocated to expenses): SR=(Income-Expenses)/Income

Sheet Budget_Planning
C2: Budget Planning
C5: Define starting year in settings -> | E5: 2022 | S5: 2023 | AG5: 2024 | AU5: 2025 | BI5: 2026 | BW5: 2027 | CK5: 2028 | CY5: 2029 | DM5: 2030
E6: =IF(E7=0,"Yes","Jan") -> Yes | F6: =IF(F7=0, "Yes", "Feb") -> Yes | G6: =IF(G7=0, "Yes", "Mar") -> Yes | H6: =IF(H7=0, "Yes", "Apr") -> Yes | I6: =IF(I7=0, "Yes", "May") -> Yes | J6: =IF(J7=0, "Yes", "Jun") -> Yes | K6: =IF(K7=0, "Yes", "Jul") -> Yes | L6: =IF(L7=0, "Yes", "Aug") -> Yes | M6: =IF(M7=0, "Yes", "Sep") -> Yes | N6: =IF(N7=0, "Yes", "Oct") -> Yes | O6: =IF(O7=0, "Yes", "Nov") -> Yes | P6: =IF(P7=0, "Yes", "Dec") -> Yes | Q6: =IF(Q7=0, "Yes", "Total") -> Yes | S6: =IF(T7=0, "Yes", "Jan") -> Yes | T6: =IF(T7>=0, "Yes", "Feb") -> Yes | U6: =IF(U7=0, "Yes", "Mar") -> Yes | V6: =IF(V7=0, "Yes", "Apr") -> Yes | W6: =IF(W7=0, "Yes", "May") -> Yes | X6: =IF(X7=0, "Yes", "Jun") -> Yes | Y6: =IF(Y7=0, "Yes", "Jul") -> Yes | Z6: =IF(Z7=0, "Yes", "Aug") -> Yes | AA6: =IF(AA7=0, "Yes", "Sep") -> Yes | AB6: =IF(AB7=0, "Yes", "Oct") -> Yes | AC6: =IF(AC7=0, "Yes", "Nov") -> Yes | AD6: =IF(AD7=0, "Yes", "Dec") -> Yes | AE6: =IF(AE7=0, "Yes", "Total") -> Yes | AG6: =IF(AH7=0, "Yes", "Jan") -> Yes | AH6: =IF(AH7>=0, "Yes", "Feb") -> Yes | AI6: =IF(AI7=0, "Yes", "Mar") -> Yes | AJ6: =IF(AJ7=0, "Yes", "Apr") -> Yes | AK6: =IF(AK7=0, "Yes", "May") -> Yes | AL6: =IF(AL7=0, "Yes", "Jun") -> Yes | AM6: =IF(AM7=0, "Yes", "Jul") -> Yes | AN6: =IF(AN7=0, "Yes", "Aug") -> Yes | AO6: =IF(AO7=0, "Yes", "Sep") -> Yes | AP6: =IF(AP7=0, "Yes", "Oct") -> Yes | AQ6: =IF(AQ7=0, "Yes", "Nov") -> Yes | AR6: =IF(AR7=0, "Yes", "Dec") -> Yes | AS6: =IF(AS7=0, "Yes", "Total") -> Yes | AU6: =IF(AV7=0, "Yes", "Jan") -> Yes | AV6: =IF(AV7>=0, "Yes", "Feb") -> Yes | AW6: =IF(AW7=0, "Yes", "Mar") -> Yes | AX6: =IF(AX7=0, "Yes", "Apr") -> Yes | AY6: =IF(AY7=0, "Yes", "May") -> Yes | AZ6: =IF(AZ7=0, "Yes", "Jun") -> Yes | BA6: =IF(BA7=0, "Yes", "Jul") -> Yes | BB6: =IF(BB7=0, "Yes", "Aug") -> Yes | BC6: =IF(BC7=0, "Yes", "Sep") -> Yes | BD6: =IF(BD7=0, "Yes", "Oct") -> Yes | BE6: =IF(BE7=0, "Yes", "Nov") -> Yes | BF6: =IF(BF7=0, "Yes", "Dec") -> Yes | BG6: =IF(BG7=0, "Yes", "Total") -> Yes | BI6: =IF(BJ7=0, "Yes", "Jan") -> Yes | BJ6: =IF(BJ7>=0, "Yes", "Feb") -> Yes | BK6: =IF(BK7=0, "Yes", "Mar") -> Yes | BL6: =IF(BL7=0, "Yes", "Apr") -> Yes | BM6: =IF(BM7=0, "Yes", "May") -> Yes | BN6: =IF(BN7=0, "Yes", "Jun") -> Yes | BO6: =IF(BO7=0, "Yes", "Jul") -> Yes | BP6: =IF(BP7=0, "Yes", "Aug") -> Yes | BQ6: =IF(BQ7=0, "Yes", "Sep") -> Yes | BR6: =IF(BR7=0, "Yes", "Oct") -> Yes | BS6: =IF(BS7=0, "Yes", "Nov") -> Yes | BT6: =IF(BT7=0, "Yes", "Dec") -> Yes | BU6: =IF(BU7=0, "Yes", "Total") -> Yes | BW6: =IF(BX7=0, "Yes", "Jan") -> Yes | BX6: =IF(BX7>=0, "Yes", "Feb") -> Yes | BY6: =IF(BY7=0, "Yes", "Mar") -> Yes | BZ6: =IF(BZ7=0, "Yes", "Apr") -> Yes | CA6: =IF(CA7=0, "Yes", "May") -> Yes | CB6: =IF(CB7=0, "Yes", "Jun") -> Yes | CC6: =IF(CC7=0, "Yes", "Jul") -> Yes | CD6: =IF(CD7=0, "Yes", "Aug") -> Yes | CE6: =IF(CE7=0, "Yes", "Sep") -> Yes | CF6: =IF(CF7=0, "Yes", "Oct") -> Yes | CG6: =IF(CG7=0, "Yes", "Nov") -> Yes | CH6: =IF(CH7=0, "Yes", "Dec") -> Yes | CI6: =IF(CI7=0, "Yes", "Total") -> Yes | CK6: =IF(CL7=0, "Yes", "Jan") -> Yes | CL6: =IF(CL7>=0, "Yes", "Feb") -> Yes | CM6: =IF(CM7=0, "Yes", "Mar") -> Yes | CN6: =IF(CN7=0, "Yes", "Apr") -> Yes | CO6: =IF(CO7=0, "Yes", "May") -> Yes | CP6: =IF(CP7=0, "Yes", "Jun") -> Yes | CQ6: =IF(CQ7=0, "Yes", "Jul") -> Yes | CR6: =IF(CR7=0, "Yes", "Aug") -> Yes | CS6: =IF(CS7=0, "Yes", "Sep") -> Yes | CT6: =IF(CT7=0, "Yes", "Oct") -> Yes | CU6: =IF(CU7=0, "Yes", "Nov") -> Yes | CV6: =IF(CV7=0, "Yes", "Dec") -> Yes | CW6: =IF(CW7=0, "Yes", "Total") -> Yes | CY6: =IF(CZ7=0, "Yes", "Jan") -> Yes | CZ6: =IF(CZ7>=0, "Yes", "Feb") -> Yes | DA6: =IF(DA7=0, "Yes", "Mar") -> Yes | DB6: =IF(DB7=0, "Yes", "Apr") -> Yes | DC6: =IF(DC7=0, "Yes", "May") -> Yes | DD6: =IF(DD7=0, "Yes", "Jun") -> Yes | DE6: =IF(DE7=0, "Yes", "Jul") -> Yes | DF6: =IF(DF7=0, "Yes", "Aug") -> Yes | DG6: =IF(DG7=0, "Yes", "Sep") -> Yes | DH6: =IF(DH7=0, "Yes", "Oct") -> Yes | DI6: =IF(DI7=0, "Yes", "Nov") -> Yes | DJ6: =IF(DJ7=0, "Yes", "Dec") -> Yes | DK6: =IF(DK7=0, "Yes", "Total") -> Yes | DM6: =IF(DN7=0, "Yes", "Jan") -> Yes | DN6: =IF(DN7>=0, "Yes", "Feb") -> Yes | DO6: =IF(DO7=0, "Yes", "Mar") -> Yes | DP6: =IF(DP7=0, "Yes", "Apr") -> Yes | DQ6: =IF(DQ7=0, "Yes", "May") -> Yes | DR6: =IF(DR7=0, "Yes", "Jun") -> Yes | DS6: =IF(DS7=0, "Yes", "Jul") -> Yes | DT6: =IF(DT7=0, "Yes", "Aug") -> Yes | DU6: =IF(DU7=0, "Yes", "Sep") -> Yes | DV6: =IF(DV7=0, "Yes", "Oct") -> Yes | DW6: =IF(DW7=0, "Yes", "Nov") -> Yes | DX6: =IF(DX7=0, "Yes", "Dec") -> Yes | DY6: =IF(DY7=0, "Yes", "Total") -> Yes
C7: To be allocated: | E7: =E20-(E33+E46) -> 0 | F7: =F20-(F33+F46) -> 0 | G7: =G20-(G33+G46) -> 0 | H7: =H20-(H33+H46) -> 0 | I7: =I20-(I33+I46) -> 0 | J7: =J20-(J33+J46) -> 0 | K7: =K20-(K33+K46) -> 0 | L7: =L20-(L33+L46) -> 0 | ... Q7: =Q20-(Q33+Q46) -> 0 | S7: =S20-(S33+S46) -> 0 | T7: =T20-(T33+T46) -> 0 | U7: =U20-(U33+U46) -> 0 | V7: =V20-(V33+V46) -> 0 | W7: =W20-(W33+W46) -> 0 | X7: =X20-(X33+X46) -> 0 | Y7: =Y20-(Y33+Y46) -> 0 | Z7: =Z20-(Z33+Z46) -> 0 | ... AE7: =AE20-(AE33+AE46) -> 0 | AG7: =AG20-(AG33+AG46) -> 0 | AH7: =AH20-(AH33+AH46) -> 0 | AI7: =AI20-(AI33+AI46) -> 0 | AJ7: =AJ20-(AJ33+AJ46) -> 0 | AK7: =AK20-(AK33+AK46) -> 0 | AL7: =AL20-(AL33+AL46) -> 0 | AM7: =AM20-(AM33+AM46) -> 0 | AN7: =AN20-(AN33+AN46) -> 0 | ... AS7: =AS20-(AS33+AS46) -> 0 | AU7: =AU20-(AU33+AU46) -> 0 | AV7: =AV20-(AV33+AV46) -> 0 | AW7: =AW20-(AW33+AW46) -> 0 | AX7: =AX20-(AX33+AX46) -> 0 | AY7: =AY20-(AY33+AY46) -> 0 | AZ7: =AZ20-(AZ33+AZ46) -> 0 | BA7: =BA20-(BA33+BA46) -> 0 | BB7: =BB20-(BB33+BB46) -> 0 | ... BG7: =BG20-(BG33+BG46) -> 0 | BI7: =BI20-(BI33+BI46) -> 0 | BJ7: =BJ20-(BJ33+BJ46) -> 0 | BK7: =BK20-(BK33+BK46) -> 0 | BL7: =BL20-(BL33+BL46) -> 0 | BM7: =BM20-(BM33+BM46) -> 0 | BN7: =BN20-(BN33+BN46) -> 0 | BO7: =BO20-(BO33+BO46) -> 0 | BP7: =BP20-(BP33+BP46) -> 0 | ... BU7: =BU20-(BU33+BU46) -> 0 | BW7: =BW20-(BW33+BW46) -> 0 | BX7: =BX20-(BX33+BX46) -> 0 | BY7: =BY20-(BY33+BY46) -> 0 | BZ7: =BZ20-(BZ33+BZ46) -> 0 | CA7: =CA20-(CA33+CA46) -> 0 | CB7: =CB20-(CB33+CB46) -> 0 | CC7: =CC20-(CC33+CC46) -> 0 | CD7: =CD20-(CD33+CD46) -> 0 | ... CI7: =CI20-(CI33+CI46) -> 0 | CK7: =CK20-(CK33+CK46) -> 0 | CL7: =CL20-(CL33+CL46) -> 0 | CM7: =CM20-(CM33+CM46) -> 0 | CN7: =CN20-(CN33+CN46) -> 0 | CO7: =CO20-(CO33+CO46) -> 0 | CP7: =CP20-(CP33+CP46) -> 0 | CQ7: =CQ20-(CQ33+CQ46) -> 0 | CR7: =CR20-(CR33+CR46) -> 0 | ... CW7: =CW20-(CW33+CW46) -> 0 | CY7: =CY20-(CY33+CY46) -> 0 | CZ7: =CZ20-(CZ33+CZ46) -> 0 | DA7: =DA20-(DA33+DA46) -> 0 | DB7: =DB20-(DB33+DB46) -> 0 | DC7: =DC20-(DC33+DC46) -> 0 | DD7: =DD20-(DD33+DD46) -> 0 | DE7: =DE20-(DE33+DE46) -> 0 | DF7: =DF20-(DF33+DF46) -> 0 | ... DK7: =DK20-(DK33+DK46) -> 0 | DM7: =DM20-(DM33+DM46) -> 0 | DN7: =DN20-(DN33+DN46) -> 0 | DO7: =DO20-(DO33+DO46) -> 0 | DP7: =DP20-(DP33+DP46) -> 0 | DQ7: =DQ20-(DQ33+DQ46) -> 0 | DR7: =DR20-(DR33+DR46) -> 0 | DS7: =DS20-(DS33+DS46) -> 0 | DT7: =DT20-(DT33+DT46) -> 0 | ... DY7: =DY20-(DY33+DY46) -> 0
C9: Income | E9: =DATE(E$5,1,1) -> 44562 | F9: =DATE(E$5,2,1) -> 44593 | G9: =DATE(E$5,3,1) -> 44621 | H9: =DATE(E$5,4,1) -> 44652 | I9: =DATE(E$5,5,1) -> 44682 | J9: =DATE(E$5,6,1) -> 44713 | K9: =DATE(E$5,7,1) -> 44743 | L9: =DATE(E$5,8,1) -> 44774 | M9: =DATE(E$5,9,1) -> 44805 | N9: =DATE(E$5,10,1) -> 44835 | O9: =DATE(E$5,11,1) -> 44866 | P9: =DATE(E$5,12,1) -> 44896 | Q9: =E5 -> 2022 | S9: =DATE(S$5,1,1) -> 44927 | T9: =DATE(S$5,2,1) -> 44958 | U9: =DATE(S$5,3,1) -> 44986 | V9: =DATE(S$5,4,1) -> 45017 | W9: =DATE(S$5,5,1) -> 45047 | X9: =DATE(S$5,6,1) -> 45078 | Y9: =DATE(S$5,7,1) -> 45108 | Z9: =DATE(S$5,8,1) -> 45139 | AA9: =DATE(S$5,9,1) -> 45170 | AB9: =DATE(S$5,10,1) -> 45200 | AC9: =DATE(S$5,11,1) -> 45231 | AD9: =DATE(S$5,12,1) -> 45261 | AE9: =Q9+1 -> 2023 | AG9: =DATE(AG$5,1,1) -> 45292 | AH9: =DATE(AG$5,2,1) -> 45323 | AI9: =DATE(AG$5,3,1) -> 45352 | AJ9: =DATE(AG$5,4,1) -> 45383 | AK9: =DATE(AG$5,5,1) -> 45413 | AL9: =DATE(AG$5,6,1) -> 45444 | AM9: =DATE(AG$5,7,1) -> 45474 | AN9: =DATE(AG$5,8,1) -> 45505 | AO9: =DATE(AG$5,9,1) -> 45536 | AP9: =DATE(AG$5,10,1) -> 45566 | AQ9: =DATE(AG$5,11,1) -> 45597 | AR9: =DATE(AG$5,12,1) -> 45627 | AS9: =AE9+1 -> 2024 | AU9: =DATE(AU$5,1,1) -> 45658 | AV9: =DATE(AU$5,2,1) -> 45689 | AW9: =DATE(AU$5,3,1) -> 45717 | AX9: =DATE(AU$5,4,1) -> 45748 | AY9: =DATE(AU$5,5,1) -> 45778 | AZ9: =DATE(AU$5,6,1) -> 45809 | BA9: =DATE(AU$5,7,1) -> 45839 | BB9: =DATE(AU$5,8,1) -> 45870 | BC9: =DATE(AU$5,9,1) -> 45901 | BD9: =DATE(AU$5,10,1) -> 45931 | BE9: =DATE(AU$5,11,1) -> 45962 | BF9: =DATE(AU$5,12,1) -> 45992 | BG9: =AS9+1 -> 2025 | BI9: =DATE(BI$5,1,1) -> 46023 | BJ9: =DATE(BI$5,2,1) -> 46054 | BK9: =DATE(BI$5,3,1) -> 46082 | BL9: =DATE(BI$5,4,1) -> 46113 | BM9: =DATE(BI$5,5,1) -> 46143 | BN9: =DATE(BI$5,6,1) -> 46174 | BO9: =DATE(BI$5,7,1) -> 46204 | BP9: =DATE(BI$5,8,1) -> 46235 | BQ9: =DATE(BI$5,9,1) -> 46266 | BR9: =DATE(BI$5,10,1) -> 46296 | BS9: =DATE(BI$5,11,1) -> 46327 | BT9: =DATE(BI$5,12,1) -> 46357 | BU9: =BG9+1 -> 2026 | BW9: =DATE(BW$5,1,1) -> 46388 | BX9: =DATE(BW$5,2,1) -> 46419 | BY9: =DATE(BW$5,3,1) -> 46447 | BZ9: =DATE(BW$5,4,1) -> 46478 | CA9: =DATE(BW$5,5,1) -> 46508 | CB9: =DATE(BW$5,6,1) -> 46539 | CC9: =DATE(BW$5,7,1) -> 46569 | CD9: =DATE(BW$5,8,1) -> 46600 | CE9: =DATE(BW$5,9,1) -> 46631 | CF9: =DATE(BW$5,10,1) -> 46661 | CG9: =DATE(BW$5,11,1) -> 46692 | CH9: =DATE(BW$5,12,1) -> 46722 | CI9: =BU9+1 -> 2027 | CK9: =DATE(CK$5,1,1) -> 46753 | CL9: =DATE(CK$5,2,1) -> 46784 | CM9: =DATE(CK$5,3,1) -> 46813 | CN9: =DATE(CK$5,4,1) -> 46844 | CO9: =DATE(CK$5,5,1) -> 46874 | CP9: =DATE(CK$5,6,1) -> 46905 | CQ9: =DATE(CK$5,7,1) -> 46935 | CR9: =DATE(CK$5,8,1) -> 46966 | CS9: =DATE(CK$5,9,1) -> 46997 | CT9: =DATE(CK$5,10,1) -> 47027 | CU9: =DATE(CK$5,11,1) -> 47058 | CV9: =DATE(CK$5,12,1) -> 47088 | CW9: =CI9+1 -> 2028 | CY9: =DATE(CY$5,1,1) -> 47119 | CZ9: =DATE(CY$5,2,1) -> 47150 | DA9: =DATE(CY$5,3,1) -> 47178 | DB9: =DATE(CY$5,4,1) -> 47209 | DC9: =DATE(CY$5,5,1) -> 47239 | DD9: =DATE(CY$5,6,1) -> 47270 | DE9: =DATE(CY$5,7,1) -> 47300 | DF9: =DATE(CY$5,8,1) -> 47331 | DG9: =DATE(CY$5,9,1) -> 47362 | DH9: =DATE(CY$5,10,1) -> 47392 | DI9: =DATE(CY$5,11,1) -> 47423 | DJ9: =DATE(CY$5,12,1) -> 47453 | DK9: =CW9+1 -> 2029 | DM9: =DATE(DM$5,1,1) -> 47484 | DN9: =DATE(DM$5,2,1) -> 47515 | DO9: =DATE(DM$5,3,1) -> 47543 | DP9: =DATE(DM$5,4,1) -> 47574 | DQ9: =DATE(DM$5,5,1) -> 47604 | DR9: =DATE(DM$5,6,1) -> 47635 | DS9: =DATE(DM$5,7,1) -> 47665 | DT9: =DATE(DM$5,8,1) -> 47696 | DU9: =DATE(DM$5,9,1) -> 47727 | DV9: =DATE(DM$5,10,1) -> 47757 | DW9: =DATE(DM$5,11,1) -> 47788 | DX9: =DATE(DM$5,12,1) -> 47818 | DY9: =DK9+1 -> 2030
C10: Employment(Net) | E10: 3500 | F10: 3500 | G10: 3500 | H10: 4500 | I10: 4500 | J10: 4500 | K10: 4500 | L10: 4500 | M10: 4500 | N10: 4500 | O10: 4500 | P10: 4500 | Q10: =SUM(E10:P10) -> 51000 | AE10: =SUM(S10:AD10) -> 0 | AS10: =SUM(AG10:AR10) -> 0 | BG10: =SUM(AU10:BF10) -> 0 | BU10: =SUM(BI10:BT10) -> 0 | CI10: =SUM(BW10:CH10) -> 0 | CW10: =SUM(CK10:CV10) -> 0 | DK10: =SUM(CY10:DJ10) -> 0 | DY10: =SUM(DM10:DX10) -> 0
C11: Side Hustles(net) | E11: 1000 | F11: 1000 | G11: 1000 | H11: 1000 | I11: 1000 | J11: 1000 | K11: 1000 | L11: 1000 | M11: 1000 | N11: 1000 | O11: 1000 | P11: 1000 | Q11: =SUM(E11:P11) -> 12000 | AE11: =SUM(S11:AD11) -> 0 | AS11: =SUM(AG11:AR11) -> 0 | BG11: =SUM(AU11:BF11) -> 0 | BU11: =SUM(BI11:BT11) -> 0 | CI11: =SUM(BW11:CH11) -> 0 | CW11: =SUM(CK11:CV11) -> 0 | DK11: =SUM(CY11:DJ11) -> 0 | DY11: =SUM(DM11:DX11) -> 0
C12: Dividends | E12: 150 | F12: 50 | G12: 100 | H12: 150 | I12: 50 | J12: 100 | K12: 150 | L12: 50 | M12: 100 | N12: 150 | O12: 50 | P12: 100 | Q12: =SUM(E12:P12) -> 1200 | AE12: =SUM(S12:AD12) -> 0 | AS12: =SUM(AG12:AR12) -> 0 | BG12: =SUM(AU12:BF12) -> 0 | BU12: =SUM(BI12:BT12) -> 0 | CI12: =SUM(BW12:CH12) -> 0 | CW12: =SUM(CK12:CV12) -> 0 | DK12: =SUM(CY12:DJ12) -> 0 | DY12: =SUM(DM12:DX12) -> 0
C13: Enter Income Category | Q13: =SUM(E13:P13) -> 0 | AE13: =SUM(S13:AD13) -> 0 | AS13: =SUM(AG13:AR13) -> 0 | BG13: =SUM(AU13:BF13) -> 0 | BU13: =SUM(BI13:BT13) -> 0 | CI13: =SUM(BW13:CH13) -> 0 | CW13: =SUM(CK13:CV13) -> 0 | DK13: =SUM(CY13:DJ13) -> 0 | DY13: =SUM(DM13:DX13) -> 0
C14: Enter Income Category | Q14: =SUM(E14:P14) -> 0 | AE14: =SUM(S14:AD14) -> 0 | AS14: =SUM(AG14:AR14) -> 0 | BG14: =SUM(AU14:BF14) -> 0 | BU14: =SUM(BI14:BT14) -> 0 | CI14: =SUM(BW14:CH14) -> 0 | CW14: =SUM(CK14:CV14) -> 0 | DK14: =SUM(CY14:DJ14) -> 0 | DY14: =SUM(DM14:DX14) -> 0
C15: Enter Income Category | Q15: =SUM(E15:P15) -> 0 | AE15: =SUM(S15:AD15) -> 0 | AS15: =SUM(AG15:AR15) -> 0 | BG15: =SUM(AU15:BF15) -> 0 | BU15: =SUM(BI15:BT15) -> 0 | CI15: =SUM(BW15:CH15) -> 0 | CW15: =SUM(CK15:CV15) -> 0 | DK15: =SUM(CY15:DJ15) -> 0 | DY15: =SUM(DM15:DX15) -> 0
C16: Enter Income Category | Q16: =SUM(E16:P16) -> 0 | AE16: =SUM(S16:AD16) -> 0 | AS16: =SUM(AG16:AR16) -> 0 | BG16: =SUM(AU16:BF16) -> 0 | BU16: =SUM(BI16:BT16) -> 0 | CI16: =SUM(BW16:CH16) -> 0 | CW16: =SUM(CK16:CV16) -> 0 | DK16: =SUM(CY16:DJ16) -> 0 | DY16: =SUM(DM16:DX16) -> 0
C17: Enter Income Category | Q17: =SUM(E17:P17) -> 0 | AE17: =SUM(S17:AD17) -> 0 | AS17: =SUM(AG17:AR17) -> 0 | BG17: =SUM(AU17:BF17) -> 0 | BU17: =SUM(BI17:BT17) -> 0 | CI17: =SUM(BW17:CH17) -> 0 | CW17: =SUM(CK17:CV17) -> 0 | DK17: =SUM(CY17:DJ17) -> 0 | DY17: =SUM(DM17:DX17) -> 0
C18: Enter Income Category | Q18: =SUM(E18:P18) -> 0 | AE18: =SUM(S18:AD18) -> 0 | AS18: =SUM(AG18:AR18) -> 0 | BG18: =SUM(AU18:BF18) -> 0 | BU18: =SUM(BI18:BT18) -> 0 | CI18: =SUM(BW18:CH18) -> 0 | CW18: =SUM(CK18:CV18) -> 0 | DK18: =SUM(CY18:DJ18) -> 0 | DY18: =SUM(DM18:DX18) -> 0
C19: Enter Income Category | Q19: =SUM(E19:P19) -> 0 | AE19: =SUM(S19:AD19) -> 0 | AS19: =SUM(AG19:AR19) -> 0 | BG19: =SUM(AU19:BF19) -> 0 | BU19: =SUM(BI19:BT19) -> 0 | CI19: =SUM(BW19:CH19) -> 0 | CW19: =SUM(CK19:CV19) -> 0 | DK19: =SUM(CY19:DJ19) -> 0 | DY19: =SUM(DM19:DX19) -> 0
C20: Total | E20: {=SUM(INDIRECT(ADDRESS(income_min_row,COLUMN()) & ":" & ADDRESS(income_max_row, COLUMN())))} -> 4650 | F20: {=SUM(INDIRECT(ADDRESS(income_min_row,COLUMN()) & ":" & ADDRESS(income_max_row, COLUMN())))} -> 4550 | G20: {=SUM(INDIRECT(ADDRESS(income_min_row,COLUMN()) & ":" & ADDRESS(income_max_row, COLUMN())))} -> 4600 | H20: {=SUM(INDIRECT(ADDRESS(income_min_row,COLUMN()) & ":" & ADDRESS(income_max_row, COLUMN())))} -> 5650 | I20: {=SUM(INDIRECT(ADDRESS(income_min_row,COLUMN()) & ":" & ADDRESS(income_max_row, COLUMN())))} -> 5550 | J20: {=SUM(INDIRECT(ADDRESS(income_min_row,COLUMN()) & ":" & ADDRESS(income_max_row, COLUMN())))} -> 5600 | K20: {=SUM(INDIRECT(ADDRESS(income_min_row,COLUMN()) & ":" & ADDRESS(income_max_row, COLUMN())))} -> 5650 | L20: {=SUM(INDIRECT(ADDRESS(income_min_row,COLUMN()) & ":" & ADDRESS(income_max_row, COLUMN())))} -> 5550 | ... P20: {=SUM(INDIRECT(ADDRESS(income_min_row,COLUMN()) & ":" & ADDRESS(income_max_row, COLUMN())))} -> 5600 | Q20: =SUM(E20:P20) -> 64200 | S20: {=SUM(INDIRECT(ADDRESS(income_min_row,COLUMN()) & ":" & ADDRESS(income_max_row, COLUMN())))} -> 0 | T20: {=SUM(INDIRECT(ADDRESS(income_min_row,COLUMN()) & ":" & ADDRESS(income_max_row, COLUMN())))} -> 0 | U20: {=SUM(INDIRECT(ADDRESS(income_min_row,COLUMN()) & ":" & ADDRESS(income_max_row, COLUMN())))} -> 0 | V20: {=SUM(INDIRECT(ADDRESS(income_min_row,COLUMN()) & ":" & ADDRESS(income_max_row, COLUMN())))} -> 0 | X20: {=SUM(INDIRECT(ADDRESS(income_min_row,COLUMN()) & ":" & ADDRESS(income_max_row, COLUMN())))} -> 0 | Y20: {=SUM(INDIRECT(ADDRESS(income_min_row,COLUMN()) & ":" & ADDRESS(income_max_row, COLUMN())))} -> 0 | Z20: {=SUM(INDIRECT(ADDRESS(income_min_row,COLUMN()) & ":" & ADDRESS(income_max_row, COLUMN())))} -> 0 | AA20: {=SUM(INDIRECT(ADDRESS(income_min_row,COLUMN()) & ":" & ADDRESS(income_max_row, COLUMN())))} -> 0 | AB20: {=SUM(INDIRECT(ADDRESS(income_min_row,COLUMN()) & ":" & ADDRESS(income_max_row, COLUMN())))} -> 0 | AC20: {=SUM(INDIRECT(ADDRESS(income_min_row,COLUMN()) & ":" & ADDRESS(income_max_row, COLUMN())))} -> 0 | AD20: {=SUM(INDIRECT(ADDRESS(income_min_row,COLUMN()) & ":" & ADDRESS(income_max_row, COLUMN())))} -> 0 | AE20: =SUM(S20:AD20) -> 0 | AG20: {=SUM(INDIRECT(ADDRESS(income_min_row,COLUMN()) & ":" & ADDRESS(income_max_row, COLUMN())))} -> 0 | AH20: {=SUM(INDIRECT(ADDRESS(income_min_row,COLUMN()) & ":" & ADDRESS(income_max_row, COLUMN())))} -> 0 | AI20: {=SUM(INDIRECT(ADDRESS(income_min_row,COLUMN()) & ":" & ADDRESS(income_max_row, COLUMN())))} -> 0 | AJ20: {=SUM(INDIRECT(ADDRESS(income_min_row,COLUMN()) & ":" & ADDRESS(income_max_row, COLUMN())))} -> 0 | AL20: {=SUM(INDIRECT(ADDRESS(income_min_row,COLUMN()) & ":" & ADDRESS(income_max_row, COLUMN())))} -> 0 | AM20: {=SUM(INDIRECT(ADDRESS(income_min_row,COLUMN()) & ":" & ADDRESS(income_max_row, COLUMN())))} -> 0 | AN20: {=SUM(INDIRECT(ADDRESS(income_min_row,COLUMN()) & ":" & ADDRESS(income_max_row, COLUMN())))} -> 0 | AO20: {=SUM(INDIRECT(ADDRESS(income_min_row,COLUMN()) & ":" & ADDRESS(income_max_row, COLUMN())))} -> 0 | AP20: {=SUM(INDIRECT(ADDRESS(income_min_row,COLUMN()) & ":" & ADDRESS(income_max_row, COLUMN())))} -> 0 | AQ20: {=SUM(INDIRECT(ADDRESS(income_min_row,COLUMN()) & ":" & ADDRESS(income_max_row, COLUMN())))} -> 0 | AR20: {=SUM(INDIRECT(ADDRESS(income_min_row,COLUMN()) & ":" & ADDRESS(income_max_row, COLUMN())))} -> 0 | AS20: =SUM(AG20:AR20) -> 0 | AU20: {=SUM(INDIRECT(ADDRESS(income_min_row,COLUMN()) & ":" & ADDRESS(income_max_row, COLUMN())))} -> 0 | AV20: {=SUM(INDIRECT(ADDRESS(income_min_row,COLUMN()) & ":" & ADDRESS(income_max_row, COLUMN())))} -> 0 | AW20: {=SUM(INDIRECT(ADDRESS(income_min_row,COLUMN()) & ":" & ADDRESS(income_max_row, COLUMN())))} -> 0 | AX20: {=SUM(INDIRECT(ADDRESS(income_min_row,COLUMN()) & ":" & ADDRESS(income_max_row, COLUMN())))} -> 0 | AZ20: {=SUM(INDIRECT(ADDRESS(income_min_row,COLUMN()) & ":" & ADDRESS(income_max_row, COLUMN())))} -> 0 | BA20: {=SUM(INDIRECT(ADDRESS(income_min_row,COLUMN()) & ":" & ADDRESS(income_max_row, COLUMN())))} -> 0 | BB20: {=SUM(INDIRECT(ADDRESS(income_min_row,COLUMN()) & ":" & ADDRESS(income_max_row, COLUMN())))} -> 0 | BC20: {=SUM(INDIRECT(ADDRESS(income_min_row,COLUMN()) & ":" & ADDRESS(income_max_row, COLUMN())))} -> 0 | BD20: {=SUM(INDIRECT(ADDRESS(income_min_row,COLUMN()) & ":" & ADDRESS(income_max_row, COLUMN())))} -> 0 | BE20: {=SUM(INDIRECT(ADDRESS(income_min_row,COLUMN()) & ":" & ADDRESS(income_max_row, COLUMN())))} -> 0 | BF20: {=SUM(INDIRECT(ADDRESS(income_min_row,COLUMN()) & ":" & ADDRESS(income_max_row, COLUMN())))} -> 0 | BG20: =SUM(AU20:BF20) -> 0 | BI20: {=SUM(INDIRECT(ADDRESS(income_min_row,COLUMN()) & ":" & ADDRESS(income_max_row, COLUMN())))} -> 0 | BJ20: {=SUM(INDIRECT(ADDRESS(income_min_row,COLUMN()) & ":" & ADDRESS(income_max_row, COLUMN())))} -> 0 | BK20: {=SUM(INDIRECT(ADDRESS(income_min_row,COLUMN()) & ":" & ADDRESS(income_max_row, COLUMN())))} -> 0 | BL20: {=SUM(INDIRECT(ADDRESS(income_min_row,COLUMN()) & ":" & ADDRESS(income_max_row, COLUMN())))} -> 0 | BN20: {=SUM(INDIRECT(ADDRESS(income_min_row,COLUMN()) & ":" & ADDRESS(income_max_row, COLUMN())))} -> 0 | BO20: {=SUM(INDIRECT(ADDRESS(income_min_row,COLUMN()) & ":" & ADDRESS(income_max_row, COLUMN())))} -> 0 | BP20: {=SUM(INDIRECT(ADDRESS(income_min_row,COLUMN()) & ":" & ADDRESS(income_max_row, COLUMN())))} -> 0 | BQ20: {=SUM(INDIRECT(ADDRESS(income_min_row,COLUMN()) & ":" & ADDRESS(income_max_row, COLUMN())))} -> 0 | BR20: {=SUM(INDIRECT(ADDRESS(income_min_row,COLUMN()) & ":" & ADDRESS(income_max_row, COLUMN())))} -> 0 | BS20: {=SUM(INDIRECT(ADDRESS(income_min_row,COLUMN()) & ":" & ADDRESS(income_max_row, COLUMN())))} -> 0 | BT20: {=SUM(INDIRECT(ADDRESS(income_min_row,COLUMN()) & ":" & ADDRESS(income_max_row, COLUMN())))} -> 0 | BU20: =SUM(BI20:BT20) -> 0 | BW20: {=SUM(INDIRECT(ADDRESS(income_min_row,COLUMN()) & ":" & ADDRESS(income_max_row, COLUMN())))} -> 0 | BX20: {=SUM(INDIRECT(ADDRESS(income_min_row,COLUMN()) & ":" & ADDRESS(income_max_row, COLUMN())))} -> 0 | BY20: {=SUM(INDIRECT(ADDRESS(income_min_row,COLUMN()) & ":" & ADDRESS(income_max_row, COLUMN())))} -> 0 | BZ20: {=SUM(INDIRECT(ADDRESS(income_min_row,COLUMN()) & ":" & ADDRESS(income_max_row, COLUMN())))} -> 0 | CB20: {=SUM(INDIRECT(ADDRESS(income_min_row,COLUMN()) & ":" & ADDRESS(income_max_row, COLUMN())))} -> 0 | CC20: {=SUM(INDIRECT(ADDRESS(income_min_row,COLUMN()) & ":" & ADDRESS(income_max_row, COLUMN())))} -> 0 | CD20: {=SUM(INDIRECT(ADDRESS(income_min_row,COLUMN()) & ":" & ADDRESS(income_max_row, COLUMN())))} -> 0 | CE20: {=SUM(INDIRECT(ADDRESS(income_min_row,COLUMN()) & ":" & ADDRESS(income_max_row, COLUMN())))} -> 0 | CF20: {=SUM(INDIRECT(ADDRESS(income_min_row,COLUMN()) & ":" & ADDRESS(income_max_row, COLUMN())))} -> 0 | CG20: {=SUM(INDIRECT(ADDRESS(income_min_row,COLUMN()) & ":" & ADDRESS(income_max_row, COLUMN())))} -> 0 | CH20: {=SUM(INDIRECT(ADDRESS(income_min_row,COLUMN()) & ":" & ADDRESS(income_max_row, COLUMN())))} -> 0 | CI20: =SUM(BW20:CH20) -> 0 | CK20: {=SUM(INDIRECT(ADDRESS(income_min_row,COLUMN()) & ":" & ADDRESS(income_max_row, COLUMN())))} -> 0 | CL20: {=SUM(INDIRECT(ADDRESS(income_min_row,COLUMN()) & ":" & ADDRESS(income_max_row, COLUMN())))} -> 0 | CM20: {=SUM(INDIRECT(ADDRESS(income_min_row,COLUMN()) & ":" & ADDRESS(income_max_row, COLUMN())))} -> 0 | CN20: {=SUM(INDIRECT(ADDRESS(income_min_row,COLUMN()) & ":" & ADDRESS(income_max_row, COLUMN())))} -> 0 | CP20: {=SUM(INDIRECT(ADDRESS(income_min_row,COLUMN()) & ":" & ADDRESS(income_max_row, COLUMN())))} -> 0 | CQ20: {=SUM(INDIRECT(ADDRESS(income_min_row,COLUMN()) & ":" & ADDRESS(income_max_row, COLUMN())))} -> 0 | CR20: {=SUM(INDIRECT(ADDRESS(income_min_row,COLUMN()) & ":" & ADDRESS(income_max_row, COLUMN())))} -> 0 | CS20: {=SUM(INDIRECT(ADDRESS(income_min_row,COLUMN()) & ":" & ADDRESS(income_max_row, COLUMN())))} -> 0 | CT20: {=SUM(INDIRECT(ADDRESS(income_min_row,COLUMN()) & ":" & ADDRESS(income_max_row, COLUMN())))} -> 0 | CU20: {=SUM(INDIRECT(ADDRESS(income_min_row,COLUMN()) & ":" & ADDRESS(income_max_row, COLUMN())))} -> 0 | CV20: {=SUM(INDIRECT(ADDRESS(income_min_row,COLUMN()) & ":" & ADDRESS(income_max_row, COLUMN())))} -> 0 | CW20: =SUM(CK20:CV20) -> 0 | CY20: {=SUM(INDIRECT(ADDRESS(income_min_row,COLUMN()) & ":" & ADDRESS(income_max_row, COLUMN())))} -> 0 | CZ20: {=SUM(INDIRECT(ADDRESS(income_min_row,COLUMN()) & ":" & ADDRESS(income_max_row, COLUMN())))} -> 0 | DA20: {=SUM(INDIRECT(ADDRESS(income_min_row,COLUMN()) & ":" & ADDRESS(income_max_row, COLUMN())))} -> 0 | DB20: {=SUM(INDIRECT(ADDRESS(income_min_row,COLUMN()) & ":" & ADDRESS(income_max_row, COLUMN())))} -> 0 | DD20: {=SUM(INDIRECT(ADDRESS(income_min_row,COLUMN()) & ":" & ADDRESS(income_max_row, COLUMN())))} -> 0 | DE20: {=SUM(INDIRECT(ADDRESS(income_min_row,COLUMN()) & ":" & ADDRESS(income_max_row, COLUMN())))} -> 0 | DF20: {=SUM(INDIRECT(ADDRESS(income_min_row,COLUMN()) & ":" & ADDRESS(income_max_row, COLUMN())))} -> 0 | DG20: {=SUM(INDIRECT(ADDRESS(income_min_row,COLUMN()) & ":" & ADDRESS(income_max_row, COLUMN())))} -> 0 | DH20: {=SUM(INDIRECT(ADDRESS(income_min_row,COLUMN()) & ":" & ADDRESS(income_max_row, COLUMN())))} -> 0 | DI20: {=SUM(INDIRECT(ADDRESS(income_min_row,COLUMN()) & ":" & ADDRESS(income_max_row, COLUMN())))} -> 0 | DJ20: {=SUM(INDIRECT(ADDRESS(income_min_row,COLUMN()) & ":" & ADDRESS(income_max_row, COLUMN())))} -> 0 | DK20: =SUM(CY20:DJ20) -> 0 | DM20: {=SUM(INDIRECT(ADDRESS(income_min_row,COLUMN()) & ":" & ADDRESS(income_max_row, COLUMN())))} -> 0 | DN20: {=SUM(INDIRECT(ADDRESS(income_min_row,COLUMN()) & ":" & ADDRESS(income_max_row, COLUMN())))} -> 0 | DO20: {=SUM(INDIRECT(ADDRESS(income_min_row,COLUMN()) & ":" & ADDRESS(income_max_row, COLUMN())))} -> 0 | DP20: {=SUM(INDIRECT(ADDRESS(income_min_row,COLUMN()) & ":" & ADDRESS(income_max_row, COLUMN())))} -> 0 | DR20: {=SUM(INDIRECT(ADDRESS(income_min_row,COLUMN()) & ":" & ADDRESS(income_max_row, COLUMN())))} -> 0 | DS20: {=SUM(INDIRECT(ADDRESS(income_min_row,COLUMN()) & ":" & ADDRESS(income_max_row, COLUMN())))} -> 0 | DT20: {=SUM(INDIRECT(ADDRESS(income_min_row,COLUMN()) & ":" & ADDRESS(income_max_row, COLUMN())))} -> 0 | DU20: {=SUM(INDIRECT(ADDRESS(income_min_row,COLUMN()) & ":" & ADDRESS(income_max_row, COLUMN())))} -> 0 | DV20: {=SUM(INDIRECT(ADDRESS(income_min_row,COLUMN()) & ":" & ADDRESS(income_max_row, COLUMN())))} -> 0 | DW20: {=SUM(INDIRECT(ADDRESS(income_min_row,COLUMN()) & ":" & ADDRESS(income_max_row, COLUMN())))} -> 0 | DX20: {=SUM(INDIRECT(ADDRESS(income_min_row,COLUMN()) & ":" & ADDRESS(income_max_row, COLUMN())))} -> 0 | DY20: =SUM(DM20:DX20) -> 0
C22: Expenses | E22: =DATE(E$5,1,1) -> 44562 | F22: =DATE(E$5,2,1) -> 44593 | G22: =DATE(E$5,3,1) -> 44621 | H22: =DATE(E$5,4,1) -> 44652 | I22: =DATE(E$5,5,1) -> 44682 | J22: =DATE(E$5,6,1) -> 44713 | K22: =DATE(E$5,7,1) -> 44743 | L22: =DATE(E$5,8,1) -> 44774 | M22: =DATE(E$5,9,1) -> 44805 | N22: =DATE(E$5,10,1) -> 44835 | O22: =DATE(E$5,11,1) -> 44866 | P22: =DATE(E$5,12,1) -> 44896 | Q22: 2022 | S22: =DATE(S$5,1,1) -> 44927 | T22: =DATE(S$5,2,1) -> 44958 | U22: =DATE(S$5,3,1) -> 44986 | V22: =DATE(S$5,4,1) -> 45017 | W22: =DATE(S$5,5,1) -> 45047 | X22: =DATE(S$5,6,1) -> 45078 | Y22: =DATE(S$5,7,1) -> 45108 | Z22: =DATE(S$5,8,1) -> 45139 | AA22: =DATE(S$5,9,1) -> 45170 | AB22: =DATE(S$5,10,1) -> 45200 | AC22: =DATE(S$5,11,1) -> 45231 | AD22: =DATE(S$5,12,1) -> 45261 | AE22: =Q22+1 -> 2023 | AG22: =DATE(AG$5,1,1) -> 45292 | AH22: =DATE(AG$5,2,1) -> 45323 | AI22: =DATE(AG$5,3,1) -> 45352 | AJ22: =DATE(AG$5,4,1) -> 45383 | AK22: =DATE(AG$5,5,1) -> 45413 | AL22: =DATE(AG$5,6,1) -> 45444 | AM22: =DATE(AG$5,7,1) -> 45474 | AN22: =DATE(AG$5,8,1) -> 45505 | AO22: =DATE(AG$5,9,1) -> 45536 | AP22: =DATE(AG$5,10,1) -> 45566 | AQ22: =DATE(AG$5,11,1) -> 45597 | AR22: =DATE(AG$5,12,1) -> 45627 | AS22: =AE22+1 -> 2024 | AU22: =DATE(AU$5,1,1) -> 45658 | AV22: =DATE(AU$5,2,1) -> 45689 | AW22: =DATE(AU$5,3,1) -> 45717 | AX22: =DATE(AU$5,4,1) -> 45748 | AY22: =DATE(AU$5,5,1) -> 45778 | AZ22: =DATE(AU$5,6,1) -> 45809 | BA22: =DATE(AU$5,7,1) -> 45839 | BB22: =DATE(AU$5,8,1) -> 45870 | BC22: =DATE(AU$5,9,1) -> 45901 | BD22: =DATE(AU$5,10,1) -> 45931 | BE22: =DATE(AU$5,11,1) -> 45962 | BF22: =DATE(AU$5,12,1) -> 45992 | BG22: =AS22+1 -> 2025 | BI22: =DATE(BI$5,1,1) -> 46023 | BJ22: =DATE(BI$5,2,1) -> 46054 | BK22: =DATE(BI$5,3,1) -> 46082 | BL22: =DATE(BI$5,4,1) -> 46113 | BM22: =DATE(BI$5,5,1) -> 46143 | BN22: =DATE(BI$5,6,1) -> 46174 | BO22: =DATE(BI$5,7,1) -> 46204 | BP22: =DATE(BI$5,8,1) -> 46235 | BQ22: =DATE(BI$5,9,1) -> 46266 | BR22: =DATE(BI$5,10,1) -> 46296 | BS22: =DATE(BI$5,11,1) -> 46327 | BT22: =DATE(BI$5,12,1) -> 46357 | BU22: =BG22+1 -> 2026 | BW22: =DATE(BW$5,1,1) -> 46388 | BX22: =DATE(BW$5,2,1) -> 46419 | BY22: =DATE(BW$5,3,1) -> 46447 | BZ22: =DATE(BW$5,4,1) -> 46478 | CA22: =DATE(BW$5,5,1) -> 46508 | CB22: =DATE(BW$5,6,1) -> 46539 | CC22: =DATE(BW$5,7,1) -> 46569 | CD22: =DATE(BW$5,8,1) -> 46600 | CE22: =DATE(BW$5,9,1) -> 46631 | CF22: =DATE(BW$5,10,1) -> 46661 | CG22: =DATE(BW$5,11,1) -> 46692 | CH22: =DATE(BW$5,12,1) -> 46722 | CI22: =BU22+1 -> 2027 | CK22: =DATE(CK$5,1,1) -> 46753 | CL22: =DATE(CK$5,2,1) -> 46784 | CM22: =DATE(CK$5,3,1) -> 46813 | CN22: =DATE(CK$5,4,1) -> 46844 | CO22: =DATE(CK$5,5,1) -> 46874 | CP22: =DATE(CK$5,6,1) -> 46905 | CQ22: =DATE(CK$5,7,1) -> 46935 | CR22: =DATE(CK$5,8,1) -> 46966 | CS22: =DATE(CK$5,9,1) -> 46997 | CT22: =DATE(CK$5,10,1) -> 47027 | CU22: =DATE(CK$5,11,1) -> 47058 | CV22: =DATE(CK$5,12,1) -> 47088 | CW22: =CI22+1 -> 2028 | CY22: =DATE(CY$5,1,1) -> 47119 | CZ22: =DATE(CY$5,2,1) -> 47150 | DA22: =DATE(CY$5,3,1) -> 47178 | DB22: =DATE(CY$5,4,1) -> 47209 | DC22: =DATE(CY$5,5,1) -> 47239 | DD22: =DATE(CY$5,6,1) -> 47270 | DE22: =DATE(CY$5,7,1) -> 47300 | DF22: =DATE(CY$5,8,1) -> 47331 | DG22: =DATE(CY$5,9,1) -> 47362 | DH22: =DATE(CY$5,10,1) -> 47392 | DI22: =DATE(CY$5,11,1) -> 47423 | DJ22: =DATE(CY$5,12,1) -> 47453 | DK22: =CW22+1 -> 2029 | DM22: =DATE(DM$5,1,1) -> 47484 | DN22: =DATE(DM$5,2,1) -> 47515 | DO22: =DATE(DM$5,3,1) -> 47543 | DP22: =DATE(DM$5,4,1) -> 47574 | DQ22: =DATE(DM$5,5,1) -> 47604 | DR22: =DATE(DM$5,6,1) -> 47635 | DS22: =DATE(DM$5,7,1) -> 47665 | DT22: =DATE(DM$5,8,1) -> 47696 | DU22: =DATE(DM$5,9,1) -> 47727 | DV22: =DATE(DM$5,10,1) -> 47757 | DW22: =DATE(DM$5,11,1) -> 47788 | DX22: =DATE(DM$5,12,1) -> 47818 | DY22: =DK22+1 -> 2030
C23: Housing | E23: 1200 | F23: 1200 | G23: 1200 | H23: 1200 | I23: 1200 | J23: 1200 | K23: 1200 | L23: 1200 | M23: 1200 | N23: 1200 | O23: 1200 | P23: 1200 | Q23: =SUM(E23:P23) -> 14400 | AE23: =SUM(S23:AD23) -> 0 | AS23: =SUM(AG23:AR23) -> 0 | BG23: =SUM(AU23:BF23) -> 0 | BU23: =SUM(BI23:BT23) -> 0 | CI23: =SUM(BW23:CH23) -> 0 | CW23: =SUM(CK23:CV23) -> 0 | DK23: =SUM(CY23:DJ23) -> 0 | DY23: =SUM(DM23:DX23) -> 0
C24: Utilities | E24: 300 | F24: 300 | G24: 300 | H24: 300 | I24: 300 | J24: 300 | K24: 300 | L24: 300 | M24: 300 | N24: 300 | O24: 300 | P24: 300 | Q24: =SUM(E24:P24) -> 3600 | AE24: =SUM(S24:AD24) -> 0 | AS24: =SUM(AG24:AR24) -> 0 | BG24: =SUM(AU24:BF24) -> 0 | BU24: =SUM(BI24:BT24) -> 0 | CI24: =SUM(BW24:CH24) -> 0 | CW24: =SUM(CK24:CV24) -> 0 | DK24: =SUM(CY24:DJ24) -> 0 | DY24: =SUM(DM24:DX24) -> 0
C25: Groceries | E25: 350 | F25: 350 | G25: 350 | H25: 350 | I25: 350 | J25: 350 | K25: 350 | L25: 350 | M25: 350 | N25: 350 | O25: 350 | P25: 350 | Q25: =SUM(E25:P25) -> 4200 | AE25: =SUM(S25:AD25) -> 0 | AS25: =SUM(AG25:AR25) -> 0 | BG25: =SUM(AU25:BF25) -> 0 | BU25: =SUM(BI25:BT25) -> 0 | CI25: =SUM(BW25:CH25) -> 0 | CW25: =SUM(CK25:CV25) -> 0 | DK25: =SUM(CY25:DJ25) -> 0 | DY25: =SUM(DM25:DX25) -> 0
C26: Transport | E26: 300 | F26: 300 | G26: 300 | H26: 300 | I26: 300 | J26: 300 | K26: 300 | L26: 300 | M26: 300 | N26: 300 | O26: 300 | P26: 300 | Q26: =SUM(E26:P26) -> 3600 | AE26: =SUM(S26:AD26) -> 0 | AS26: =SUM(AG26:AR26) -> 0 | BG26: =SUM(AU26:BF26) -> 0 | BU26: =SUM(BI26:BT26) -> 0 | CI26: =SUM(BW26:CH26) -> 0 | CW26: =SUM(CK26:CV26) -> 0 | DK26: =SUM(CY26:DJ26) -> 0 | DY26: =SUM(DM26:DX26) -> 0
C27: Insurance | E27: 0 | F27: 0 | G27: 150 | H27: 0 | I27: 0 | J27: 150 | K27: 0 | L27: 0 | M27: 150 | N27: 0 | O27: 0 | P27: 150 | Q27: =SUM(E27:P27) -> 600 | AE27: =SUM(S27:AD27) -> 0 | AS27: =SUM(AG27:AR27) -> 0 | BG27: =SUM(AU27:BF27) -> 0 | BU27: =SUM(BI27:BT27) -> 0 | CI27: =SUM(BW27:CH27) -> 0 | CW27: =SUM(CK27:CV27) -> 0 | DK27: =SUM(CY27:DJ27) -> 0 | DY27: =SUM(DM27:DX27) -> 0
C28: Clothing | E28: 200 | F28: 200 | G28: 200 | H28: 200 | I28: 200 | J28: 200 | K28: 200 | L28: 200 | M28: 200 | N28: 200 | O28: 200 | P28: 200 | Q28: =SUM(E28:P28) -> 2400 | AE28: =SUM(S28:AD28) -> 0 | AS28: =SUM(AG28:AR28) -> 0 | BG28: =SUM(AU28:BF28) -> 0 | BU28: =SUM(BI28:BT28) -> 0 | CI28: =SUM(BW28:CH28) -> 0 | CW28: =SUM(CK28:CV28) -> 0 | DK28: =SUM(CY28:DJ28) -> 0 | DY28: =SUM(DM28:DX28) -> 0
C29: Body care | E29: 200 | F29: 200 | G29: 200 | H29: 200 | I29: 200 | J29: 200 | K29: 200 | L29: 200 | M29: 200 | N29: 200 | O29: 200 | P29: 200 | Q29: =SUM(E29:P29) -> 2400 | AE29: =SUM(S29:AD29) -> 0 | AS29: =SUM(AG29:AR29) -> 0 | BG29: =SUM(AU29:BF29) -> 0 | BU29: =SUM(BI29:BT29) -> 0 | CI29: =SUM(BW29:CH29) -> 0 | CW29: =SUM(CK29:CV29) -> 0 | DK29: =SUM(CY29:DJ29) -> 0 | DY29: =SUM(DM29:DX29) -> 0
C30: Media | E30: 50 | F30: 50 | G30: 50 | H30: 50 | I30: 50 | J30: 50 | K30: 50 | L30: 50 | M30: 50 | N30: 50 | O30: 50 | P30: 50 | Q30: =SUM(E30:P30) -> 600 | AE30: =SUM(S30:AD30) -> 0 | AS30: =SUM(AG30:AR30) -> 0 | BG30: =SUM(AU30:BF30) -> 0 | BU30: =SUM(BI30:BT30) -> 0 | CI30: =SUM(BW30:CH30) -> 0 | CW30: =SUM(CK30:CV30) -> 0 | DK30: =SUM(CY30:DJ30) -> 0 | DY30: =SUM(DM30:DX30) -> 0
C31: Fun&Vacation | E31: 300 | F31: 300 | G31: 300 | H31: 1200 | I31: 300 | J31: 300 | K31: 300 | L31: 1500 | M31: 300 | N31: 300 | O31: 300 | P31: 600 | Q31: =SUM(E31:P31) -> 6000 | AE31: =SUM(S31:AD31) -> 0 | AS31: =SUM(AG31:AR31) -> 0 | BG31: =SUM(AU31:BF31) -> 0 | BU31: =SUM(BI31:BT31) -> 0 | CI31: =SUM(BW31:CH31) -> 0 | CW31: =SUM(CK31:CV31) -> 0 | DK31: =SUM(CY31:DJ31) -> 0 | DY31: =SUM(DM31:DX31) -> 0
C32: Enter Income Category | Q32: =SUM(E32:P32) -> 0 | AE32: =SUM(S32:AD32) -> 0 | AS32: =SUM(AG32:AR32) -> 0 | BG32: =SUM(AU32:BF32) -> 0 | BU32: =SUM(BI32:BT32) -> 0 | CI32: =SUM(BW32:CH32) -> 0 | CW32: =SUM(CK32:CV32) -> 0 | DK32: =SUM(CY32:DJ32) -> 0 | DY32: =SUM(DM32:DX32) -> 0
C33: Total | E33: {=SUM(INDIRECT(ADDRESS(expenses_min_row,COLUMN()) & ":" & ADDRESS(expenses_max_row, COLUMN())))} -> 2900 | F33: {=SUM(INDIRECT(ADDRESS(expenses_min_row,COLUMN()) & ":" & ADDRESS(expenses_max_row, COLUMN())))} -> 2900 | G33: {=SUM(INDIRECT(ADDRESS(expenses_min_row,COLUMN()) & ":" & ADDRESS(expenses_max_row, COLUMN())))} -> 3050 | H33: {=SUM(INDIRECT(ADDRESS(expenses_min_row,COLUMN()) & ":" & ADDRESS(expenses_max_row, COLUMN())))} -> 3800 | I33: {=SUM(INDIRECT(ADDRESS(expenses_min_row,COLUMN()) & ":" & ADDRESS(expenses_max_row, COLUMN())))} -> 2900 | J33: {=SUM(INDIRECT(ADDRESS(expenses_min_row,COLUMN()) & ":" & ADDRESS(expenses_max_row, COLUMN())))} -> 3050 | K33: {=SUM(INDIRECT(ADDRESS(expenses_min_row,COLUMN()) & ":" & ADDRESS(expenses_max_row, COLUMN())))} -> 2900 | L33: {=SUM(INDIRECT(ADDRESS(expenses_min_row,COLUMN()) & ":" & ADDRESS(expenses_max_row, COLUMN())))} -> 4100 | ... P33: {=SUM(INDIRECT(ADDRESS(expenses_min_row,COLUMN()) & ":" & ADDRESS(expenses_max_row, COLUMN())))} -> 3350 | Q33: =SUM(E33:P33) -> 37800 | S33: {=SUM(INDIRECT(ADDRESS(expenses_min_row,COLUMN()) & ":" & ADDRESS(expenses_max_row, COLUMN())))} -> 0 | T33: {=SUM(INDIRECT(ADDRESS(expenses_min_row,COLUMN()) & ":" & ADDRESS(expenses_max_row, COLUMN())))} -> 0 | U33: {=SUM(INDIRECT(ADDRESS(expenses_min_row,COLUMN()) & ":" & ADDRESS(expenses_max_row, COLUMN())))} -> 0 | V33: {=SUM(INDIRECT(ADDRESS(expenses_min_row,COLUMN()) & ":" & ADDRESS(expenses_max_row, COLUMN())))} -> 0 | W33: {=SUM(INDIRECT(ADDRESS(expenses_min_row,COLUMN()) & ":" & ADDRESS(expenses_max_row, COLUMN())))} -> 0 | X33: {=SUM(INDIRECT(ADDRESS(expenses_min_row,COLUMN()) & ":" & ADDRESS(expenses_max_row, COLUMN())))} -> 0 | Y33: {=SUM(INDIRECT(ADDRESS(expenses_min_row,COLUMN()) & ":" & ADDRESS(expenses_max_row, COLUMN())))} -> 0 | Z33: {=SUM(INDIRECT(ADDRESS(expenses_min_row,COLUMN()) & ":" & ADDRESS(expenses_max_row, COLUMN())))} -> 0 | ... AD33: {=SUM(INDIRECT(ADDRESS(expenses_min_row,COLUMN()) & ":" & ADDRESS(expenses_max_row, COLUMN())))} -> 0 | AE33: =SUM(S33:AD33) -> 0 | AG33: {=SUM(INDIRECT(ADDRESS(expenses_min_row,COLUMN()) & ":" & ADDRESS(expenses_max_row, COLUMN())))} -> 0 | AH33: {=SUM(INDIRECT(ADDRESS(expenses_min_row,COLUMN()) & ":" & ADDRESS(expenses_max_row, COLUMN())))} -> 0 | AI33: {=SUM(INDIRECT(ADDRESS(expenses_min_row,COLUMN()) & ":" & ADDRESS(expenses_max_row, COLUMN())))} -> 0 | AJ33: {=SUM(INDIRECT(ADDRESS(expenses_min_row,COLUMN()) & ":" & ADDRESS(expenses_max_row, COLUMN())))} -> 0 | AK33: {=SUM(INDIRECT(ADDRESS(expenses_min_row,COLUMN()) & ":" & ADDRESS(expenses_max_row, COLUMN())))} -> 0 | AL33: {=SUM(INDIRECT(ADDRESS(expenses_min_row,COLUMN()) & ":" & ADDRESS(expenses_max_row, COLUMN())))} -> 0 | AM33: {=SUM(INDIRECT(ADDRESS(expenses_min_row,COLUMN()) & ":" & ADDRESS(expenses_max_row, COLUMN())))} -> 0 | AN33: {=SUM(INDIRECT(ADDRESS(expenses_min_row,COLUMN()) & ":" & ADDRESS(expenses_max_row, COLUMN())))} -> 0 | ... AR33: {=SUM(INDIRECT(ADDRESS(expenses_min_row,COLUMN()) & ":" & ADDRESS(expenses_max_row, COLUMN())))} -> 0 | AS33: =SUM(AG33:AR33) -> 0 | AU33: {=SUM(INDIRECT(ADDRESS(expenses_min_row,COLUMN()) & ":" & ADDRESS(expenses_max_row, COLUMN())))} -> 0 | AV33: {=SUM(INDIRECT(ADDRESS(expenses_min_row,COLUMN()) & ":" & ADDRESS(expenses_max_row, COLUMN())))} -> 0 | AW33: {=SUM(INDIRECT(ADDRESS(expenses_min_row,COLUMN()) & ":" & ADDRESS(expenses_max_row, COLUMN())))} -> 0 | AX33: {=SUM(INDIRECT(ADDRESS(expenses_min_row,COLUMN()) & ":" & ADDRESS(expenses_max_row, COLUMN())))} -> 0 | AY33: {=SUM(INDIRECT(ADDRESS(expenses_min_row,COLUMN()) & ":" & ADDRESS(expenses_max_row, COLUMN())))} -> 0 | AZ33: {=SUM(INDIRECT(ADDRESS(expenses_min_row,COLUMN()) & ":" & ADDRESS(expenses_max_row, COLUMN())))} -> 0 | BA33: {=SUM(INDIRECT(ADDRESS(expenses_min_row,COLUMN()) & ":" & ADDRESS(expenses_max_row, COLUMN())))} -> 0 | BB33: {=SUM(INDIRECT(ADDRESS(expenses_min_row,COLUMN()) & ":" & ADDRESS(expenses_max_row, COLUMN())))} -> 0 | ... BF33: {=SUM(INDIRECT(ADDRESS(expenses_min_row,COLUMN()) & ":" & ADDRESS(expenses_max_row, COLUMN())))} -> 0 | BG33: =SUM(AU33:BF33) -> 0 | BI33: {=SUM(INDIRECT(ADDRESS(expenses_min_row,COLUMN()) & ":" & ADDRESS(expenses_max_row, COLUMN())))} -> 0 | BJ33: {=SUM(INDIRECT(ADDRESS(expenses_min_row,COLUMN()) & ":" & ADDRESS(expenses_max_row, COLUMN())))} -> 0 | BK33: {=SUM(INDIRECT(ADDRESS(expenses_min_row,COLUMN()) & ":" & ADDRESS(expenses_max_row, COLUMN())))} -> 0 | BL33: {=SUM(INDIRECT(ADDRESS(expenses_min_row,COLUMN()) & ":" & ADDRESS(expenses_max_row, COLUMN())))} -> 0 | BM33: {=SUM(INDIRECT(ADDRESS(expenses_min_row,COLUMN()) & ":" & ADDRESS(expenses_max_row, COLUMN())))} -> 0 | BN33: {=SUM(INDIRECT(ADDRESS(expenses_min_row,COLUMN()) & ":" & ADDRESS(expenses_max_row, COLUMN())))} -> 0 | BO33: {=SUM(INDIRECT(ADDRESS(expenses_min_row,COLUMN()) & ":" & ADDRESS(expenses_max_row, COLUMN())))} -> 0 | BP33: {=SUM(INDIRECT(ADDRESS(expenses_min_row,COLUMN()) & ":" & ADDRESS(expenses_max_row, COLUMN())))} -> 0 | ... BT33: {=SUM(INDIRECT(ADDRESS(expenses_min_row,COLUMN()) & ":" & ADDRESS(expenses_max_row, COLUMN())))} -> 0 | BU33: =SUM(BI33:BT33) -> 0 | BW33: {=SUM(INDIRECT(ADDRESS(expenses_min_row,COLUMN()) & ":" & ADDRESS(expenses_max_row, COLUMN())))} -> 0 | BX33: {=SUM(INDIRECT(ADDRESS(expenses_min_row,COLUMN()) & ":" & ADDRESS(expenses_max_row, COLUMN())))} -> 0 | BY33: {=SUM(INDIRECT(ADDRESS(expenses_min_row,COLUMN()) & ":" & ADDRESS(expenses_max_row, COLUMN())))} -> 0 | BZ33: {=SUM(INDIRECT(ADDRESS(expenses_min_row,COLUMN()) & ":" & ADDRESS(expenses_max_row, COLUMN())))} -> 0 | CA33: {=SUM(INDIRECT(ADDRESS(expenses_min_row,COLUMN()) & ":" & ADDRESS(expenses_max_row, COLUMN())))} -> 0 | CB33: {=SUM(INDIRECT(ADDRESS(expenses_min_row,COLUMN()) & ":" & ADDRESS(expenses_max_row, COLUMN())))} -> 0 | CC33: {=SUM(INDIRECT(ADDRESS(expenses_min_row,COLUMN()) & ":" & ADDRESS(expenses_max_row, COLUMN())))} -> 0 | CD33: {=SUM(INDIRECT(ADDRESS(expenses_min_row,COLUMN()) & ":" & ADDRESS(expenses_max_row, COLUMN())))} -> 0 | ... CH33: {=SUM(INDIRECT(ADDRESS(expenses_min_row,COLUMN()) & ":" & ADDRESS(expenses_max_row, COLUMN())))} -> 0 | CI33: =SUM(BW33:CH33) -> 0 | CK33: {=SUM(INDIRECT(ADDRESS(expenses_min_row,COLUMN()) & ":" & ADDRESS(expenses_max_row, COLUMN())))} -> 0 | CL33: {=SUM(INDIRECT(ADDRESS(expenses_min_row,COLUMN()) & ":" & ADDRESS(expenses_max_row, COLUMN())))} -> 0 | CM33: {=SUM(INDIRECT(ADDRESS(expenses_min_row,COLUMN()) & ":" & ADDRESS(expenses_max_row, COLUMN())))} -> 0 | CN33: {=SUM(INDIRECT(ADDRESS(expenses_min_row,COLUMN()) & ":" & ADDRESS(expenses_max_row, COLUMN())))} -> 0 | CO33: {=SUM(INDIRECT(ADDRESS(expenses_min_row,COLUMN()) & ":" & ADDRESS(expenses_max_row, COLUMN())))} -> 0 | CP33: {=SUM(INDIRECT(ADDRESS(expenses_min_row,COLUMN()) & ":" & ADDRESS(expenses_max_row, COLUMN())))} -> 0 | CQ33: {=SUM(INDIRECT(ADDRESS(expenses_min_row,COLUMN()) & ":" & ADDRESS(expenses_max_row, COLUMN())))} -> 0 | CR33: {=SUM(INDIRECT(ADDRESS(expenses_min_row,COLUMN()) & ":" & ADDRESS(expenses_max_row, COLUMN())))} -> 0 | ... CV33: {=SUM(INDIRECT(ADDRESS(expenses_min_row,COLUMN()) & ":" & ADDRESS(expenses_max_row, COLUMN())))} -> 0 | CW33: =SUM(CK33:CV33) -> 0 | CY33: {=SUM(INDIRECT(ADDRESS(expenses_min_row,COLUMN()) & ":" & ADDRESS(expenses_max_row, COLUMN())))} -> 0 | CZ33: {=SUM(INDIRECT(ADDRESS(expenses_min_row,COLUMN()) & ":" & ADDRESS(expenses_max_row, COLUMN())))} -> 0 | DA33: {=SUM(INDIRECT(ADDRESS(expenses_min_row,COLUMN()) & ":" & ADDRESS(expenses_max_row, COLUMN())))} -> 0 | DB33: {=SUM(INDIRECT(ADDRESS(expenses_min_row,COLUMN()) & ":" & ADDRESS(expenses_max_row, COLUMN())))} -> 0 | DC33: {=SUM(INDIRECT(ADDRESS(expenses_min_row,COLUMN()) & ":" & ADDRESS(expenses_max_row, COLUMN())))} -> 0 | DD33: {=SUM(INDIRECT(ADDRESS(expenses_min_row,COLUMN()) & ":" & ADDRESS(expenses_max_row, COLUMN())))} -> 0 | DE33: {=SUM(INDIRECT(ADDRESS(expenses_min_row,COLUMN()) & ":" & ADDRESS(expenses_max_row, COLUMN())))} -> 0 | DF33: {=SUM(INDIRECT(ADDRESS(expenses_min_row,COLUMN()) & ":" & ADDRESS(expenses_max_row, COLUMN())))} -> 0 | ... DJ33: {=SUM(INDIRECT(ADDRESS(expenses_min_row,COLUMN()) & ":" & ADDRESS(expenses_max_row, COLUMN())))} -> 0 | DK33: =SUM(CY33:DJ33) -> 0 | DM33: {=SUM(INDIRECT(ADDRESS(expenses_min_row,COLUMN()) & ":" & ADDRESS(expenses_max_row, COLUMN())))} -> 0 | DN33: {=SUM(INDIRECT(ADDRESS(expenses_min_row,COLUMN()) & ":" & ADDRESS(expenses_max_row, COLUMN())))} -> 0 | DO33: {=SUM(INDIRECT(ADDRESS(expenses_min_row,COLUMN()) & ":" & ADDRESS(expenses_max_row, COLUMN())))} -> 0 | DP33: {=SUM(INDIRECT(ADDRESS(expenses_min_row,COLUMN()) & ":" & ADDRESS(expenses_max_row, COLUMN())))} -> 0 | DQ33: {=SUM(INDIRECT(ADDRESS(expenses_min_row,COLUMN()) & ":" & ADDRESS(expenses_max_row, COLUMN())))} -> 0 | DR33: {=SUM(INDIRECT(ADDRESS(expenses_min_row,COLUMN()) & ":" & ADDRESS(expenses_max_row, COLUMN())))} -> 0 | DS33: {=SUM(INDIRECT(ADDRESS(expenses_min_row,COLUMN()) & ":" & ADDRESS(expenses_max_row, COLUMN())))} -> 0 | DT33: {=SUM(INDIRECT(ADDRESS(expenses_min_row,COLUMN()) & ":" & ADDRESS(expenses_max_row, COLUMN())))} -> 0 | ... DX33: {=SUM(INDIRECT(ADDRESS(expenses_min_row,COLUMN()) & ":" & ADDRESS(expenses_max_row, COLUMN())))} -> 0 | DY33: =SUM(DM33:DX33) -> 0
C35: Savings | E35: =DATE(E$5,1,1) -> 44562 | F35: =DATE(E$5,2,1) -> 44593 | G35: =DATE(E$5,3,1) -> 44621 | H35: =DATE(E$5,4,1) -> 44652 | I35: =DATE(E$5,5,1) -> 44682 | J35: =DATE(E$5,6,1) -> 44713 | K35: =DATE(E$5,7,1) -> 44743 | L35: =DATE(E$5,8,1) -> 44774 | M35: =DATE(E$5,9,1) -> 44805 | N35: =DATE(E$5,10,1) -> 44835 | O35: =DATE(E$5,11,1) -> 44866 | P35: =DATE(E$5,12,1) -> 44896 | Q35: 2022 | S35: =DATE(S$5,1,1) -> 44927 | T35: =DATE(S$5,2,1) -> 44958 | U35: =DATE(S$5,3,1) -> 44986 | V35: =DATE(S$5,4,1) -> 45017 | W35: =DATE(S$5,5,1) -> 45047 | X35: =DATE(S$5,6,1) -> 45078 | Y35: =DATE(S$5,7,1) -> 45108 | Z35: =DATE(S$5,8,1) -> 45139 | AA35: =DATE(S$5,9,1) -> 45170 | AB35: =DATE(S$5,10,1) -> 45200 | AC35: =DATE(S$5,11,1) -> 45231 | AD35: =DATE(S$5,12,1) -> 45261 | AE35: =Q35+1 -> 2023 | AG35: =DATE(AG$5,1,1) -> 45292 | AH35: =DATE(AG$5,2,1) -> 45323 | AI35: =DATE(AG$5,3,1) -> 45352 | AJ35: =DATE(AG$5,4,1) -> 45383 | AK35: =DATE(AG$5,5,1) -> 45413 | AL35: =DATE(AG$5,6,1) -> 45444 | AM35: =DATE(AG$5,7,1) -> 45474 | AN35: =DATE(AG$5,8,1) -> 45505 | AO35: =DATE(AG$5,9,1) -> 45536 | AP35: =DATE(AG$5,10,1) -> 45566 | AQ35: =DATE(AG$5,11,1) -> 45597 | AR35: =DATE(AG$5,12,1) -> 45627 | AS35: =AE35+1 -> 2024 | AU35: =DATE(AU$5,1,1) -> 45658 | AV35: =DATE(AU$5,2,1) -> 45689 | AW35: =DATE(AU$5,3,1) -> 45717 | AX35: =DATE(AU$5,4,1) -> 45748 | AY35: =DATE(AU$5,5,1) -> 45778 | AZ35: =DATE(AU$5,6,1) -> 45809 | BA35: =DATE(AU$5,7,1) -> 45839 | BB35: =DATE(AU$5,8,1) -> 45870 | BC35: =DATE(AU$5,9,1) -> 45901 | BD35: =DATE(AU$5,10,1) -> 45931 | BE35: =DATE(AU$5,11,1) -> 45962 | BF35: =DATE(AU$5,12,1) -> 45992 | BG35: =AS35+1 -> 2025 | BI35: =DATE(BI$5,1,1) -> 46023 | BJ35: =DATE(BI$5,2,1) -> 46054 | BK35: =DATE(BI$5,3,1) -> 46082 | BL35: =DATE(BI$5,4,1) -> 46113 | BM35: =DATE(BI$5,5,1) -> 46143 | BN35: =DATE(BI$5,6,1) -> 46174 | BO35: =DATE(BI$5,7,1) -> 46204 | BP35: =DATE(BI$5,8,1) -> 46235 | BQ35: =DATE(BI$5,9,1) -> 46266 | BR35: =DATE(BI$5,10,1) -> 46296 | BS35: =DATE(BI$5,11,1) -> 46327 | BT35: =DATE(BI$5,12,1) -> 46357 | BU35: =BG35+1 -> 2026 | BW35: =DATE(BW$5,1,1) -> 46388 | BX35: =DATE(BW$5,2,1) -> 46419 | BY35: =DATE(BW$5,3,1) -> 46447 | BZ35: =DATE(BW$5,4,1) -> 46478 | CA35: =DATE(BW$5,5,1) -> 46508 | CB35: =DATE(BW$5,6,1) -> 46539 | CC35: =DATE(BW$5,7,1) -> 46569 | CD35: =DATE(BW$5,8,1) -> 46600 | CE35: =DATE(BW$5,9,1) -> 46631 | CF35: =DATE(BW$5,10,1) -> 46661 | CG35: =DATE(BW$5,11,1) -> 46692 | CH35: =DATE(BW$5,12,1) -> 46722 | CI35: =BU35+1 -> 2027 | CK35: =DATE(CK$5,1,1) -> 46753 | CL35: =DATE(CK$5,2,1) -> 46784 | CM35: =DATE(CK$5,3,1) -> 46813 | CN35: =DATE(CK$5,4,1) -> 46844 | CO35: =DATE(CK$5,5,1) -> 46874 | CP35: =DATE(CK$5,6,1) -> 46905 | CQ35: =DATE(CK$5,7,1) -> 46935 | CR35: =DATE(CK$5,8,1) -> 46966 | CS35: =DATE(CK$5,9,1) -> 46997 | CT35: =DATE(CK$5,10,1) -> 47027 | CU35: =DATE(CK$5,11,1) -> 47058 | CV35: =DATE(CK$5,12,1) -> 47088 | CW35: =CI35+1 -> 2028 | CY35: =DATE(CY$5,1,1) -> 47119 | CZ35: =DATE(CY$5,2,1) -> 47150 | DA35: =DATE(CY$5,3,1) -> 47178 | DB35: =DATE(CY$5,4,1) -> 47209 | DC35: =DATE(CY$5,5,1) -> 47239 | DD35: =DATE(CY$5,6,1) -> 47270 | DE35: =DATE(CY$5,7,1) -> 47300 | DF35: =DATE(CY$5,8,1) -> 47331 | DG35: =DATE(CY$5,9,1) -> 47362 | DH35: =DATE(CY$5,10,1) -> 47392 | DI35: =DATE(CY$5,11,1) -> 47423 | DJ35: =DATE(CY$5,12,1) -> 47453 | DK35: =CW35+1 -> 2029 | DM35: =DATE(DM$5,1,1) -> 47484 | DN35: =DATE(DM$5,2,1) -> 47515 | DO35: =DATE(DM$5,3,1) -> 47543 | DP35: =DATE(DM$5,4,1) -> 47574 | DQ35: =DATE(DM$5,5,1) -> 47604 | DR35: =DATE(DM$5,6,1) -> 47635 | DS35: =DATE(DM$5,7,1) -> 47665 | DT35: =DATE(DM$5,8,1) -> 47696 | DU35: =DATE(DM$5,9,1) -> 47727 | DV35: =DATE(DM$5,10,1) -> 47757 | DW35: =DATE(DM$5,11,1) -> 47788 | DX35: =DATE(DM$5,12,1) -> 47818 | DY35: =DK35+1 -> 2030
C36: Emergency Fund | E36: 1000 | F36: 1000 | G36: 1000 | H36: 0 | I36: 0 | J36: 0 | K36: 0 | L36: 0 | M36: 0 | N36: 0 | O36: 0 | P36: 0 | Q36: =SUM(E36:P36) -> 3000 | AE36: =SUM(S36:AD36) -> 0 | AS36: =SUM(AG36:AR36) -> 0 | BG36: =SUM(AU36:BF36) -> 0 | BU36: =SUM(BI36:BT36) -> 0 | CI36: =SUM(BW36:CH36) -> 0 | CW36: =SUM(CK36:CV36) -> 0 | DK36: =SUM(CY36:DJ36) -> 0 | DY36: =SUM(DM36:DX36) -> 0
C37: Retirement Account | E37: 400 | F37: 400 | G37: 400 | H37: 400 | I37: 400 | J37: 400 | K37: 400 | L37: 400 | M37: 400 | N37: 400 | O37: 400 | P37: 400 | Q37: =SUM(E37:P37) -> 4800 | AE37: =SUM(S37:AD37) -> 0 | AS37: =SUM(AG37:AR37) -> 0 | BG37: =SUM(AU37:BF37) -> 0 | BU37: =SUM(BI37:BT37) -> 0 | CI37: =SUM(BW37:CH37) -> 0 | CW37: =SUM(CK37:CV37) -> 0 | DK37: =SUM(CY37:DJ37) -> 0 | DY37: =SUM(DM37:DX37) -> 0
C38: Stock Portfolio | E38: 150 | F38: 150 | G38: 150 | H38: 750 | I38: 750 | J38: 750 | K38: 750 | L38: 750 | M38: 750 | N38: 750 | O38: 750 | P38: 750 | Q38: =SUM(E38:P38) -> 7200 | AE38: =SUM(S38:AD38) -> 0 | AS38: =SUM(AG38:AR38) -> 0 | BG38: =SUM(AU38:BF38) -> 0 | BU38: =SUM(BI38:BT38) -> 0 | CI38: =SUM(BW38:CH38) -> 0 | CW38: =SUM(CK38:CV38) -> 0 | DK38: =SUM(CY38:DJ38) -> 0 | DY38: =SUM(DM38:DX38) -> 0
C39: Sinking Fund | E39: 0 | F39: 0 | G39: 0 | H39: 600 | I39: 1400 | J39: 1300 | K39: 1500 | L39: 200 | M39: 1300 | N39: 1500 | O39: 1400 | P39: 1000 | Q39: =SUM(E39:P39) -> 10200 | AE39: =SUM(S39:AD39) -> 0 | AS39: =SUM(AG39:AR39) -> 0 | BG39: =SUM(AU39:BF39) -> 0 | BU39: =SUM(BI39:BT39) -> 0 | CI39: =SUM(BW39:CH39) -> 0 | CW39: =SUM(CK39:CV39) -> 0 | DK39: =SUM(CY39:DJ39) -> 0 | DY39: =SUM(DM39:DX39) -> 0
C40: Sinking fund rest | E40: 200 | F40: 100 | G40: 0 | H40: 100 | I40: 100 | J40: 100 | K40: 100 | L40: 100 | M40: 100 | N40: 100 | O40: 100 | P40: 100 | Q40: =SUM(E40:P40) -> 1200 | AE40: =SUM(S40:AD40) -> 0 | AS40: =SUM(AG40:AR40) -> 0 | BG40: =SUM(AU40:BF40) -> 0 | BU40: =SUM(BI40:BT40) -> 0 | CI40: =SUM(BW40:CH40) -> 0 | CW40: =SUM(CK40:CV40) -> 0 | DK40: =SUM(CY40:DJ40) -> 0 | DY40: =SUM(DM40:DX40) -> 0
C41: Enter savings Category | Q41: =SUM(E41:P41) -> 0 | AE41: =SUM(S41:AD41) -> 0 | AS41: =SUM(AG41:AR41) -> 0 | BG41: =SUM(AU41:BF41) -> 0 | BU41: =SUM(BI41:BT41) -> 0 | CI41: =SUM(BW41:CH41) -> 0 | CW41: =SUM(CK41:CV41) -> 0 | DK41: =SUM(CY41:DJ41) -> 0 | DY41: =SUM(DM41:DX41) -> 0
C42: Entersavings Category | Q42: =SUM(E42:P42) -> 0 | AE42: =SUM(S42:AD42) -> 0 | AS42: =SUM(AG42:AR42) -> 0 | BG42: =SUM(AU42:BF42) -> 0 | BU42: =SUM(BI42:BT42) -> 0 | CI42: =SUM(BW42:CH42) -> 0 | CW42: =SUM(CK42:CV42) -> 0 | DK42: =SUM(CY42:DJ42) -> 0 | DY42: =SUM(DM42:DX42) -> 0
C43: Enter savings Category | Q43: =SUM(E43:P43) -> 0 | AE43: =SUM(S43:AD43) -> 0 | AS43: =SUM(AG43:AR43) -> 0 | BG43: =SUM(AU43:BF43) -> 0 | BU43: =SUM(BI43:BT43) -> 0 | CI43: =SUM(BW43:CH43) -> 0 | CW43: =SUM(CK43:CV43) -> 0 | DK43: =SUM(CY43:DJ43) -> 0 | DY43: =SUM(DM43:DX43) -> 0
C44: Enter savings Category | Q44: =SUM(E44:P44) -> 0 | AE44: =SUM(S44:AD44) -> 0 | AS44: =SUM(AG44:AR44) -> 0 | BG44: =SUM(AU44:BF44) -> 0 | BU44: =SUM(BI44:BT44) -> 0 | CI44: =SUM(BW44:CH44) -> 0 | CW44: =SUM(CK44:CV44) -> 0 | DK44: =SUM(CY44:DJ44) -> 0 | DY44: =SUM(DM44:DX44) -> 0
C45: Enter savings Category | Q45: =SUM(E45:P45) -> 0 | AE45: =SUM(S45:AD45) -> 0 | AS45: =SUM(AG45:AR45) -> 0 | BG45: =SUM(AU45:BF45) -> 0 | BU45: =SUM(BI45:BT45) -> 0 | CI45: =SUM(BW45:CH45) -> 0 | CW45: =SUM(CK45:CV45) -> 0 | DK45: =SUM(CY45:DJ45) -> 0 | DY45: =SUM(DM45:DX45) -> 0
C46: Total | E46: {=SUM(INDIRECT(ADDRESS(savings_min_row,COLUMN()) & ":" & ADDRESS(savings_max_row, COLUMN())))} -> 1750 | F46: {=SUM(INDIRECT(ADDRESS(savings_min_row,COLUMN()) & ":" & ADDRESS(savings_max_row, COLUMN())))} -> 1650 | G46: {=SUM(INDIRECT(ADDRESS(savings_min_row,COLUMN()) & ":" & ADDRESS(savings_max_row, COLUMN())))} -> 1550 | H46: {=SUM(INDIRECT(ADDRESS(savings_min_row,COLUMN()) & ":" & ADDRESS(savings_max_row, COLUMN())))} -> 1850 | I46: {=SUM(INDIRECT(ADDRESS(savings_min_row,COLUMN()) & ":" & ADDRESS(savings_max_row, COLUMN())))} -> 2650 | J46: {=SUM(INDIRECT(ADDRESS(savings_min_row,COLUMN()) & ":" & ADDRESS(savings_max_row, COLUMN())))} -> 2550 | K46: {=SUM(INDIRECT(ADDRESS(savings_min_row,COLUMN()) & ":" & ADDRESS(savings_max_row, COLUMN())))} -> 2750 | L46: {=SUM(INDIRECT(ADDRESS(savings_min_row,COLUMN()) & ":" & ADDRESS(savings_max_row, COLUMN())))} -> 1450 | ... P46: {=SUM(INDIRECT(ADDRESS(savings_min_row,COLUMN()) & ":" & ADDRESS(savings_max_row, COLUMN())))} -> 2250 | Q46: =SUM(E46:P46) -> 26400 | S46: {=SUM(INDIRECT(ADDRESS(savings_min_row,COLUMN()) & ":" & ADDRESS(savings_max_row, COLUMN())))} -> 0 | T46: {=SUM(INDIRECT(ADDRESS(savings_min_row,COLUMN()) & ":" & ADDRESS(savings_max_row, COLUMN())))} -> 0 | U46: {=SUM(INDIRECT(ADDRESS(savings_min_row,COLUMN()) & ":" & ADDRESS(savings_max_row, COLUMN())))} -> 0 | V46: {=SUM(INDIRECT(ADDRESS(savings_min_row,COLUMN()) & ":" & ADDRESS(savings_max_row, COLUMN())))} -> 0 | W46: {=SUM(INDIRECT(ADDRESS(savings_min_row,COLUMN()) & ":" & ADDRESS(savings_max_row, COLUMN())))} -> 0 | X46: {=SUM(INDIRECT(ADDRESS(savings_min_row,COLUMN()) & ":" & ADDRESS(savings_max_row, COLUMN())))} -> 0 | Y46: {=SUM(INDIRECT(ADDRESS(savings_min_row,COLUMN()) & ":" & ADDRESS(savings_max_row, COLUMN())))} -> 0 | Z46: {=SUM(INDIRECT(ADDRESS(savings_min_row,COLUMN()) & ":" & ADDRESS(savings_max_row, COLUMN())))} -> 0 | ... AD46: {=SUM(INDIRECT(ADDRESS(savings_min_row,COLUMN()) & ":" & ADDRESS(savings_max_row, COLUMN())))} -> 0 | AE46: =SUM(S46:AD46) -> 0 | AG46: {=SUM(INDIRECT(ADDRESS(savings_min_row,COLUMN()) & ":" & ADDRESS(savings_max_row, COLUMN())))} -> 0 | AH46: {=SUM(INDIRECT(ADDRESS(savings_min_row,COLUMN()) & ":" & ADDRESS(savings_max_row, COLUMN())))} -> 0 | AI46: {=SUM(INDIRECT(ADDRESS(savings_min_row,COLUMN()) & ":" & ADDRESS(savings_max_row, COLUMN())))} -> 0 | AJ46: {=SUM(INDIRECT(ADDRESS(savings_min_row,COLUMN()) & ":" & ADDRESS(savings_max_row, COLUMN())))} -> 0 | AK46: {=SUM(INDIRECT(ADDRESS(savings_min_row,COLUMN()) & ":" & ADDRESS(savings_max_row, COLUMN())))} -> 0 | AL46: {=SUM(INDIRECT(ADDRESS(savings_min_row,COLUMN()) & ":" & ADDRESS(savings_max_row, COLUMN())))} -> 0 | AM46: {=SUM(INDIRECT(ADDRESS(savings_min_row,COLUMN()) & ":" & ADDRESS(savings_max_row, COLUMN())))} -> 0 | AN46: {=SUM(INDIRECT(ADDRESS(savings_min_row,COLUMN()) & ":" & ADDRESS(savings_max_row, COLUMN())))} -> 0 | ... AR46: {=SUM(INDIRECT(ADDRESS(savings_min_row,COLUMN()) & ":" & ADDRESS(savings_max_row, COLUMN())))} -> 0 | AS46: =SUM(AG46:AR46) -> 0 | AU46: {=SUM(INDIRECT(ADDRESS(savings_min_row,COLUMN()) & ":" & ADDRESS(savings_max_row, COLUMN())))} -> 0 | AV46: {=SUM(INDIRECT(ADDRESS(savings_min_row,COLUMN()) & ":" & ADDRESS(savings_max_row, COLUMN())))} -> 0 | AW46: {=SUM(INDIRECT(ADDRESS(savings_min_row,COLUMN()) & ":" & ADDRESS(savings_max_row, COLUMN())))} -> 0 | AX46: {=SUM(INDIRECT(ADDRESS(savings_min_row,COLUMN()) & ":" & ADDRESS(savings_max_row, COLUMN())))} -> 0 | AY46: {=SUM(INDIRECT(ADDRESS(savings_min_row,COLUMN()) & ":" & ADDRESS(savings_max_row, COLUMN())))} -> 0 | AZ46: {=SUM(INDIRECT(ADDRESS(savings_min_row,COLUMN()) & ":" & ADDRESS(savings_max_row, COLUMN())))} -> 0 | BA46: {=SUM(INDIRECT(ADDRESS(savings_min_row,COLUMN()) & ":" & ADDRESS(savings_max_row, COLUMN())))} -> 0 | BB46: {=SUM(INDIRECT(ADDRESS(savings_min_row,COLUMN()) & ":" & ADDRESS(savings_max_row, COLUMN())))} -> 0 | ... BF46: {=SUM(INDIRECT(ADDRESS(savings_min_row,COLUMN()) & ":" & ADDRESS(savings_max_row, COLUMN())))} -> 0 | BG46: =SUM(AU46:BF46) -> 0 | BI46: {=SUM(INDIRECT(ADDRESS(savings_min_row,COLUMN()) & ":" & ADDRESS(savings_max_row, COLUMN())))} -> 0 | BJ46: {=SUM(INDIRECT(ADDRESS(savings_min_row,COLUMN()) & ":" & ADDRESS(savings_max_row, COLUMN())))} -> 0 | BK46: {=SUM(INDIRECT(ADDRESS(savings_min_row,COLUMN()) & ":" & ADDRESS(savings_max_row, COLUMN())))} -> 0 | BL46: {=SUM(INDIRECT(ADDRESS(savings_min_row,COLUMN()) & ":" & ADDRESS(savings_max_row, COLUMN())))} -> 0 | BM46: {=SUM(INDIRECT(ADDRESS(savings_min_row,COLUMN()) & ":" & ADDRESS(savings_max_row, COLUMN())))} -> 0 | BN46: {=SUM(INDIRECT(ADDRESS(savings_min_row,COLUMN()) & ":" & ADDRESS(savings_max_row, COLUMN())))} -> 0 | BO46: {=SUM(INDIRECT(ADDRESS(savings_min_row,COLUMN()) & ":" & ADDRESS(savings_max_row, COLUMN())))} -> 0 | BP46: {=SUM(INDIRECT(ADDRESS(savings_min_row,COLUMN()) & ":" & ADDRESS(savings_max_row, COLUMN())))} -> 0 | ... BT46: {=SUM(INDIRECT(ADDRESS(savings_min_row,COLUMN()) & ":" & ADDRESS(savings_max_row, COLUMN())))} -> 0 | BU46: =SUM(BI46:BT46) -> 0 | BW46: {=SUM(INDIRECT(ADDRESS(savings_min_row,COLUMN()) & ":" & ADDRESS(savings_max_row, COLUMN())))} -> 0 | BX46: {=SUM(INDIRECT(ADDRESS(savings_min_row,COLUMN()) & ":" & ADDRESS(savings_max_row, COLUMN())))} -> 0 | BY46: {=SUM(INDIRECT(ADDRESS(savings_min_row,COLUMN()) & ":" & ADDRESS(savings_max_row, COLUMN())))} -> 0 | BZ46: {=SUM(INDIRECT(ADDRESS(savings_min_row,COLUMN()) & ":" & ADDRESS(savings_max_row, COLUMN())))} -> 0 | CA46: {=SUM(INDIRECT(ADDRESS(savings_min_row,COLUMN()) & ":" & ADDRESS(savings_max_row, COLUMN())))} -> 0 | CB46: {=SUM(INDIRECT(ADDRESS(savings_min_row,COLUMN()) & ":" & ADDRESS(savings_max_row, COLUMN())))} -> 0 | CC46: {=SUM(INDIRECT(ADDRESS(savings_min_row,COLUMN()) & ":" & ADDRESS(savings_max_row, COLUMN())))} -> 0 | CD46: {=SUM(INDIRECT(ADDRESS(savings_min_row,COLUMN()) & ":" & ADDRESS(savings_max_row, COLUMN())))} -> 0 | ... CH46: {=SUM(INDIRECT(ADDRESS(savings_min_row,COLUMN()) & ":" & ADDRESS(savings_max_row, COLUMN())))} -> 0 | CI46: =SUM(BW46:CH46) -> 0 | CK46: {=SUM(INDIRECT(ADDRESS(savings_min_row,COLUMN()) & ":" & ADDRESS(savings_max_row, COLUMN())))} -> 0 | CL46: {=SUM(INDIRECT(ADDRESS(savings_min_row,COLUMN()) & ":" & ADDRESS(savings_max_row, COLUMN())))} -> 0 | CM46: {=SUM(INDIRECT(ADDRESS(savings_min_row,COLUMN()) & ":" & ADDRESS(savings_max_row, COLUMN())))} -> 0 | CN46: {=SUM(INDIRECT(ADDRESS(savings_min_row,COLUMN()) & ":" & ADDRESS(savings_max_row, COLUMN())))} -> 0 | CO46: {=SUM(INDIRECT(ADDRESS(savings_min_row,COLUMN()) & ":" & ADDRESS(savings_max_row, COLUMN())))} -> 0 | CP46: {=SUM(INDIRECT(ADDRESS(savings_min_row,COLUMN()) & ":" & ADDRESS(savings_max_row, COLUMN())))} -> 0 | CQ46: {=SUM(INDIRECT(ADDRESS(savings_min_row,COLUMN()) & ":" & ADDRESS(savings_max_row, COLUMN())))} -> 0 | CR46: {=SUM(INDIRECT(ADDRESS(savings_min_row,COLUMN()) & ":" & ADDRESS(savings_max_row, COLUMN())))} -> 0 | ... CV46: {=SUM(INDIRECT(ADDRESS(savings_min_row,COLUMN()) & ":" & ADDRESS(savings_max_row, COLUMN())))} -> 0 | CW46: =SUM(CK46:CV46) -> 0 | CY46: {=SUM(INDIRECT(ADDRESS(savings_min_row,COLUMN()) & ":" & ADDRESS(savings_max_row, COLUMN())))} -> 0 | CZ46: {=SUM(INDIRECT(ADDRESS(savings_min_row,COLUMN()) & ":" & ADDRESS(savings_max_row, COLUMN())))} -> 0 | DA46: {=SUM(INDIRECT(ADDRESS(savings_min_row,COLUMN()) & ":" & ADDRESS(savings_max_row, COLUMN())))} -> 0 | DB46: {=SUM(INDIRECT(ADDRESS(savings_min_row,COLUMN()) & ":" & ADDRESS(savings_max_row, COLUMN())))} -> 0 | DC46: {=SUM(INDIRECT(ADDRESS(savings_min_row,COLUMN()) & ":" & ADDRESS(savings_max_row, COLUMN())))} -> 0 | DD46: {=SUM(INDIRECT(ADDRESS(savings_min_row,COLUMN()) & ":" & ADDRESS(savings_max_row, COLUMN())))} -> 0 | DE46: {=SUM(INDIRECT(ADDRESS(savings_min_row,COLUMN()) & ":" & ADDRESS(savings_max_row, COLUMN())))} -> 0 | DF46: {=SUM(INDIRECT(ADDRESS(savings_min_row,COLUMN()) & ":" & ADDRESS(savings_max_row, COLUMN())))} -> 0 | ... DJ46: {=SUM(INDIRECT(ADDRESS(savings_min_row,COLUMN()) & ":" & ADDRESS(savings_max_row, COLUMN())))} -> 0 | DK46: =SUM(CY46:DJ46) -> 0 | DM46: {=SUM(INDIRECT(ADDRESS(savings_min_row,COLUMN()) & ":" & ADDRESS(savings_max_row, COLUMN())))} -> 0 | DN46: {=SUM(INDIRECT(ADDRESS(savings_min_row,COLUMN()) & ":" & ADDRESS(savings_max_row, COLUMN())))} -> 0 | DO46: {=SUM(INDIRECT(ADDRESS(savings_min_row,COLUMN()) & ":" & ADDRESS(savings_max_row, COLUMN())))} -> 0 | DP46: {=SUM(INDIRECT(ADDRESS(savings_min_row,COLUMN()) & ":" & ADDRESS(savings_max_row, COLUMN())))} -> 0 | DQ46: {=SUM(INDIRECT(ADDRESS(savings_min_row,COLUMN()) & ":" & ADDRESS(savings_max_row, COLUMN())))} -> 0 | DR46: {=SUM(INDIRECT(ADDRESS(savings_min_row,COLUMN()) & ":" & ADDRESS(savings_max_row, COLUMN())))} -> 0 | DS46: {=SUM(INDIRECT(ADDRESS(savings_min_row,COLUMN()) & ":" & ADDRESS(savings_max_row, COLUMN())))} -> 0 | DT46: {=SUM(INDIRECT(ADDRESS(savings_min_row,COLUMN()) & ":" & ADDRESS(savings_max_row, COLUMN())))} -> 0 | ... DX46: {=SUM(INDIRECT(ADDRESS(savings_min_row,COLUMN()) & ":" & ADDRESS(savings_max_row, COLUMN())))} -> 0 | DY46: =SUM(DM46:DX46) -> 0

Sheet Budget_Tracking
B2: Budget Tracking
C11: Date | D11: Type | E11: Category | F11: Amount | G11: Details | H11: Balance | I11: Effective Date
C12: 44552 | D12: Income | E12: Employment(Net) | F12: 3500 | H12: {=SUMPRODUCT(Tracking[Amount],-- (Tracking[Date]<=Tracking[[#This Row],[Date]]), (Tracking[Type]<>"Income")*(-1)+(Tracking[Type]="Income"))} -> 3500 | I12: =IF(AND(Tracking[[#This Row],[Type]] = "Income", shift_late_income_status="Active", DAY(Tracking[[#This Row],[Date]])>=shift_late_income_starting_day), DATE(YEAR(Tracking[[#This Row],[Date]]), MONTH(Tracking[[#This Row],[Date]])+1,1),Tracking[[#This Row],[Date]]) -> 44562
C13: 44563 | D13: Expenses | E13: Housing | F13: 1200 | H13: {=SUMPRODUCT(Tracking[Amount],-- (Tracking[Date]<=Tracking[[#This Row],[Date]]), (Tracking[Type]<>"Income")*(-1)+(Tracking[Type]="Income"))} -> 2300 | I13: =IF(AND(Tracking[[#This Row],[Type]] = "Income", shift_late_income_status="Active", DAY(Tracking[[#This Row],[Date]])>=shift_late_income_starting_day), DATE(YEAR(Tracking[[#This Row],[Date]]), MONTH(Tracking[[#This Row],[Date]])+1,1),Tracking[[#This Row],[Date]]) -> 44563
C14: 44564 | D14: Expenses | E14: Clothing | F14: 150 | H14: {=SUMPRODUCT(Tracking[Amount],-- (Tracking[Date]<=Tracking[[#This Row],[Date]]), (Tracking[Type]<>"Income")*(-1)+(Tracking[Type]="Income"))} -> 2150 | I14: =IF(AND(Tracking[[#This Row],[Type]] = "Income", shift_late_income_status="Active", DAY(Tracking[[#This Row],[Date]])>=shift_late_income_starting_day), DATE(YEAR(Tracking[[#This Row],[Date]]), MONTH(Tracking[[#This Row],[Date]])+1,1),Tracking[[#This Row],[Date]]) -> 44564
C15: 44565 | D15: Savings | E15: Emergency Fund | F15: 1000 | H15: {=SUMPRODUCT(Tracking[Amount],-- (Tracking[Date]<=Tracking[[#This Row],[Date]]), (Tracking[Type]<>"Income")*(-1)+(Tracking[Type]="Income"))} -> 1150 | I15: =IF(AND(Tracking[[#This Row],[Type]] = "Income", shift_late_income_status="Active", DAY(Tracking[[#This Row],[Date]])>=shift_late_income_starting_day), DATE(YEAR(Tracking[[#This Row],[Date]]), MONTH(Tracking[[#This Row],[Date]])+1,1),Tracking[[#This Row],[Date]]) -> 44565
C16: 44566 | D16: Income | E16: Side Hustles(net) | F16: 500 | H16: {=SUMPRODUCT(Tracking[Amount],-- (Tracking[Date]<=Tracking[[#This Row],[Date]]), (Tracking[Type]<>"Income")*(-1)+(Tracking[Type]="Income"))} -> 1650 | I16: =IF(AND(Tracking[[#This Row],[Type]] = "Income", shift_late_income_status="Active", DAY(Tracking[[#This Row],[Date]])>=shift_late_income_starting_day), DATE(YEAR(Tracking[[#This Row],[Date]]), MONTH(Tracking[[#This Row],[Date]])+1,1),Tracking[[#This Row],[Date]]) -> 44566
C17: 44567 | D17: Expenses | E17: Groceries | F17: 200 | H17: {=SUMPRODUCT(Tracking[Amount],-- (Tracking[Date]<=Tracking[[#This Row],[Date]]), (Tracking[Type]<>"Income")*(-1)+(Tracking[Type]="Income"))} -> 1450 | I17: =IF(AND(Tracking[[#This Row],[Type]] = "Income", shift_late_income_status="Active", DAY(Tracking[[#This Row],[Date]])>=shift_late_income_starting_day), DATE(YEAR(Tracking[[#This Row],[Date]]), MONTH(Tracking[[#This Row],[Date]])+1,1),Tracking[[#This Row],[Date]]) -> 44567
C18: 44568 | D18: Expenses | E18: Transport | F18: 100 | H18: {=SUMPRODUCT(Tracking[Amount],-- (Tracking[Date]<=Tracking[[#This Row],[Date]]), (Tracking[Type]<>"Income")*(-1)+(Tracking[Type]="Income"))} -> 1350 | I18: =IF(AND(Tracking[[#This Row],[Type]] = "Income", shift_late_income_status="Active", DAY(Tracking[[#This Row],[Date]])>=shift_late_income_starting_day), DATE(YEAR(Tracking[[#This Row],[Date]]), MONTH(Tracking[[#This Row],[Date]])+1,1),Tracking[[#This Row],[Date]]) -> 44568
C19: 44569 | D19: Savings | E19: Retirement Account | F19: 500 | H19: {=SUMPRODUCT(Tracking[Amount],-- (Tracking[Date]<=Tracking[[#This Row],[Date]]), (Tracking[Type]<>"Income")*(-1)+(Tracking[Type]="Income"))} -> 850 | I19: =IF(AND(Tracking[[#This Row],[Type]] = "Income", shift_late_income_status="Active", DAY(Tracking[[#This Row],[Date]])>=shift_late_income_starting_day), DATE(YEAR(Tracking[[#This Row],[Date]]), MONTH(Tracking[[#This Row],[Date]])+1,1),Tracking[[#This Row],[Date]]) -> 44569
C20: 44570 | D20: Expenses | E20: Groceries | F20: 500 | H20: {=SUMPRODUCT(Tracking[Amount],-- (Tracking[Date]<=Tracking[[#This Row],[Date]]), (Tracking[Type]<>"Income")*(-1)+(Tracking[Type]="Income"))} -> 350 | I20: =IF(AND(Tracking[[#This Row],[Type]] = "Income", shift_late_income_status="Active", DAY(Tracking[[#This Row],[Date]])>=shift_late_income_starting_day), DATE(YEAR(Tracking[[#This Row],[Date]]), MONTH(Tracking[[#This Row],[Date]])+1,1),Tracking[[#This Row],[Date]]) -> 44570
C21: 44571 | D21: Expenses | E21: Transport | F21: 200 | H21: {=SUMPRODUCT(Tracking[Amount],-- (Tracking[Date]<=Tracking[[#This Row],[Date]]), (Tracking[Type]<>"Income")*(-1)+(Tracking[Type]="Income"))} -> 150 | I21: =IF(AND(Tracking[[#This Row],[Type]] = "Income", shift_late_income_status="Active", DAY(Tracking[[#This Row],[Date]])>=shift_late_income_starting_day), DATE(YEAR(Tracking[[#This Row],[Date]]), MONTH(Tracking[[#This Row],[Date]])+1,1),Tracking[[#This Row],[Date]]) -> 44571
C22: 44573 | D22: Income | E22: Side Hustles(net) | F22: 500 | H22: {=SUMPRODUCT(Tracking[Amount],-- (Tracking[Date]<=Tracking[[#This Row],[Date]]), (Tracking[Type]<>"Income")*(-1)+(Tracking[Type]="Income"))} -> 650 | I22: =IF(AND(Tracking[[#This Row],[Type]] = "Income", shift_late_income_status="Active", DAY(Tracking[[#This Row],[Date]])>=shift_late_income_starting_day), DATE(YEAR(Tracking[[#This Row],[Date]]), MONTH(Tracking[[#This Row],[Date]])+1,1),Tracking[[#This Row],[Date]]) -> 44573
C23: 44574 | D23: Income | E23: Employment(Net) | F23: 1000 | H23: {=SUMPRODUCT(Tracking[Amount],-- (Tracking[Date]<=Tracking[[#This Row],[Date]]), (Tracking[Type]<>"Income")*(-1)+(Tracking[Type]="Income"))} -> 1650 | I23: =IF(AND(Tracking[[#This Row],[Type]] = "Income", shift_late_income_status="Active", DAY(Tracking[[#This Row],[Date]])>=shift_late_income_starting_day), DATE(YEAR(Tracking[[#This Row],[Date]]), MONTH(Tracking[[#This Row],[Date]])+1,1),Tracking[[#This Row],[Date]]) -> 44574
... C56: 44635 | D56: Savings | E56: Stock Portfolio | F56: 300 | H56: {=SUMPRODUCT(Tracking[Amount],-- (Tracking[Date]<=Tracking[[#This Row],[Date]]), (Tracking[Type]<>"Income")*(-1)+(Tracking[Type]="Income"))} -> 130 | I56: =IF(AND(Tracking[[#This Row],[Type]] = "Income", shift_late_income_status="Active", DAY(Tracking[[#This Row],[Date]])>=shift_late_income_starting_day), DATE(YEAR(Tracking[[#This Row],[Date]]), MONTH(Tracking[[#This Row],[Date]])+1,1),Tracking[[#This Row],[Date]]) -> 44635

Sheet Budget_Dashboard
B2: Budget Dashboard
AL5: Year | AQ5: Period
AJ6: Select Year-> | AL6: 2022 | AO6: Select period-> | AQ6: Total Year
Y8: ="Breakdown-"& IF(Selected_period="Total Year",Selected_Year&"(Total Year)",selected_period_display&""& Selected_Year) -> Breakdown-2022(Total Year) | AF8: ="Summary-"& IF(Selected_period="Total Year",Selected_Year&"(Total Year)",selected_period_display&""& Selected_Year) -> Summary-2022(Total Year)
C9: row_id | D9: header_row_id | E9: is_header | F9: is_cat | G9: is_total | H9: is_empty | I9: type | J9: item | K9: tracked | L9: budget | M9: sort_min_row | N9: sort_max_row | O9: tracked_range | P9: tracked_rank | Q9: budget_range | R9: budget_rank | S9: comb_rank | T9: comb_rank_range | U9: comb_rank_norm | V9: comb_rank_norm_run_range | W9: comb_rank_unique | X9: sorted_row_id[Lookup]
C10: 9 | D10: =IF(is_header,row_id, IF(NOT(is_empty),D9,-1)) -> 9 | E10: {=1*OR(row_id=income_header_row,row_id=expenses_header_row,row_id=Savings_header_row)} -> 1 | F10: =1*NOT(OR(is_header,is_total,is_empty)) -> 0 | G10: {=1*OR(row_id=income_total_row,row_id=expenses_total_row,row_id=savings_total_row)} -> 0 | H10: =1*OR(row_id="/1",row_id="/2",row_id=-1) -> 0 | I10: {=IFERROR(INDEX(Budget_Planning!$C:$C,header_row_id), " ")} -> Income | J10: {=IFERROR(INDEX(Budget_Planning!$C:$C,row_id), " ")} -> Income | K10: {=IF(OR(is_header,is_empty),"", IF(is_total, IF(Selected_period="Total Year", SUM(Tracking[Amount]*(Tracking[Type]=type)*(YEAR(Tracking[Effective Date])=Selected_Year) ), SUM(Tracking[Amount]*(Tracking[Type]=type)*(YEAR(Tracking[Effective Date])=Selected_Year) * (MONTH(Tracking[Effective Date])=Selected_period))), IF(Selected_period="Total Year", SUM(Tracking[Amount]*(Tracking[Type]=type)*(Tracking[Category]=item)*(YEAR(Tracking[Effective Date])=Selected_Year)), SUM(Tracking[Amount]*(Tracking[Type]=type)*(Tracking[Category]=item)*(YEAR(Tracking[Effective Date])=Selected_Year) * (MONTH(Tracking[Effective Date])=Selected_period)) )))} | L10: {=IF(OR(is_header,is_empty),"", INDEX(Budget_Planning!$E:$DY,row_id, MATCH(IF(Selected_period="Total Year",Selected_Year,DATE(Selected_Year,Selected_period,1)), Budget_Planning!$E$9:$DY$9, 0)))} | N10: {=IF(is_cat, IF(header_row_id=income_header_row, MATCH(income_max_row,$C:$C,0), IF(header_row_id=expenses_header_row,MATCH(expenses_max_row,$C:$C,0), IF(header_row_id=Savings_header_row,MATCH(savings_max_row,$C:$C,0),""))), "")} | O10: =IF(is_cat,ADDRESS(sort_min_row,COLUMN(tracked)) &":" & ADDRESS(sort_max_row,COLUMN(tracked)), "") | P10: =IF(is_cat,RANK(tracked,INDIRECT(tracked_range),0), "") | Q10: =IF(is_cat,ADDRESS(sort_min_row,COLUMN(budget)) & ":" &ADDRESS(sort_max_row,COLUMN(budget)), "") | R10: =IF(is_cat,RANK(budget,INDIRECT(budget_range),0),"") | S10: =IF(is_cat,_xlfn.NUMBERVALUE(tracked_rank& budget_rank),"") | U10: =IF(is_cat,RANK(comb_rank,INDIRECT(comb_rank_range),1),"") | V10: =IF(is_cat,ADDRESS(sort_min_row,COLUMN(comb_rank_norm)) & ":" &ADDRESS(ROW(),COLUMN(comb_rank_norm)), "") | W10: =IF(is_cat,comb_rank_norm+ COUNTIF(INDIRECT(comb_rank_norm_run_range),comb_rank_norm)-1,"") | X10: =IF(is_cat,header_row_id+comb_rank_unique,row_id) -> 9 | Y10: =IF(is_empty,"",INDEX($J:$J,MATCH(row_id,$X:$X,0))) -> Income | Z10: =IF(is_empty,"",IF(is_header,"Tracked",INDEX($K:$K, MATCH(row_id,$X:$X,0)))) -> Tracked | AA10: =IF(is_empty,"",IF(is_header,"Budget",INDEX($L:$L, MATCH(row_id,$X:$X,0)))) -> Budget | AB10: =IF(is_empty,"",IF(is_header,"%Compl.",IFERROR(out_tracked/out_budget,"-"))) -> %Compl. | AC10: =IF(is_empty,"",IF(is_header,"Remaining",IF(out_budget-out_tracked > 0, out_budget-out_tracked,0))) -> Remaining | AD10: =IF(is_empty,"",IF(is_header,"Excess",IF(out_budget-out_tracked < 0, out_tracked-out_budget,0))) -> Excess
C11: {=IF(C10=-1,-1, IF(C10<income_max_row,C10+1, IF(C10=income_max_row,income_total_row, IF(C10=income_total_row, "/1", IF(C10="/1",expenses_header_row, IF(C10<expenses_max_row, C10+1, IF(C10=expenses_max_row,expenses_total_row, IF(C10=expenses_total_row,"/2", IF(C10="/2",Savings_header_row, IF(C10<savings_max_row,C10+1, IF(C10=savings_max_row,savings_total_row, -1)))))))))))} -> 10 | D11: =IF(is_header,row_id, IF(NOT(is_empty),D10,-1)) -> 9 | E11: {=1*OR(row_id=income_header_row,row_id=expenses_header_row,row_id=Savings_header_row)} -> 0 | F11: =1*NOT(OR(is_header,is_total,is_empty)) -> 1 | G11: {=1*OR(row_id=income_total_row,row_id=expenses_total_row,row_id=savings_total_row)} -> 0 | H11: =1*OR(row_id="/1",row_id="/2",row_id=-1) -> 0 | I11: {=IFERROR(INDEX(Budget_Planning!$C:$C,header_row_id), " ")} -> Income | J11: {=IFERROR(INDEX(Budget_Planning!$C:$C,row_id), " ")} -> Employment(Net) | K11: {=IF(OR(is_header,is_empty),"", IF(is_total, IF(Selected_period="Total Year", SUM(Tracking[Amount]*(Tracking[Type]=type)*(YEAR(Tracking[Effective Date])=Selected_Year) ), SUM(Tracking[Amount]*(Tracking[Type]=type)*(YEAR(Tracking[Effective Date])=Selected_Year) * (MONTH(Tracking[Effective Date])=Selected_period))), IF(Selected_period="Total Year", SUM(Tracking[Amount]*(Tracking[Type]=type)*(Tracking[Category]=item)*(YEAR(Tracking[Effective Date])=Selected_Year)), SUM(Tracking[Amount]*(Tracking[Type]=type)*(Tracking[Category]=item)*(YEAR(Tracking[Effective Date])=Selected_Year) * (MONTH(Tracking[Effective Date])=Selected_period)) )))} -> 6500 | L11: {=IF(OR(is_header,is_empty),"", INDEX(Budget_Planning!$E:$DY,row_id, MATCH(IF(Selected_period="Total Year",Selected_Year,DATE(Selected_Year,Selected_period,1)), Budget_Planning!$E$9:$DY$9, 0)))} -> 51000 | M11: {=IF(is_cat, IF(header_row_id=income_header_row, MATCH(income_min_row,$C:$C,0), IF(header_row_id=expenses_header_row,MATCH(expenses_min_row,$C:$C,0), IF(header_row_id=Savings_header_row,MATCH(savings_min_row,$C:$C,0),""))), "")} -> 11 | N11: {=IF(is_cat, IF(header_row_id=income_header_row, MATCH(income_max_row,$C:$C,0), IF(header_row_id=expenses_header_row,MATCH(expenses_max_row,$C:$C,0), IF(header_row_id=Savings_header_row,MATCH(savings_max_row,$C:$C,0),""))), "")} -> 13 | O11: =IF(is_cat,ADDRESS(sort_min_row,COLUMN(tracked)) &":" & ADDRESS(sort_max_row,COLUMN(tracked)), "") -> $K$11:$K$13 | P11: =IF(is_cat,RANK(tracked,INDIRECT(tracked_range),0), "") -> 1 | Q11: =IF(is_cat,ADDRESS(sort_min_row,COLUMN(budget)) & ":" &ADDRESS(sort_max_row,COLUMN(budget)), "") -> $L$11:$L$13 | R11: =IF(is_cat,RANK(budget,INDIRECT(budget_range),0),"") -> 1 | S11: =IF(is_cat,_xlfn.NUMBERVALUE(tracked_rank& budget_rank),"") -> 11 | T11: =IF(is_cat,ADDRESS(sort_min_row,COLUMN(comb_rank)) & ":" &ADDRESS(sort_max_row,COLUMN(comb_rank)), "") -> $S$11:$S$13 | U11: =IF(is_cat,RANK(comb_rank,INDIRECT(comb_rank_range),1),"") -> 1 | V11: =IF(is_cat,ADDRESS(sort_min_row,COLUMN(comb_rank_norm)) & ":" &ADDRESS(ROW(),COLUMN(comb_rank_norm)), "") -> $U$11:$U$11 | W11: =IF(is_cat,comb_rank_norm+ COUNTIF(INDIRECT(comb_rank_norm_run_range),comb_rank_norm)-1,"") -> 1 | X11: =IF(is_cat,header_row_id+comb_rank_unique,row_id) -> 10 | Y11: =IF(is_empty,"",INDEX($J:$J,MATCH(row_id,$X:$X,0))) -> Employment(Net) | Z11: =IF(is_empty,"",IF(is_header,"Tracked",INDEX($K:$K, MATCH(row_id,$X:$X,0)))) -> 6500 | AA11: =IF(is_empty,"",IF(is_header,"Budget",INDEX($L:$L, MATCH(row_id,$X:$X,0)))) -> 51000 | AB11: =IF(is_empty,"",IF(is_header,"%Compl.",IFERROR(out_tracked/out_budget,"-"))) -> 0.12745098 | AC11: =IF(is_empty,"",IF(is_header,"Remaining",IF(out_budget-out_tracked > 0, out_budget-out_tracked,0))) -> 44500 | AD11: =IF(is_empty,"",IF(is_header,"Excess",IF(out_budget-out_tracked < 0, out_tracked-out_budget,0))) -> 0
C12: {=IF(C11=-1,-1, IF(C11<income_max_row,C11+1, IF(C11=income_max_row,income_total_row, IF(C11=income_total_row, "/1", IF(C11="/1",expenses_header_row, IF(C11<expenses_max_row, C11+1, IF(C11=expenses_max_row,expenses_total_row, IF(C11=expenses_total_row,"/2", IF(C11="/2",Savings_header_row, IF(C11<savings_max_row,C11+1, IF(C11=savings_max_row,savings_total_row, -1)))))))))))} -> 11 | D12: =IF(is_header,row_id, IF(NOT(is_empty),D11,-1)) -> 9 | E12: {=1*OR(row_id=income_header_row,row_id=expenses_header_row,row_id=Savings_header_row)} -> 0 | F12: =1*NOT(OR(is_header,is_total,is_empty)) -> 1 | G12: {=1*OR(row_id=income_total_row,row_id=expenses_total_row,row_id=savings_total_row)} -> 0 | H12: =1*OR(row_id="/1",row_id="/2",row_id=-1) -> 0 | I12: {=IFERROR(INDEX(Budget_Planning!$C:$C,header_row_id), " ")} -> Income | J12: {=IFERROR(INDEX(Budget_Planning!$C:$C,row_id), " ")} -> Side Hustles(net) | K12: {=IF(OR(is_header,is_empty),"", IF(is_total, IF(Selected_period="Total Year", SUM(Tracking[Amount]*(Tracking[Type]=type)*(YEAR(Tracking[Effective Date])=Selected_Year) ), SUM(Tracking[Amount]*(Tracking[Type]=type)*(YEAR(Tracking[Effective Date])=Selected_Year) * (MONTH(Tracking[Effective Date])=Selected_period))), IF(Selected_period="Total Year", SUM(Tracking[Amount]*(Tracking[Type]=type)*(Tracking[Category]=item)*(YEAR(Tracking[Effective Date])=Selected_Year)), SUM(Tracking[Amount]*(Tracking[Type]=type)*(Tracking[Category]=item)*(YEAR(Tracking[Effective Date])=Selected_Year) * (MONTH(Tracking[Effective Date])=Selected_period)) )))} -> 4500 | L12: {=IF(OR(is_header,is_empty),"", INDEX(Budget_Planning!$E:$DY,row_id, MATCH(IF(Selected_period="Total Year",Selected_Year,DATE(Selected_Year,Selected_period,1)), Budget_Planning!$E$9:$DY$9, 0)))} -> 12000 | M12: {=IF(is_cat, IF(header_row_id=income_header_row, MATCH(income_min_row,$C:$C,0), IF(header_row_id=expenses_header_row,MATCH(expenses_min_row,$C:$C,0), IF(header_row_id=Savings_header_row,MATCH(savings_min_row,$C:$C,0),""))), "")} -> 11 | N12: {=IF(is_cat, IF(header_row_id=income_header_row, MATCH(income_max_row,$C:$C,0), IF(header_row_id=expenses_header_row,MATCH(expenses_max_row,$C:$C,0), IF(header_row_id=Savings_header_row,MATCH(savings_max_row,$C:$C,0),""))), "")} -> 13 | O12: =IF(is_cat,ADDRESS(sort_min_row,COLUMN(tracked)) &":" & ADDRESS(sort_max_row,COLUMN(tracked)), "") -> $K$11:$K$13 | P12: =IF(is_cat,RANK(tracked,INDIRECT(tracked_range),0), "") -> 2 | Q12: =IF(is_cat,ADDRESS(sort_min_row,COLUMN(budget)) & ":" &ADDRESS(sort_max_row,COLUMN(budget)), "") -> $L$11:$L$13 | R12: =IF(is_cat,RANK(budget,INDIRECT(budget_range),0),"") -> 2 | S12: =IF(is_cat,_xlfn.NUMBERVALUE(tracked_rank& budget_rank),"") -> 22 | T12: =IF(is_cat,ADDRESS(sort_min_row,COLUMN(comb_rank)) & ":" &ADDRESS(sort_max_row,COLUMN(comb_rank)), "") -> $S$11:$S$13 | U12: =IF(is_cat,RANK(comb_rank,INDIRECT(comb_rank_range),1),"") -> 2 | V12: =IF(is_cat,ADDRESS(sort_min_row,COLUMN(comb_rank_norm)) & ":" &ADDRESS(ROW(),COLUMN(comb_rank_norm)), "") -> $U$11:$U$12 | W12: =IF(is_cat,comb_rank_norm+ COUNTIF(INDIRECT(comb_rank_norm_run_range),comb_rank_norm)-1,"") -> 2 | X12: =IF(is_cat,header_row_id+comb_rank_unique,row_id) -> 11 | Y12: =IF(is_empty,"",INDEX($J:$J,MATCH(row_id,$X:$X,0))) -> Side Hustles(net) | Z12: =IF(is_empty,"",IF(is_header,"Tracked",INDEX($K:$K, MATCH(row_id,$X:$X,0)))) -> 4500 | AA12: =IF(is_empty,"",IF(is_header,"Budget",INDEX($L:$L, MATCH(row_id,$X:$X,0)))) -> 12000 | AB12: =IF(is_empty,"",IF(is_header,"%Compl.",IFERROR(out_tracked/out_budget,"-"))) -> 0.375 | AC12: =IF(is_empty,"",IF(is_header,"Remaining",IF(out_budget-out_tracked > 0, out_budget-out_tracked,0))) -> 7500 | AD12: =IF(is_empty,"",IF(is_header,"Excess",IF(out_budget-out_tracked < 0, out_tracked-out_budget,0))) -> 0 | AI12: =Calculations!E35 -> Employment(Net) | AJ12: =Calculations!F35 -> 6500
C13: {=IF(C12=-1,-1, IF(C12<income_max_row,C12+1, IF(C12=income_max_row,income_total_row, IF(C12=income_total_row, "/1", IF(C12="/1",expenses_header_row, IF(C12<expenses_max_row, C12+1, IF(C12=expenses_max_row,expenses_total_row, IF(C12=expenses_total_row,"/2", IF(C12="/2",Savings_header_row, IF(C12<savings_max_row,C12+1, IF(C12=savings_max_row,savings_total_row, -1)))))))))))} -> 12 | D13: =IF(is_header,row_id, IF(NOT(is_empty),D12,-1)) -> 9 | E13: {=1*OR(row_id=income_header_row,row_id=expenses_header_row,row_id=Savings_header_row)} -> 0 | F13: =1*NOT(OR(is_header,is_total,is_empty)) -> 1 | G13: {=1*OR(row_id=income_total_row,row_id=expenses_total_row,row_id=savings_total_row)} -> 0 | H13: =1*OR(row_id="/1",row_id="/2",row_id=-1) -> 0 | I13: {=IFERROR(INDEX(Budget_Planning!$C:$C,header_row_id), " ")} -> Income | J13: {=IFERROR(INDEX(Budget_Planning!$C:$C,row_id), " ")} -> Dividends | K13: {=IF(OR(is_header,is_empty),"", IF(is_total, IF(Selected_period="Total Year", SUM(Tracking[Amount]*(Tracking[Type]=type)*(YEAR(Tracking[Effective Date])=Selected_Year) ), SUM(Tracking[Amount]*(Tracking[Type]=type)*(YEAR(Tracking[Effective Date])=Selected_Year) * (MONTH(Tracking[Effective Date])=Selected_period))), IF(Selected_period="Total Year", SUM(Tracking[Amount]*(Tracking[Type]=type)*(Tracking[Category]=item)*(YEAR(Tracking[Effective Date])=Selected_Year)), SUM(Tracking[Amount]*(Tracking[Type]=type)*(Tracking[Category]=item)*(YEAR(Tracking[Effective Date])=Selected_Year) * (MONTH(Tracking[Effective Date])=Selected_period)) )))} -> 350 | L13: {=IF(OR(is_header,is_empty),"", INDEX(Budget_Planning!$E:$DY,row_id, MATCH(IF(Selected_period="Total Year",Selected_Year,DATE(Selected_Year,Selected_period,1)), Budget_Planning!$E$9:$DY$9, 0)))} -> 1200 | M13: {=IF(is_cat, IF(header_row_id=income_header_row, MATCH(income_min_row,$C:$C,0), IF(header_row_id=expenses_header_row,MATCH(expenses_min_row,$C:$C,0), IF(header_row_id=Savings_header_row,MATCH(savings_min_row,$C:$C,0),""))), "")} -> 11 | N13: {=IF(is_cat, IF(header_row_id=income_header_row, MATCH(income_max_row,$C:$C,0), IF(header_row_id=expenses_header_row,MATCH(expenses_max_row,$C:$C,0), IF(header_row_id=Savings_header_row,MATCH(savings_max_row,$C:$C,0),""))), "")} -> 13 | O13: =IF(is_cat,ADDRESS(sort_min_row,COLUMN(tracked)) &":" & ADDRESS(sort_max_row,COLUMN(tracked)), "") -> $K$11:$K$13 | P13: =IF(is_cat,RANK(tracked,INDIRECT(tracked_range),0), "") -> 3 | Q13: =IF(is_cat,ADDRESS(sort_min_row,COLUMN(budget)) & ":" &ADDRESS(sort_max_row,COLUMN(budget)), "") -> $L$11:$L$13 | R13: =IF(is_cat,RANK(budget,INDIRECT(budget_range),0),"") -> 3 | S13: =IF(is_cat,_xlfn.NUMBERVALUE(tracked_rank& budget_rank),"") -> 33 | T13: =IF(is_cat,ADDRESS(sort_min_row,COLUMN(comb_rank)) & ":" &ADDRESS(sort_max_row,COLUMN(comb_rank)), "") -> $S$11:$S$13 | U13: =IF(is_cat,RANK(comb_rank,INDIRECT(comb_rank_range),1),"") -> 3 | V13: =IF(is_cat,ADDRESS(sort_min_row,COLUMN(comb_rank_norm)) & ":" &ADDRESS(ROW(),COLUMN(comb_rank_norm)), "") -> $U$11:$U$13 | W13: =IF(is_cat,comb_rank_norm+ COUNTIF(INDIRECT(comb_rank_norm_run_range),comb_rank_norm)-1,"") -> 3 | X13: =IF(is_cat,header_row_id+comb_rank_unique,row_id) -> 12 | Y13: =IF(is_empty,"",INDEX($J:$J,MATCH(row_id,$X:$X,0))) -> Dividends | Z13: =IF(is_empty,"",IF(is_header,"Tracked",INDEX($K:$K, MATCH(row_id,$X:$X,0)))) -> 350 | AA13: =IF(is_empty,"",IF(is_header,"Budget",INDEX($L:$L, MATCH(row_id,$X:$X,0)))) -> 1200 | AB13: =IF(is_empty,"",IF(is_header,"%Compl.",IFERROR(out_tracked/out_budget,"-"))) -> 0.29166667 | AC13: =IF(is_empty,"",IF(is_header,"Remaining",IF(out_budget-out_tracked > 0, out_budget-out_tracked,0))) -> 850 | AD13: =IF(is_empty,"",IF(is_header,"Excess",IF(out_budget-out_tracked < 0, out_tracked-out_budget,0))) -> 0 | AI13: =Calculations!E36 -> Side Hustles(net) | AJ13: =Calculations!F36 -> 4500
C14: {=IF(C13=-1,-1, IF(C13<income_max_row,C13+1, IF(C13=income_max_row,income_total_row, IF(C13=income_total_row, "/1", IF(C13="/1",expenses_header_row, IF(C13<expenses_max_row, C13+1, IF(C13=expenses_max_row,expenses_total_row, IF(C13=expenses_total_row,"/2", IF(C13="/2",Savings_header_row, IF(C13<savings_max_row,C13+1, IF(C13=savings_max_row,savings_total_row, -1)))))))))))} -> 20 | D14: =IF(is_header,row_id, IF(NOT(is_empty),D13,-1)) -> 9 | E14: {=1*OR(row_id=income_header_row,row_id=expenses_header_row,row_id=Savings_header_row)} -> 0 | F14: =1*NOT(OR(is_header,is_total,is_empty)) -> 0 | G14: {=1*OR(row_id=income_total_row,row_id=expenses_total_row,row_id=savings_total_row)} -> 1 | H14: =1*OR(row_id="/1",row_id="/2",row_id=-1) -> 0 | I14: {=IFERROR(INDEX(Budget_Planning!$C:$C,header_row_id), " ")} -> Income | J14: {=IFERROR(INDEX(Budget_Planning!$C:$C,row_id), " ")} -> Total | K14: {=IF(OR(is_header,is_empty),"", IF(is_total, IF(Selected_period="Total Year", SUM(Tracking[Amount]*(Tracking[Type]=type)*(YEAR(Tracking[Effective Date])=Selected_Year) ), SUM(Tracking[Amount]*(Tracking[Type]=type)*(YEAR(Tracking[Effective Date])=Selected_Year) * (MONTH(Tracking[Effective Date])=Selected_period))), IF(Selected_period="Total Year", SUM(Tracking[Amount]*(Tracking[Type]=type)*(Tracking[Category]=item)*(YEAR(Tracking[Effective Date])=Selected_Year)), SUM(Tracking[Amount]*(Tracking[Type]=type)*(Tracking[Category]=item)*(YEAR(Tracking[Effective Date])=Selected_Year) * (MONTH(Tracking[Effective Date])=Selected_period)) )))} -> 11350 | L14: {=IF(OR(is_header,is_empty),"", INDEX(Budget_Planning!$E:$DY,row_id, MATCH(IF(Selected_period="Total Year",Selected_Year,DATE(Selected_Year,Selected_period,1)), Budget_Planning!$E$9:$DY$9, 0)))} -> 64200 | M14: {=IF(is_cat, IF(header_row_id=income_header_row, MATCH(income_min_row,$C:$C,0), IF(header_row_id=expenses_header_row,MATCH(expenses_min_row,$C:$C,0), IF(header_row_id=Savings_header_row,MATCH(savings_min_row,$C:$C,0),""))), "")} | N14: {=IF(is_cat, IF(header_row_id=income_header_row, MATCH(income_max_row,$C:$C,0), IF(header_row_id=expenses_header_row,MATCH(expenses_max_row,$C:$C,0), IF(header_row_id=Savings_header_row,MATCH(savings_max_row,$C:$C,0),""))), "")} | O14: =IF(is_cat,ADDRESS(sort_min_row,COLUMN(tracked)) &":" & ADDRESS(sort_max_row,COLUMN(tracked)), "") | P14: =IF(is_cat,RANK(tracked,INDIRECT(tracked_range),0), "") | Q14: =IF(is_cat,ADDRESS(sort_min_row,COLUMN(budget)) & ":" &ADDRESS(sort_max_row,COLUMN(budget)), "") | R14: =IF(is_cat,RANK(budget,INDIRECT(budget_range),0),"") | S14: =IF(is_cat,_xlfn.NUMBERVALUE(tracked_rank& budget_rank),"") | T14: =IF(is_cat,ADDRESS(sort_min_row,COLUMN(comb_rank)) & ":" &ADDRESS(sort_max_row,COLUMN(comb_rank)), "") | U14: =IF(is_cat,RANK(comb_rank,INDIRECT(comb_rank_range),1),"") | V14: =IF(is_cat,ADDRESS(sort_min_row,COLUMN(comb_rank_norm)) & ":" &ADDRESS(ROW(),COLUMN(comb_rank_norm)), "") | W14: =IF(is_cat,comb_rank_norm+ COUNTIF(INDIRECT(comb_rank_norm_run_range),comb_rank_norm)-1,"") | X14: =IF(is_cat,header_row_id+comb_rank_unique,row_id) -> 20 | Y14: =IF(is_empty,"",INDEX($J:$J,MATCH(row_id,$X:$X,0))) -> Total | Z14: =IF(is_empty,"",IF(is_header,"Tracked",INDEX($K:$K, MATCH(row_id,$X:$X,0)))) -> 11350 | AA14: =IF(is_empty,"",IF(is_header,"Budget",INDEX($L:$L, MATCH(row_id,$X:$X,0)))) -> 64200 | AB14: =IF(is_empty,"",IF(is_header,"%Compl.",IFERROR(out_tracked/out_budget,"-"))) -> 0.17679128 | AC14: =IF(is_empty,"",IF(is_header,"Remaining",IF(out_budget-out_tracked > 0, out_budget-out_tracked,0))) -> 52850 | AD14: =IF(is_empty,"",IF(is_header,"Excess",IF(out_budget-out_tracked < 0, out_tracked-out_budget,0))) -> 0 | AI14: =Calculations!E37 -> Dividends | AJ14: =Calculations!F37 -> 350
C15: {=IF(C14=-1,-1, IF(C14<income_max_row,C14+1, IF(C14=income_max_row,income_total_row, IF(C14=income_total_row, "/1", IF(C14="/1",expenses_header_row, IF(C14<expenses_max_row, C14+1, IF(C14=expenses_max_row,expenses_total_row, IF(C14=expenses_total_row,"/2", IF(C14="/2",Savings_header_row, IF(C14<savings_max_row,C14+1, IF(C14=savings_max_row,savings_total_row, -1)))))))))))} -> /1 | D15: =IF(is_header,row_id, IF(NOT(is_empty),D14,-1)) -> -1 | E15: {=1*OR(row_id=income_header_row,row_id=expenses_header_row,row_id=Savings_header_row)} -> 0 | F15: =1*NOT(OR(is_header,is_total,is_empty)) -> 0 | G15: {=1*OR(row_id=income_total_row,row_id=expenses_total_row,row_id=savings_total_row)} -> 0 | H15: =1*OR(row_id="/1",row_id="/2",row_id=-1) -> 1 | I15: {=IFERROR(INDEX(Budget_Planning!$C:$C,header_row_id), " ")} | J15: {=IFERROR(INDEX(Budget_Planning!$C:$C,row_id), " ")} | K15: {=IF(OR(is_header,is_empty),"", IF(is_total, IF(Selected_period="Total Year", SUM(Tracking[Amount]*(Tracking[Type]=type)*(YEAR(Tracking[Effective Date])=Selected_Year) ), SUM(Tracking[Amount]*(Tracking[Type]=type)*(YEAR(Tracking[Effective Date])=Selected_Year) * (MONTH(Tracking[Effective Date])=Selected_period))), IF(Selected_period="Total Year", SUM(Tracking[Amount]*(Tracking[Type]=type)*(Tracking[Category]=item)*(YEAR(Tracking[Effective Date])=Selected_Year)), SUM(Tracking[Amount]*(Tracking[Type]=type)*(Tracking[Category]=item)*(YEAR(Tracking[Effective Date])=Selected_Year) * (MONTH(Tracking[Effective Date])=Selected_period)) )))} | L15: {=IF(OR(is_header,is_empty),"", INDEX(Budget_Planning!$E:$DY,row_id, MATCH(IF(Selected_period="Total Year",Selected_Year,DATE(Selected_Year,Selected_period,1)), Budget_Planning!$E$9:$DY$9, 0)))} | M15: {=IF(is_cat, IF(header_row_id=income_header_row, MATCH(income_min_row,$C:$C,0), IF(header_row_id=expenses_header_row,MATCH(expenses_min_row,$C:$C,0), IF(header_row_id=Savings_header_row,MATCH(savings_min_row,$C:$C,0),""))), "")} | N15: {=IF(is_cat, IF(header_row_id=income_header_row, MATCH(income_max_row,$C:$C,0), IF(header_row_id=expenses_header_row,MATCH(expenses_max_row,$C:$C,0), IF(header_row_id=Savings_header_row,MATCH(savings_max_row,$C:$C,0),""))), "")} | O15: =IF(is_cat,ADDRESS(sort_min_row,COLUMN(tracked)) &":" & ADDRESS(sort_max_row,COLUMN(tracked)), "") | P15: =IF(is_cat,RANK(tracked,INDIRECT(tracked_range),0), "") | Q15: =IF(is_cat,ADDRESS(sort_min_row,COLUMN(budget)) & ":" &ADDRESS(sort_max_row,COLUMN(budget)), "") | R15: =IF(is_cat,RANK(budget,INDIRECT(budget_range),0),"") | S15: =IF(is_cat,_xlfn.NUMBERVALUE(tracked_rank& budget_rank),"") | T15: =IF(is_cat,ADDRESS(sort_min_row,COLUMN(comb_rank)) & ":" &ADDRESS(sort_max_row,COLUMN(comb_rank)), "") | U15: =IF(is_cat,RANK(comb_rank,INDIRECT(comb_rank_range),1),"") | V15: =IF(is_cat,ADDRESS(sort_min_row,COLUMN(comb_rank_norm)) & ":" &ADDRESS(ROW(),COLUMN(comb_rank_norm)), "") | W15: =IF(is_cat,comb_rank_norm+ COUNTIF(INDIRECT(comb_rank_norm_run_range),comb_rank_norm)-1,"") | X15: =IF(is_cat,header_row_id+comb_rank_unique,row_id) -> /1 | Y15: =IF(is_empty,"",INDEX($J:$J,MATCH(row_id,$X:$X,0))) | Z15: =IF(is_empty,"",IF(is_header,"Tracked",INDEX($K:$K, MATCH(row_id,$X:$X,0)))) | AA15: =IF(is_empty,"",IF(is_header,"Budget",INDEX($L:$L, MATCH(row_id,$X:$X,0)))) | AB15: =IF(is_empty,"",IF(is_header,"%Compl.",IFERROR(out_tracked/out_budget,"-"))) | AC15: =IF(is_empty,"",IF(is_header,"Remaining",IF(out_budget-out_tracked > 0, out_budget-out_tracked,0))) | AD15: =IF(is_empty,"",IF(is_header,"Excess",IF(out_budget-out_tracked < 0, out_tracked-out_budget,0))) | AI15: =Calculations!E38 | AJ15: =Calculations!F38
C16: {=IF(C15=-1,-1, IF(C15<income_max_row,C15+1, IF(C15=income_max_row,income_total_row, IF(C15=income_total_row, "/1", IF(C15="/1",expenses_header_row, IF(C15<expenses_max_row, C15+1, IF(C15=expenses_max_row,expenses_total_row, IF(C15=expenses_total_row,"/2", IF(C15="/2",Savings_header_row, IF(C15<savings_max_row,C15+1, IF(C15=savings_max_row,savings_total_row, -1)))))))))))} -> 22 | D16: =IF(is_header,row_id, IF(NOT(is_empty),D15,-1)) -> 22 | E16: {=1*OR(row_id=income_header_row,row_id=expenses_header_row,row_id=Savings_header_row)} -> 1 | F16: =1*NOT(OR(is_header,is_total,is_empty)) -> 0 | G16: {=1*OR(row_id=income_total_row,row_id=expenses_total_row,row_id=savings_total_row)} -> 0 | H16: =1*OR(row_id="/1",row_id="/2",row_id=-1) -> 0 | I16: {=IFERROR(INDEX(Budget_Planning!$C:$C,header_row_id), " ")} -> Expenses | J16: {=IFERROR(INDEX(Budget_Planning!$C:$C,row_id), " ")} -> Expenses | K16: {=IF(OR(is_header,is_empty),"", IF(is_total, IF(Selected_period="Total Year", SUM(Tracking[Amount]*(Tracking[Type]=type)*(YEAR(Tracking[Effective Date])=Selected_Year) ), SUM(Tracking[Amount]*(Tracking[Type]=type)*(YEAR(Tracking[Effective Date])=Selected_Year) * (MONTH(Tracking[Effective Date])=Selected_period))), IF(Selected_period="Total Year", SUM(Tracking[Amount]*(Tracking[Type]=type)*(Tracking[Category]=item)*(YEAR(Tracking[Effective Date])=Selected_Year)), SUM(Tracking[Amount]*(Tracking[Type]=type)*(Tracking[Category]=item)*(YEAR(Tracking[Effective Date])=Selected_Year) * (MONTH(Tracking[Effective Date])=Selected_period)) )))} | L16: {=IF(OR(is_header,is_empty),"", INDEX(Budget_Planning!$E:$DY,row_id, MATCH(IF(Selected_period="Total Year",Selected_Year,DATE(Selected_Year,Selected_period,1)), Budget_Planning!$E$9:$DY$9, 0)))} | M16: {=IF(is_cat, IF(header_row_id=income_header_row, MATCH(income_min_row,$C:$C,0), IF(header_row_id=expenses_header_row,MATCH(expenses_min_row,$C:$C,0), IF(header_row_id=Savings_header_row,MATCH(savings_min_row,$C:$C,0),""))), "")} | N16: {=IF(is_cat, IF(header_row_id=income_header_row, MATCH(income_max_row,$C:$C,0), IF(header_row_id=expenses_header_row,MATCH(expenses_max_row,$C:$C,0), IF(header_row_id=Savings_header_row,MATCH(savings_max_row,$C:$C,0),""))), "")} | O16: =IF(is_cat,ADDRESS(sort_min_row,COLUMN(tracked)) &":" & ADDRESS(sort_max_row,COLUMN(tracked)), "") | P16: =IF(is_cat,RANK(tracked,INDIRECT(tracked_range),0), "") | Q16: =IF(is_cat,ADDRESS(sort_min_row,COLUMN(budget)) & ":" &ADDRESS(sort_max_row,COLUMN(budget)), "") | R16: =IF(is_cat,RANK(budget,INDIRECT(budget_range),0),"") | S16: =IF(is_cat,_xlfn.NUMBERVALUE(tracked_rank& budget_rank),"") | T16: =IF(is_cat,ADDRESS(sort_min_row,COLUMN(comb_rank)) & ":" &ADDRESS(sort_max_row,COLUMN(comb_rank)), "") | U16: =IF(is_cat,RANK(comb_rank,INDIRECT(comb_rank_range),1),"") | V16: =IF(is_cat,ADDRESS(sort_min_row,COLUMN(comb_rank_norm)) & ":" &ADDRESS(ROW(),COLUMN(comb_rank_norm)), "") | W16: =IF(is_cat,comb_rank_norm+ COUNTIF(INDIRECT(comb_rank_norm_run_range),comb_rank_norm)-1,"") | X16: =IF(is_cat,header_row_id+comb_rank_unique,row_id) -> 22 | Y16: =IF(is_empty,"",INDEX($J:$J,MATCH(row_id,$X:$X,0))) -> Expenses | Z16: =IF(is_empty,"",IF(is_header,"Tracked",INDEX($K:$K, MATCH(row_id,$X:$X,0)))) -> Tracked | AA16: =IF(is_empty,"",IF(is_header,"Budget",INDEX($L:$L, MATCH(row_id,$X:$X,0)))) -> Budget | AB16: =IF(is_empty,"",IF(is_header,"%Compl.",IFERROR(out_tracked/out_budget,"-"))) -> %Compl. | AC16: =IF(is_empty,"",IF(is_header,"Remaining",IF(out_budget-out_tracked > 0, out_budget-out_tracked,0))) -> Remaining | AD16: =IF(is_empty,"",IF(is_header,"Excess",IF(out_budget-out_tracked < 0, out_tracked-out_budget,0))) -> Excess | AI16: =Calculations!E39 | AJ16: =Calculations!F39
C17: {=IF(C16=-1,-1, IF(C16<income_max_row,C16+1, IF(C16=income_max_row,income_total_row, IF(C16=income_total_row, "/1", IF(C16="/1",expenses_header_row, IF(C16<expenses_max_row, C16+1, IF(C16=expenses_max_row,expenses_total_row, IF(C16=expenses_total_row,"/2", IF(C16="/2",Savings_header_row, IF(C16<savings_max_row,C16+1, IF(C16=savings_max_row,savings_total_row, -1)))))))))))} -> 23 | D17: =IF(is_header,row_id, IF(NOT(is_empty),D16,-1)) -> 22 | E17: {=1*OR(row_id=income_header_row,row_id=expenses_header_row,row_id=Savings_header_row)} -> 0 | F17: =1*NOT(OR(is_header,is_total,is_empty)) -> 1 | G17: {=1*OR(row_id=income_total_row,row_id=expenses_total_row,row_id=savings_total_row)} -> 0 | H17: =1*OR(row_id="/1",row_id="/2",row_id=-1) -> 0 | I17: {=IFERROR(INDEX(Budget_Planning!$C:$C,header_row_id), " ")} -> Expenses | J17: {=IFERROR(INDEX(Budget_Planning!$C:$C,row_id), " ")} -> Housing | K17: {=IF(OR(is_header,is_empty),"", IF(is_total, IF(Selected_period="Total Year", SUM(Tracking[Amount]*(Tracking[Type]=type)*(YEAR(Tracking[Effective Date])=Selected_Year) ), SUM(Tracking[Amount]*(Tracking[Type]=type)*(YEAR(Tracking[Effective Date])=Selected_Year) * (MONTH(Tracking[Effective Date])=Selected_period))), IF(Selected_period="Total Year", SUM(Tracking[Amount]*(Tracking[Type]=type)*(Tracking[Category]=item)*(YEAR(Tracking[Effective Date])=Selected_Year)), SUM(Tracking[Amount]*(Tracking[Type]=type)*(Tracking[Category]=item)*(YEAR(Tracking[Effective Date])=Selected_Year) * (MONTH(Tracking[Effective Date])=Selected_period)) )))} -> 1800 | L17: {=IF(OR(is_header,is_empty),"", INDEX(Budget_Planning!$E:$DY,row_id, MATCH(IF(Selected_period="Total Year",Selected_Year,DATE(Selected_Year,Selected_period,1)), Budget_Planning!$E$9:$DY$9, 0)))} -> 14400 | M17: {=IF(is_cat, IF(header_row_id=income_header_row, MATCH(income_min_row,$C:$C,0), IF(header_row_id=expenses_header_row,MATCH(expenses_min_row,$C:$C,0), IF(header_row_id=Savings_header_row,MATCH(savings_min_row,$C:$C,0),""))), "")} -> 17 | N17: {=IF(is_cat, IF(header_row_id=income_header_row, MATCH(income_max_row,$C:$C,0), IF(header_row_id=expenses_header_row,MATCH(expenses_max_row,$C:$C,0), IF(header_row_id=Savings_header_row,MATCH(savings_max_row,$C:$C,0),""))), "")} -> 25 | O17: =IF(is_cat,ADDRESS(sort_min_row,COLUMN(tracked)) &":" & ADDRESS(sort_max_row,COLUMN(tracked)), "") -> $K$17:$K$25 | P17: =IF(is_cat,RANK(tracked,INDIRECT(tracked_range),0), "") -> 2 | Q17: =IF(is_cat,ADDRESS(sort_min_row,COLUMN(budget)) & ":" &ADDRESS(sort_max_row,COLUMN(budget)), "") -> $L$17:$L$25 | R17: =IF(is_cat,RANK(budget,INDIRECT(budget_range),0),"") -> 1 | S17: =IF(is_cat,_xlfn.NUMBERVALUE(tracked_rank& budget_rank),"") -> 21 | T17: =IF(is_cat,ADDRESS(sort_min_row,COLUMN(comb_rank)) & ":" &ADDRESS(sort_max_row,COLUMN(comb_rank)), "") -> $S$17:$S$25 | U17: =IF(is_cat,RANK(comb_rank,INDIRECT(comb_rank_range),1),"") -> 2 | V17: =IF(is_cat,ADDRESS(sort_min_row,COLUMN(comb_rank_norm)) & ":" &ADDRESS(ROW(),COLUMN(comb_rank_norm)), "") -> $U$17:$U$17 | W17: =IF(is_cat,comb_rank_norm+ COUNTIF(INDIRECT(comb_rank_norm_run_range),comb_rank_norm)-1,"") -> 2 | X17: =IF(is_cat,header_row_id+comb_rank_unique,row_id) -> 24 | Y17: =IF(is_empty,"",INDEX($J:$J,MATCH(row_id,$X:$X,0))) -> Groceries | Z17: =IF(is_empty,"",IF(is_header,"Tracked",INDEX($K:$K, MATCH(row_id,$X:$X,0)))) -> 2300 | AA17: =IF(is_empty,"",IF(is_header,"Budget",INDEX($L:$L, MATCH(row_id,$X:$X,0)))) -> 4200 | AB17: =IF(is_empty,"",IF(is_header,"%Compl.",IFERROR(out_tracked/out_budget,"-"))) -> 0.54761905 | AC17: =IF(is_empty,"",IF(is_header,"Remaining",IF(out_budget-out_tracked > 0, out_budget-out_tracked,0))) -> 1900 | AD17: =IF(is_empty,"",IF(is_header,"Excess",IF(out_budget-out_tracked < 0, out_tracked-out_budget,0))) -> 0 | AI17: =Calculations!E40 -> 0 | AJ17: =Calculations!F40
C18: {=IF(C17=-1,-1, IF(C17<income_max_row,C17+1, IF(C17=income_max_row,income_total_row, IF(C17=income_total_row, "/1", IF(C17="/1",expenses_header_row, IF(C17<expenses_max_row, C17+1, IF(C17=expenses_max_row,expenses_total_row, IF(C17=expenses_total_row,"/2", IF(C17="/2",Savings_header_row, IF(C17<savings_max_row,C17+1, IF(C17=savings_max_row,savings_total_row, -1)))))))))))} -> 24 | D18: =IF(is_header,row_id, IF(NOT(is_empty),D17,-1)) -> 22 | E18: {=1*OR(row_id=income_header_row,row_id=expenses_header_row,row_id=Savings_header_row)} -> 0 | F18: =1*NOT(OR(is_header,is_total,is_empty)) -> 1 | G18: {=1*OR(row_id=income_total_row,row_id=expenses_total_row,row_id=savings_total_row)} -> 0 | H18: =1*OR(row_id="/1",row_id="/2",row_id=-1) -> 0 | I18: {=IFERROR(INDEX(Budget_Planning!$C:$C,header_row_id), " ")} -> Expenses | J18: {=IFERROR(INDEX(Budget_Planning!$C:$C,row_id), " ")} -> Utilities | K18: {=IF(OR(is_header,is_empty),"", IF(is_total, IF(Selected_period="Total Year", SUM(Tracking[Amount]*(Tracking[Type]=type)*(YEAR(Tracking[Effective Date])=Selected_Year) ), SUM(Tracking[Amount]*(Tracking[Type]=type)*(YEAR(Tracking[Effective Date])=Selected_Year) * (MONTH(Tracking[Effective Date])=Selected_period))), IF(Selected_period="Total Year", SUM(Tracking[Amount]*(Tracking[Type]=type)*(Tracking[Category]=item)*(YEAR(Tracking[Effective Date])=Selected_Year)), SUM(Tracking[Amount]*(Tracking[Type]=type)*(Tracking[Category]=item)*(YEAR(Tracking[Effective Date])=Selected_Year) * (MONTH(Tracking[Effective Date])=Selected_period)) )))} -> 1400 | L18: {=IF(OR(is_header,is_empty),"", INDEX(Budget_Planning!$E:$DY,row_id, MATCH(IF(Selected_period="Total Year",Selected_Year,DATE(Selected_Year,Selected_period,1)), Budget_Planning!$E$9:$DY$9, 0)))} -> 3600 | M18: {=IF(is_cat, IF(header_row_id=income_header_row, MATCH(income_min_row,$C:$C,0), IF(header_row_id=expenses_header_row,MATCH(expenses_min_row,$C:$C,0), IF(header_row_id=Savings_header_row,MATCH(savings_min_row,$C:$C,0),""))), "")} -> 17 | N18: {=IF(is_cat, IF(header_row_id=income_header_row, MATCH(income_max_row,$C:$C,0), IF(header_row_id=expenses_header_row,MATCH(expenses_max_row,$C:$C,0), IF(header_row_id=Savings_header_row,MATCH(savings_max_row,$C:$C,0),""))), "")} -> 25 | O18: =IF(is_cat,ADDRESS(sort_min_row,COLUMN(tracked)) &":" & ADDRESS(sort_max_row,COLUMN(tracked)), "") -> $K$17:$K$25 | P18: =IF(is_cat,RANK(tracked,INDIRECT(tracked_range),0), "") -> 3 | Q18: =IF(is_cat,ADDRESS(sort_min_row,COLUMN(budget)) & ":" &ADDRESS(sort_max_row,COLUMN(budget)), "") -> $L$17:$L$25 | R18: =IF(is_cat,RANK(budget,INDIRECT(budget_range),0),"") -> 4 | S18: =IF(is_cat,_xlfn.NUMBERVALUE(tracked_rank& budget_rank),"") -> 34 | T18: =IF(is_cat,ADDRESS(sort_min_row,COLUMN(comb_rank)) & ":" &ADDRESS(sort_max_row,COLUMN(comb_rank)), "") -> $S$17:$S$25 | U18: =IF(is_cat,RANK(comb_rank,INDIRECT(comb_rank_range),1),"") -> 3 | V18: =IF(is_cat,ADDRESS(sort_min_row,COLUMN(comb_rank_norm)) & ":" &ADDRESS(ROW(),COLUMN(comb_rank_norm)), "") -> $U$17:$U$18 | W18: =IF(is_cat,comb_rank_norm+ COUNTIF(INDIRECT(comb_rank_norm_run_range),comb_rank_norm)-1,"") -> 3 | X18: =IF(is_cat,header_row_id+comb_rank_unique,row_id) -> 25 | Y18: =IF(is_empty,"",INDEX($J:$J,MATCH(row_id,$X:$X,0))) -> Housing | Z18: =IF(is_empty,"",IF(is_header,"Tracked",INDEX($K:$K, MATCH(row_id,$X:$X,0)))) -> 1800 | AA18: =IF(is_empty,"",IF(is_header,"Budget",INDEX($L:$L, MATCH(row_id,$X:$X,0)))) -> 14400 | AB18: =IF(is_empty,"",IF(is_header,"%Compl.",IFERROR(out_tracked/out_budget,"-"))) -> 0.125 | AC18: =IF(is_empty,"",IF(is_header,"Remaining",IF(out_budget-out_tracked > 0, out_budget-out_tracked,0))) -> 12600 | AD18: =IF(is_empty,"",IF(is_header,"Excess",IF(out_budget-out_tracked < 0, out_tracked-out_budget,0))) -> 0 | AI18: =Calculations!E41 -> Total | AJ18: =Calculations!F41 -> 11350
C19: {=IF(C18=-1,-1, IF(C18<income_max_row,C18+1, IF(C18=income_max_row,income_total_row, IF(C18=income_total_row, "/1", IF(C18="/1",expenses_header_row, IF(C18<expenses_max_row, C18+1, IF(C18=expenses_max_row,expenses_total_row, IF(C18=expenses_total_row,"/2", IF(C18="/2",Savings_header_row, IF(C18<savings_max_row,C18+1, IF(C18=savings_max_row,savings_total_row, -1)))))))))))} -> 25 | D19: =IF(is_header,row_id, IF(NOT(is_empty),D18,-1)) -> 22 | E19: {=1*OR(row_id=income_header_row,row_id=expenses_header_row,row_id=Savings_header_row)} -> 0 | F19: =1*NOT(OR(is_header,is_total,is_empty)) -> 1 | G19: {=1*OR(row_id=income_total_row,row_id=expenses_total_row,row_id=savings_total_row)} -> 0 | H19: =1*OR(row_id="/1",row_id="/2",row_id=-1) -> 0 | I19: {=IFERROR(INDEX(Budget_Planning!$C:$C,header_row_id), " ")} -> Expenses | J19: {=IFERROR(INDEX(Budget_Planning!$C:$C,row_id), " ")} -> Groceries | K19: {=IF(OR(is_header,is_empty),"", IF(is_total, IF(Selected_period="Total Year", SUM(Tracking[Amount]*(Tracking[Type]=type)*(YEAR(Tracking[Effective Date])=Selected_Year) ), SUM(Tracking[Amount]*(Tracking[Type]=type)*(YEAR(Tracking[Effective Date])=Selected_Year) * (MONTH(Tracking[Effective Date])=Selected_period))), IF(Selected_period="Total Year", SUM(Tracking[Amount]*(Tracking[Type]=type)*(Tracking[Category]=item)*(YEAR(Tracking[Effective Date])=Selected_Year)), SUM(Tracking[Amount]*(Tracking[Type]=type)*(Tracking[Category]=item)*(YEAR(Tracking[Effective Date])=Selected_Year) * (MONTH(Tracking[Effective Date])=Selected_period)) )))} -> 2300 | L19: {=IF(OR(is_header,is_empty),"", INDEX(Budget_Planning!$E:$DY,row_id, MATCH(IF(Selected_period="Total Year",Selected_Year,DATE(Selected_Year,Selected_period,1)), Budget_Planning!$E$9:$DY$9, 0)))} -> 4200 | M19: {=IF(is_cat, IF(header_row_id=income_header_row, MATCH(income_min_row,$C:$C,0), IF(header_row_id=expenses_header_row,MATCH(expenses_min_row,$C:$C,0), IF(header_row_id=Savings_header_row,MATCH(savings_min_row,$C:$C,0),""))), "")} -> 17 | N19: {=IF(is_cat, IF(header_row_id=income_header_row, MATCH(income_max_row,$C:$C,0), IF(header_row_id=expenses_header_row,MATCH(expenses_max_row,$C:$C,0), IF(header_row_id=Savings_header_row,MATCH(savings_max_row,$C:$C,0),""))), "")} -> 25 | O19: =IF(is_cat,ADDRESS(sort_min_row,COLUMN(tracked)) &":" & ADDRESS(sort_max_row,COLUMN(tracked)), "") -> $K$17:$K$25 | P19: =IF(is_cat,RANK(tracked,INDIRECT(tracked_range),0), "") -> 1 | Q19: =IF(is_cat,ADDRESS(sort_min_row,COLUMN(budget)) & ":" &ADDRESS(sort_max_row,COLUMN(budget)), "") -> $L$17:$L$25 | R19: =IF(is_cat,RANK(budget,INDIRECT(budget_range),0),"") -> 3 | S19: =IF(is_cat,_xlfn.NUMBERVALUE(tracked_rank& budget_rank),"") -> 13 | T19: =IF(is_cat,ADDRESS(sort_min_row,COLUMN(comb_rank)) & ":" &ADDRESS(sort_max_row,COLUMN(comb_rank)), "") -> $S$17:$S$25 | U19: =IF(is_cat,RANK(comb_rank,INDIRECT(comb_rank_range),1),"") -> 1 | V19: =IF(is_cat,ADDRESS(sort_min_row,COLUMN(comb_rank_norm)) & ":" &ADDRESS(ROW(),COLUMN(comb_rank_norm)), "") -> $U$17:$U$19 | W19: =IF(is_cat,comb_rank_norm+ COUNTIF(INDIRECT(comb_rank_norm_run_range),comb_rank_norm)-1,"") -> 1 | X19: =IF(is_cat,header_row_id+comb_rank_unique,row_id) -> 23 | Y19: =IF(is_empty,"",INDEX($J:$J,MATCH(row_id,$X:$X,0))) -> Utilities | Z19: =IF(is_empty,"",IF(is_header,"Tracked",INDEX($K:$K, MATCH(row_id,$X:$X,0)))) -> 1400 | AA19: =IF(is_empty,"",IF(is_header,"Budget",INDEX($L:$L, MATCH(row_id,$X:$X,0)))) -> 3600 | AB19: =IF(is_empty,"",IF(is_header,"%Compl.",IFERROR(out_tracked/out_budget,"-"))) -> 0.38888889 | AC19: =IF(is_empty,"",IF(is_header,"Remaining",IF(out_budget-out_tracked > 0, out_budget-out_tracked,0))) -> 2200 | AD19: =IF(is_empty,"",IF(is_header,"Excess",IF(out_budget-out_tracked < 0, out_tracked-out_budget,0))) -> 0
C20: {=IF(C19=-1,-1, IF(C19<income_max_row,C19+1, IF(C19=income_max_row,income_total_row, IF(C19=income_total_row, "/1", IF(C19="/1",expenses_header_row, IF(C19<expenses_max_row, C19+1, IF(C19=expenses_max_row,expenses_total_row, IF(C19=expenses_total_row,"/2", IF(C19="/2",Savings_header_row, IF(C19<savings_max_row,C19+1, IF(C19=savings_max_row,savings_total_row, -1)))))))))))} -> 26 | D20: =IF(is_header,row_id, IF(NOT(is_empty),D19,-1)) -> 22 | E20: {=1*OR(row_id=income_header_row,row_id=expenses_header_row,row_id=Savings_header_row)} -> 0 | F20: =1*NOT(OR(is_header,is_total,is_empty)) -> 1 | G20: {=1*OR(row_id=income_total_row,row_id=expenses_total_row,row_id=savings_total_row)} -> 0 | H20: =1*OR(row_id="/1",row_id="/2",row_id=-1) -> 0 | I20: {=IFERROR(INDEX(Budget_Planning!$C:$C,header_row_id), " ")} -> Expenses | J20: {=IFERROR(INDEX(Budget_Planning!$C:$C,row_id), " ")} -> Transport | K20: {=IF(OR(is_header,is_empty),"", IF(is_total, IF(Selected_period="Total Year", SUM(Tracking[Amount]*(Tracking[Type]=type)*(YEAR(Tracking[Effective Date])=Selected_Year) ), SUM(Tracking[Amount]*(Tracking[Type]=type)*(YEAR(Tracking[Effective Date])=Selected_Year) * (MONTH(Tracking[Effective Date])=Selected_period))), IF(Selected_period="Total Year", SUM(Tracking[Amount]*(Tracking[Type]=type)*(Tracking[Category]=item)*(YEAR(Tracking[Effective Date])=Selected_Year)), SUM(Tracking[Amount]*(Tracking[Type]=type)*(Tracking[Category]=item)*(YEAR(Tracking[Effective Date])=Selected_Year) * (MONTH(Tracking[Effective Date])=Selected_period)) )))} -> 800 | L20: {=IF(OR(is_header,is_empty),"", INDEX(Budget_Planning!$E:$DY,row_id, MATCH(IF(Selected_period="Total Year",Selected_Year,DATE(Selected_Year,Selected_period,1)), Budget_Planning!$E$9:$DY$9, 0)))} -> 3600 | M20: {=IF(is_cat, IF(header_row_id=income_header_row, MATCH(income_min_row,$C:$C,0), IF(header_row_id=expenses_header_row,MATCH(expenses_min_row,$C:$C,0), IF(header_row_id=Savings_header_row,MATCH(savings_min_row,$C:$C,0),""))), "")} -> 17 | N20: {=IF(is_cat, IF(header_row_id=income_header_row, MATCH(income_max_row,$C:$C,0), IF(header_row_id=expenses_header_row,MATCH(expenses_max_row,$C:$C,0), IF(header_row_id=Savings_header_row,MATCH(savings_max_row,$C:$C,0),""))), "")} -> 25 | O20: =IF(is_cat,ADDRESS(sort_min_row,COLUMN(tracked)) &":" & ADDRESS(sort_max_row,COLUMN(tracked)), "") -> $K$17:$K$25 | P20: =IF(is_cat,RANK(tracked,INDIRECT(tracked_range),0), "") -> 5 | Q20: =IF(is_cat,ADDRESS(sort_min_row,COLUMN(budget)) & ":" &ADDRESS(sort_max_row,COLUMN(budget)), "") -> $L$17:$L$25 | R20: =IF(is_cat,RANK(budget,INDIRECT(budget_range),0),"") -> 4 | S20: =IF(is_cat,_xlfn.NUMBERVALUE(tracked_rank& budget_rank),"") -> 54 | T20: =IF(is_cat,ADDRESS(sort_min_row,COLUMN(comb_rank)) & ":" &ADDRESS(sort_max_row,COLUMN(comb_rank)), "") -> $S$17:$S$25 | U20: =IF(is_cat,RANK(comb_rank,INDIRECT(comb_rank_range),1),"") -> 5 | V20: =IF(is_cat,ADDRESS(sort_min_row,COLUMN(comb_rank_norm)) & ":" &ADDRESS(ROW(),COLUMN(comb_rank_norm)), "") -> $U$17:$U$20 | W20: =IF(is_cat,comb_rank_norm+ COUNTIF(INDIRECT(comb_rank_norm_run_range),comb_rank_norm)-1,"") -> 5 | X20: =IF(is_cat,header_row_id+comb_rank_unique,row_id) -> 27 | Y20: =IF(is_empty,"",INDEX($J:$J,MATCH(row_id,$X:$X,0))) -> Body care | Z20: =IF(is_empty,"",IF(is_header,"Tracked",INDEX($K:$K, MATCH(row_id,$X:$X,0)))) -> 970 | AA20: =IF(is_empty,"",IF(is_header,"Budget",INDEX($L:$L, MATCH(row_id,$X:$X,0)))) -> 2400 | AB20: =IF(is_empty,"",IF(is_header,"%Compl.",IFERROR(out_tracked/out_budget,"-"))) -> 0.40416667 | AC20: =IF(is_empty,"",IF(is_header,"Remaining",IF(out_budget-out_tracked > 0, out_budget-out_tracked,0))) -> 1430 | AD20: =IF(is_empty,"",IF(is_header,"Excess",IF(out_budget-out_tracked < 0, out_tracked-out_budget,0))) -> 0
C21: {=IF(C20=-1,-1, IF(C20<income_max_row,C20+1, IF(C20=income_max_row,income_total_row, IF(C20=income_total_row, "/1", IF(C20="/1",expenses_header_row, IF(C20<expenses_max_row, C20+1, IF(C20=expenses_max_row,expenses_total_row, IF(C20=expenses_total_row,"/2", IF(C20="/2",Savings_header_row, IF(C20<savings_max_row,C20+1, IF(C20=savings_max_row,savings_total_row, -1)))))))))))} -> 27 | D21: =IF(is_header,row_id, IF(NOT(is_empty),D20,-1)) -> 22 | E21: {=1*OR(row_id=income_header_row,row_id=expenses_header_row,row_id=Savings_header_row)} -> 0 | F21: =1*NOT(OR(is_header,is_total,is_empty)) -> 1 | G21: {=1*OR(row_id=income_total_row,row_id=expenses_total_row,row_id=savings_total_row)} -> 0 | H21: =1*OR(row_id="/1",row_id="/2",row_id=-1) -> 0 | I21: {=IFERROR(INDEX(Budget_Planning!$C:$C,header_row_id), " ")} -> Expenses | J21: {=IFERROR(INDEX(Budget_Planning!$C:$C,row_id), " ")} -> Insurance | K21: {=IF(OR(is_header,is_empty),"", IF(is_total, IF(Selected_period="Total Year", SUM(Tracking[Amount]*(Tracking[Type]=type)*(YEAR(Tracking[Effective Date])=Selected_Year) ), SUM(Tracking[Amount]*(Tracking[Type]=type)*(YEAR(Tracking[Effective Date])=Selected_Year) * (MONTH(Tracking[Effective Date])=Selected_period))), IF(Selected_period="Total Year", SUM(Tracking[Amount]*(Tracking[Type]=type)*(Tracking[Category]=item)*(YEAR(Tracking[Effective Date])=Selected_Year)), SUM(Tracking[Amount]*(Tracking[Type]=type)*(Tracking[Category]=item)*(YEAR(Tracking[Effective Date])=Selected_Year) * (MONTH(Tracking[Effective Date])=Selected_period)) )))} -> 600 | L21: {=IF(OR(is_header,is_empty),"", INDEX(Budget_Planning!$E:$DY,row_id, MATCH(IF(Selected_period="Total Year",Selected_Year,DATE(Selected_Year,Selected_period,1)), Budget_Planning!$E$9:$DY$9, 0)))} -> 600 | M21: {=IF(is_cat, IF(header_row_id=income_header_row, MATCH(income_min_row,$C:$C,0), IF(header_row_id=expenses_header_row,MATCH(expenses_min_row,$C:$C,0), IF(header_row_id=Savings_header_row,MATCH(savings_min_row,$C:$C,0),""))), "")} -> 17 | N21: {=IF(is_cat, IF(header_row_id=income_header_row, MATCH(income_max_row,$C:$C,0), IF(header_row_id=expenses_header_row,MATCH(expenses_max_row,$C:$C,0), IF(header_row_id=Savings_header_row,MATCH(savings_max_row,$C:$C,0),""))), "")} -> 25 | O21: =IF(is_cat,ADDRESS(sort_min_row,COLUMN(tracked)) &":" & ADDRESS(sort_max_row,COLUMN(tracked)), "") -> $K$17:$K$25 | P21: =IF(is_cat,RANK(tracked,INDIRECT(tracked_range),0), "") -> 6 | Q21: =IF(is_cat,ADDRESS(sort_min_row,COLUMN(budget)) & ":" &ADDRESS(sort_max_row,COLUMN(budget)), "") -> $L$17:$L$25 | R21: =IF(is_cat,RANK(budget,INDIRECT(budget_range),0),"") -> 8 | S21: =IF(is_cat,_xlfn.NUMBERVALUE(tracked_rank& budget_rank),"") -> 68 | T21: =IF(is_cat,ADDRESS(sort_min_row,COLUMN(comb_rank)) & ":" &ADDRESS(sort_max_row,COLUMN(comb_rank)), "") -> $S$17:$S$25 | U21: =IF(is_cat,RANK(comb_rank,INDIRECT(comb_rank_range),1),"") -> 6 | V21: =IF(is_cat,ADDRESS(sort_min_row,COLUMN(comb_rank_norm)) & ":" &ADDRESS(ROW(),COLUMN(comb_rank_norm)), "") -> $U$17:$U$21 | W21: =IF(is_cat,comb_rank_norm+ COUNTIF(INDIRECT(comb_rank_norm_run_range),comb_rank_norm)-1,"") -> 6 | X21: =IF(is_cat,header_row_id+comb_rank_unique,row_id) -> 28 | Y21: =IF(is_empty,"",INDEX($J:$J,MATCH(row_id,$X:$X,0))) -> Transport | Z21: =IF(is_empty,"",IF(is_header,"Tracked",INDEX($K:$K, MATCH(row_id,$X:$X,0)))) -> 800 | AA21: =IF(is_empty,"",IF(is_header,"Budget",INDEX($L:$L, MATCH(row_id,$X:$X,0)))) -> 3600 | AB21: =IF(is_empty,"",IF(is_header,"%Compl.",IFERROR(out_tracked/out_budget,"-"))) -> 0.22222222 | AC21: =IF(is_empty,"",IF(is_header,"Remaining",IF(out_budget-out_tracked > 0, out_budget-out_tracked,0))) -> 2800 | AD21: =IF(is_empty,"",IF(is_header,"Excess",IF(out_budget-out_tracked < 0, out_tracked-out_budget,0))) -> 0
C22: {=IF(C21=-1,-1, IF(C21<income_max_row,C21+1, IF(C21=income_max_row,income_total_row, IF(C21=income_total_row, "/1", IF(C21="/1",expenses_header_row, IF(C21<expenses_max_row, C21+1, IF(C21=expenses_max_row,expenses_total_row, IF(C21=expenses_total_row,"/2", IF(C21="/2",Savings_header_row, IF(C21<savings_max_row,C21+1, IF(C21=savings_max_row,savings_total_row, -1)))))))))))} -> 28 | D22: =IF(is_header,row_id, IF(NOT(is_empty),D21,-1)) -> 22 | E22: {=1*OR(row_id=income_header_row,row_id=expenses_header_row,row_id=Savings_header_row)} -> 0 | F22: =1*NOT(OR(is_header,is_total,is_empty)) -> 1 | G22: {=1*OR(row_id=income_total_row,row_id=expenses_total_row,row_id=savings_total_row)} -> 0 | H22: =1*OR(row_id="/1",row_id="/2",row_id=-1) -> 0 | I22: {=IFERROR(INDEX(Budget_Planning!$C:$C,header_row_id), " ")} -> Expenses | J22: {=IFERROR(INDEX(Budget_Planning!$C:$C,row_id), " ")} -> Clothing | K22: {=IF(OR(is_header,is_empty),"", IF(is_total, IF(Selected_period="Total Year", SUM(Tracking[Amount]*(Tracking[Type]=type)*(YEAR(Tracking[Effective Date])=Selected_Year) ), SUM(Tracking[Amount]*(Tracking[Type]=type)*(YEAR(Tracking[Effective Date])=Selected_Year) * (MONTH(Tracking[Effective Date])=Selected_period))), IF(Selected_period="Total Year", SUM(Tracking[Amount]*(Tracking[Type]=type)*(Tracking[Category]=item)*(YEAR(Tracking[Effective Date])=Selected_Year)), SUM(Tracking[Amount]*(Tracking[Type]=type)*(Tracking[Category]=item)*(YEAR(Tracking[Effective Date])=Selected_Year) * (MONTH(Tracking[Effective Date])=Selected_period)) )))} -> 400 | L22: {=IF(OR(is_header,is_empty),"", INDEX(Budget_Planning!$E:$DY,row_id, MATCH(IF(Selected_period="Total Year",Selected_Year,DATE(Selected_Year,Selected_period,1)), Budget_Planning!$E$9:$DY$9, 0)))} -> 2400 | M22: {=IF(is_cat, IF(header_row_id=income_header_row, MATCH(income_min_row,$C:$C,0), IF(header_row_id=expenses_header_row,MATCH(expenses_min_row,$C:$C,0), IF(header_row_id=Savings_header_row,MATCH(savings_min_row,$C:$C,0),""))), "")} -> 17 | N22: {=IF(is_cat, IF(header_row_id=income_header_row, MATCH(income_max_row,$C:$C,0), IF(header_row_id=expenses_header_row,MATCH(expenses_max_row,$C:$C,0), IF(header_row_id=Savings_header_row,MATCH(savings_max_row,$C:$C,0),""))), "")} -> 25 | O22: =IF(is_cat,ADDRESS(sort_min_row,COLUMN(tracked)) &":" & ADDRESS(sort_max_row,COLUMN(tracked)), "") -> $K$17:$K$25 | P22: =IF(is_cat,RANK(tracked,INDIRECT(tracked_range),0), "") -> 7 | Q22: =IF(is_cat,ADDRESS(sort_min_row,COLUMN(budget)) & ":" &ADDRESS(sort_max_row,COLUMN(budget)), "") -> $L$17:$L$25 | R22: =IF(is_cat,RANK(budget,INDIRECT(budget_range),0),"") -> 6 | S22: =IF(is_cat,_xlfn.NUMBERVALUE(tracked_rank& budget_rank),"") -> 76 | T22: =IF(is_cat,ADDRESS(sort_min_row,COLUMN(comb_rank)) & ":" &ADDRESS(sort_max_row,COLUMN(comb_rank)), "") -> $S$17:$S$25 | U22: =IF(is_cat,RANK(comb_rank,INDIRECT(comb_rank_range),1),"") -> 7 | V22: =IF(is_cat,ADDRESS(sort_min_row,COLUMN(comb_rank_norm)) & ":" &ADDRESS(ROW(),COLUMN(comb_rank_norm)), "") -> $U$17:$U$22 | W22: =IF(is_cat,comb_rank_norm+ COUNTIF(INDIRECT(comb_rank_norm_run_range),comb_rank_norm)-1,"") -> 7 | X22: =IF(is_cat,header_row_id+comb_rank_unique,row_id) -> 29 | Y22: =IF(is_empty,"",INDEX($J:$J,MATCH(row_id,$X:$X,0))) -> Insurance | Z22: =IF(is_empty,"",IF(is_header,"Tracked",INDEX($K:$K, MATCH(row_id,$X:$X,0)))) -> 600 | AA22: =IF(is_empty,"",IF(is_header,"Budget",INDEX($L:$L, MATCH(row_id,$X:$X,0)))) -> 600 | AB22: =IF(is_empty,"",IF(is_header,"%Compl.",IFERROR(out_tracked/out_budget,"-"))) -> 1 | AC22: =IF(is_empty,"",IF(is_header,"Remaining",IF(out_budget-out_tracked > 0, out_budget-out_tracked,0))) -> 0 | AD22: =IF(is_empty,"",IF(is_header,"Excess",IF(out_budget-out_tracked < 0, out_tracked-out_budget,0))) -> 0
C23: {=IF(C22=-1,-1, IF(C22<income_max_row,C22+1, IF(C22=income_max_row,income_total_row, IF(C22=income_total_row, "/1", IF(C22="/1",expenses_header_row, IF(C22<expenses_max_row, C22+1, IF(C22=expenses_max_row,expenses_total_row, IF(C22=expenses_total_row,"/2", IF(C22="/2",Savings_header_row, IF(C22<savings_max_row,C22+1, IF(C22=savings_max_row,savings_total_row, -1)))))))))))} -> 29 | D23: =IF(is_header,row_id, IF(NOT(is_empty),D22,-1)) -> 22 | E23: {=1*OR(row_id=income_header_row,row_id=expenses_header_row,row_id=Savings_header_row)} -> 0 | F23: =1*NOT(OR(is_header,is_total,is_empty)) -> 1 | G23: {=1*OR(row_id=income_total_row,row_id=expenses_total_row,row_id=savings_total_row)} -> 0 | H23: =1*OR(row_id="/1",row_id="/2",row_id=-1) -> 0 | I23: {=IFERROR(INDEX(Budget_Planning!$C:$C,header_row_id), " ")} -> Expenses | J23: {=IFERROR(INDEX(Budget_Planning!$C:$C,row_id), " ")} -> Body care | K23: {=IF(OR(is_header,is_empty),"", IF(is_total, IF(Selected_period="Total Year", SUM(Tracking[Amount]*(Tracking[Type]=type)*(YEAR(Tracking[Effective Date])=Selected_Year) ), SUM(Tracking[Amount]*(Tracking[Type]=type)*(YEAR(Tracking[Effective Date])=Selected_Year) * (MONTH(Tracking[Effective Date])=Selected_period))), IF(Selected_period="Total Year", SUM(Tracking[Amount]*(Tracking[Type]=type)*(Tracking[Category]=item)*(YEAR(Tracking[Effective Date])=Selected_Year)), SUM(Tracking[Amount]*(Tracking[Type]=type)*(Tracking[Category]=item)*(YEAR(Tracking[Effective Date])=Selected_Year) * (MONTH(Tracking[Effective Date])=Selected_period)) )))} -> 970 | L23: {=IF(OR(is_header,is_empty),"", INDEX(Budget_Planning!$E:$DY,row_id, MATCH(IF(Selected_period="Total Year",Selected_Year,DATE(Selected_Year,Selected_period,1)), Budget_Planning!$E$9:$DY$9, 0)))} -> 2400 | M23: {=IF(is_cat, IF(header_row_id=income_header_row, MATCH(income_min_row,$C:$C,0), IF(header_row_id=expenses_header_row,MATCH(expenses_min_row,$C:$C,0), IF(header_row_id=Savings_header_row,MATCH(savings_min_row,$C:$C,0),""))), "")} -> 17 | N23: {=IF(is_cat, IF(header_row_id=income_header_row, MATCH(income_max_row,$C:$C,0), IF(header_row_id=expenses_header_row,MATCH(expenses_max_row,$C:$C,0), IF(header_row_id=Savings_header_row,MATCH(savings_max_row,$C:$C,0),""))), "")} -> 25 | O23: =IF(is_cat,ADDRESS(sort_min_row,COLUMN(tracked)) &":" & ADDRESS(sort_max_row,COLUMN(tracked)), "") -> $K$17:$K$25 | P23: =IF(is_cat,RANK(tracked,INDIRECT(tracked_range),0), "") -> 4 | Q23: =IF(is_cat,ADDRESS(sort_min_row,COLUMN(budget)) & ":" &ADDRESS(sort_max_row,COLUMN(budget)), "") -> $L$17:$L$25 | R23: =IF(is_cat,RANK(budget,INDIRECT(budget_range),0),"") -> 6 | S23: =IF(is_cat,_xlfn.NUMBERVALUE(tracked_rank& budget_rank),"") -> 46 | T23: =IF(is_cat,ADDRESS(sort_min_row,COLUMN(comb_rank)) & ":" &ADDRESS(sort_max_row,COLUMN(comb_rank)), "") -> $S$17:$S$25 | U23: =IF(is_cat,RANK(comb_rank,INDIRECT(comb_rank_range),1),"") -> 4 | V23: =IF(is_cat,ADDRESS(sort_min_row,COLUMN(comb_rank_norm)) & ":" &ADDRESS(ROW(),COLUMN(comb_rank_norm)), "") -> $U$17:$U$23 | W23: =IF(is_cat,comb_rank_norm+ COUNTIF(INDIRECT(comb_rank_norm_run_range),comb_rank_norm)-1,"") -> 4 | X23: =IF(is_cat,header_row_id+comb_rank_unique,row_id) -> 26 | Y23: =IF(is_empty,"",INDEX($J:$J,MATCH(row_id,$X:$X,0))) -> Clothing | Z23: =IF(is_empty,"",IF(is_header,"Tracked",INDEX($K:$K, MATCH(row_id,$X:$X,0)))) -> 400 | AA23: =IF(is_empty,"",IF(is_header,"Budget",INDEX($L:$L, MATCH(row_id,$X:$X,0)))) -> 2400 | AB23: =IF(is_empty,"",IF(is_header,"%Compl.",IFERROR(out_tracked/out_budget,"-"))) -> 0.16666667 | AC23: =IF(is_empty,"",IF(is_header,"Remaining",IF(out_budget-out_tracked > 0, out_budget-out_tracked,0))) -> 2000 | AD23: =IF(is_empty,"",IF(is_header,"Excess",IF(out_budget-out_tracked < 0, out_tracked-out_budget,0))) -> 0
C24: {=IF(C23=-1,-1, IF(C23<income_max_row,C23+1, IF(C23=income_max_row,income_total_row, IF(C23=income_total_row, "/1", IF(C23="/1",expenses_header_row, IF(C23<expenses_max_row, C23+1, IF(C23=expenses_max_row,expenses_total_row, IF(C23=expenses_total_row,"/2", IF(C23="/2",Savings_header_row, IF(C23<savings_max_row,C23+1, IF(C23=savings_max_row,savings_total_row, -1)))))))))))} -> 30 | D24: =IF(is_header,row_id, IF(NOT(is_empty),D23,-1)) -> 22 | E24: {=1*OR(row_id=income_header_row,row_id=expenses_header_row,row_id=Savings_header_row)} -> 0 | F24: =1*NOT(OR(is_header,is_total,is_empty)) -> 1 | G24: {=1*OR(row_id=income_total_row,row_id=expenses_total_row,row_id=savings_total_row)} -> 0 | H24: =1*OR(row_id="/1",row_id="/2",row_id=-1) -> 0 | I24: {=IFERROR(INDEX(Budget_Planning!$C:$C,header_row_id), " ")} -> Expenses | J24: {=IFERROR(INDEX(Budget_Planning!$C:$C,row_id), " ")} -> Media | K24: {=IF(OR(is_header,is_empty),"", IF(is_total, IF(Selected_period="Total Year", SUM(Tracking[Amount]*(Tracking[Type]=type)*(YEAR(Tracking[Effective Date])=Selected_Year) ), SUM(Tracking[Amount]*(Tracking[Type]=type)*(YEAR(Tracking[Effective Date])=Selected_Year) * (MONTH(Tracking[Effective Date])=Selected_period))), IF(Selected_period="Total Year", SUM(Tracking[Amount]*(Tracking[Type]=type)*(Tracking[Category]=item)*(YEAR(Tracking[Effective Date])=Selected_Year)), SUM(Tracking[Amount]*(Tracking[Type]=type)*(Tracking[Category]=item)*(YEAR(Tracking[Effective Date])=Selected_Year) * (MONTH(Tracking[Effective Date])=Selected_period)) )))} -> 0 | L24: {=IF(OR(is_header,is_empty),"", INDEX(Budget_Planning!$E:$DY,row_id, MATCH(IF(Selected_period="Total Year",Selected_Year,DATE(Selected_Year,Selected_period,1)), Budget_Planning!$E$9:$DY$9, 0)))} -> 600 | M24: {=IF(is_cat, IF(header_row_id=income_header_row, MATCH(income_min_row,$C:$C,0), IF(header_row_id=expenses_header_row,MATCH(expenses_min_row,$C:$C,0), IF(header_row_id=Savings_header_row,MATCH(savings_min_row,$C:$C,0),""))), "")} -> 17 | N24: {=IF(is_cat, IF(header_row_id=income_header_row, MATCH(income_max_row,$C:$C,0), IF(header_row_id=expenses_header_row,MATCH(expenses_max_row,$C:$C,0), IF(header_row_id=Savings_header_row,MATCH(savings_max_row,$C:$C,0),""))), "")} -> 25 | O24: =IF(is_cat,ADDRESS(sort_min_row,COLUMN(tracked)) &":" & ADDRESS(sort_max_row,COLUMN(tracked)), "") -> $K$17:$K$25 | P24: =IF(is_cat,RANK(tracked,INDIRECT(tracked_range),0), "") -> 8 | Q24: =IF(is_cat,ADDRESS(sort_min_row,COLUMN(budget)) & ":" &ADDRESS(sort_max_row,COLUMN(budget)), "") -> $L$17:$L$25 | R24: =IF(is_cat,RANK(budget,INDIRECT(budget_range),0),"") -> 8 | S24: =IF(is_cat,_xlfn.NUMBERVALUE(tracked_rank& budget_rank),"") -> 88 | T24: =IF(is_cat,ADDRESS(sort_min_row,COLUMN(comb_rank)) & ":" &ADDRESS(sort_max_row,COLUMN(comb_rank)), "") -> $S$17:$S$25 | U24: =IF(is_cat,RANK(comb_rank,INDIRECT(comb_rank_range),1),"") -> 9 | V24: =IF(is_cat,ADDRESS(sort_min_row,COLUMN(comb_rank_norm)) & ":" &ADDRESS(ROW(),COLUMN(comb_rank_norm)), "") -> $U$17:$U$24 | W24: =IF(is_cat,comb_rank_norm+ COUNTIF(INDIRECT(comb_rank_norm_run_range),comb_rank_norm)-1,"") -> 9 | X24: =IF(is_cat,header_row_id+comb_rank_unique,row_id) -> 31 | Y24: =IF(is_empty,"",INDEX($J:$J,MATCH(row_id,$X:$X,0))) -> Fun&Vacation | Z24: =IF(is_empty,"",IF(is_header,"Tracked",INDEX($K:$K, MATCH(row_id,$X:$X,0)))) -> 0 | AA24: =IF(is_empty,"",IF(is_header,"Budget",INDEX($L:$L, MATCH(row_id,$X:$X,0)))) -> 6000 | AB24: =IF(is_empty,"",IF(is_header,"%Compl.",IFERROR(out_tracked/out_budget,"-"))) -> 0 | AC24: =IF(is_empty,"",IF(is_header,"Remaining",IF(out_budget-out_tracked > 0, out_budget-out_tracked,0))) -> 6000 | AD24: =IF(is_empty,"",IF(is_header,"Excess",IF(out_budget-out_tracked < 0, out_tracked-out_budget,0))) -> 0
C25: {=IF(C24=-1,-1, IF(C24<income_max_row,C24+1, IF(C24=income_max_row,income_total_row, IF(C24=income_total_row, "/1", IF(C24="/1",expenses_header_row, IF(C24<expenses_max_row, C24+1, IF(C24=expenses_max_row,expenses_total_row, IF(C24=expenses_total_row,"/2", IF(C24="/2",Savings_header_row, IF(C24<savings_max_row,C24+1, IF(C24=savings_max_row,savings_total_row, -1)))))))))))} -> 31 | D25: =IF(is_header,row_id, IF(NOT(is_empty),D24,-1)) -> 22 | E25: {=1*OR(row_id=income_header_row,row_id=expenses_header_row,row_id=Savings_header_row)} -> 0 | F25: =1*NOT(OR(is_header,is_total,is_empty)) -> 1 | G25: {=1*OR(row_id=income_total_row,row_id=expenses_total_row,row_id=savings_total_row)} -> 0 | H25: =1*OR(row_id="/1",row_id="/2",row_id=-1) -> 0 | I25: {=IFERROR(INDEX(Budget_Planning!$C:$C,header_row_id), " ")} -> Expenses | J25: {=IFERROR(INDEX(Budget_Planning!$C:$C,row_id), " ")} -> Fun&Vacation | K25: {=IF(OR(is_header,is_empty),"", IF(is_total, IF(Selected_period="Total Year", SUM(Tracking[Amount]*(Tracking[Type]=type)*(YEAR(Tracking[Effective Date])=Selected_Year) ), SUM(Tracking[Amount]*(Tracking[Type]=type)*(YEAR(Tracking[Effective Date])=Selected_Year) * (MONTH(Tracking[Effective Date])=Selected_period))), IF(Selected_period="Total Year", SUM(Tracking[Amount]*(Tracking[Type]=type)*(Tracking[Category]=item)*(YEAR(Tracking[Effective Date])=Selected_Year)), SUM(Tracking[Amount]*(Tracking[Type]=type)*(Tracking[Category]=item)*(YEAR(Tracking[Effective Date])=Selected_Year) * (MONTH(Tracking[Effective Date])=Selected_period)) )))} -> 0 | L25: {=IF(OR(is_header,is_empty),"", INDEX(Budget_Planning!$E:$DY,row_id, MATCH(IF(Selected_period="Total Year",Selected_Year,DATE(Selected_Year,Selected_period,1)), Budget_Planning!$E$9:$DY$9, 0)))} -> 6000 | M25: {=IF(is_cat, IF(header_row_id=income_header_row, MATCH(income_min_row,$C:$C,0), IF(header_row_id=expenses_header_row,MATCH(expenses_min_row,$C:$C,0), IF(header_row_id=Savings_header_row,MATCH(savings_min_row,$C:$C,0),""))), "")} -> 17 | N25: {=IF(is_cat, IF(header_row_id=income_header_row, MATCH(income_max_row,$C:$C,0), IF(header_row_id=expenses_header_row,MATCH(expenses_max_row,$C:$C,0), IF(header_row_id=Savings_header_row,MATCH(savings_max_row,$C:$C,0),""))), "")} -> 25 | O25: =IF(is_cat,ADDRESS(sort_min_row,COLUMN(tracked)) &":" & ADDRESS(sort_max_row,COLUMN(tracked)), "") -> $K$17:$K$25 | P25: =IF(is_cat,RANK(tracked,INDIRECT(tracked_range),0), "") -> 8 | Q25: =IF(is_cat,ADDRESS(sort_min_row,COLUMN(budget)) & ":" &ADDRESS(sort_max_row,COLUMN(budget)), "") -> $L$17:$L$25 | R25: =IF(is_cat,RANK(budget,INDIRECT(budget_range),0),"") -> 2 | S25: =IF(is_cat,_xlfn.NUMBERVALUE(tracked_rank& budget_rank),"") -> 82 | T25: =IF(is_cat,ADDRESS(sort_min_row,COLUMN(comb_rank)) & ":" &ADDRESS(sort_max_row,COLUMN(comb_rank)), "") -> $S$17:$S$25 | U25: =IF(is_cat,RANK(comb_rank,INDIRECT(comb_rank_range),1),"") -> 8 | V25: =IF(is_cat,ADDRESS(sort_min_row,COLUMN(comb_rank_norm)) & ":" &ADDRESS(ROW(),COLUMN(comb_rank_norm)), "") -> $U$17:$U$25 | W25: =IF(is_cat,comb_rank_norm+ COUNTIF(INDIRECT(comb_rank_norm_run_range),comb_rank_norm)-1,"") -> 8 | X25: =IF(is_cat,header_row_id+comb_rank_unique,row_id) -> 30 | Y25: =IF(is_empty,"",INDEX($J:$J,MATCH(row_id,$X:$X,0))) -> Media | Z25: =IF(is_empty,"",IF(is_header,"Tracked",INDEX($K:$K, MATCH(row_id,$X:$X,0)))) -> 0 | AA25: =IF(is_empty,"",IF(is_header,"Budget",INDEX($L:$L, MATCH(row_id,$X:$X,0)))) -> 600 | AB25: =IF(is_empty,"",IF(is_header,"%Compl.",IFERROR(out_tracked/out_budget,"-"))) -> 0 | AC25: =IF(is_empty,"",IF(is_header,"Remaining",IF(out_budget-out_tracked > 0, out_budget-out_tracked,0))) -> 600 | AD25: =IF(is_empty,"",IF(is_header,"Excess",IF(out_budget-out_tracked < 0, out_tracked-out_budget,0))) -> 0 | AI25: =Calculations!I35 -> Groceries | AJ25: =Calculations!J35 -> 2300 | AP25: =Calculations!M35 -> Emergency Fund | AQ25: =Calculations!N35 -> 1100
C26: {=IF(C25=-1,-1, IF(C25<income_max_row,C25+1, IF(C25=income_max_row,income_total_row, IF(C25=income_total_row, "/1", IF(C25="/1",expenses_header_row, IF(C25<expenses_max_row, C25+1, IF(C25=expenses_max_row,expenses_total_row, IF(C25=expenses_total_row,"/2", IF(C25="/2",Savings_header_row, IF(C25<savings_max_row,C25+1, IF(C25=savings_max_row,savings_total_row, -1)))))))))))} -> 33 | D26: =IF(is_header,row_id, IF(NOT(is_empty),D25,-1)) -> 22 | E26: {=1*OR(row_id=income_header_row,row_id=expenses_header_row,row_id=Savings_header_row)} -> 0 | F26: =1*NOT(OR(is_header,is_total,is_empty)) -> 0 | G26: {=1*OR(row_id=income_total_row,row_id=expenses_total_row,row_id=savings_total_row)} -> 1 | H26: =1*OR(row_id="/1",row_id="/2",row_id=-1) -> 0 | I26: {=IFERROR(INDEX(Budget_Planning!$C:$C,header_row_id), " ")} -> Expenses | J26: {=IFERROR(INDEX(Budget_Planning!$C:$C,row_id), " ")} -> Total | K26: {=IF(OR(is_header,is_empty),"", IF(is_total, IF(Selected_period="Total Year", SUM(Tracking[Amount]*(Tracking[Type]=type)*(YEAR(Tracking[Effective Date])=Selected_Year) ), SUM(Tracking[Amount]*(Tracking[Type]=type)*(YEAR(Tracking[Effective Date])=Selected_Year) * (MONTH(Tracking[Effective Date])=Selected_period))), IF(Selected_period="Total Year", SUM(Tracking[Amount]*(Tracking[Type]=type)*(Tracking[Category]=item)*(YEAR(Tracking[Effective Date])=Selected_Year)), SUM(Tracking[Amount]*(Tracking[Type]=type)*(Tracking[Category]=item)*(YEAR(Tracking[Effective Date])=Selected_Year) * (MONTH(Tracking[Effective Date])=Selected_period)) )))} -> 8270 | L26: {=IF(OR(is_header,is_empty),"", INDEX(Budget_Planning!$E:$DY,row_id, MATCH(IF(Selected_period="Total Year",Selected_Year,DATE(Selected_Year,Selected_period,1)), Budget_Planning!$E$9:$DY$9, 0)))} -> 37800 | M26: {=IF(is_cat, IF(header_row_id=income_header_row, MATCH(income_min_row,$C:$C,0), IF(header_row_id=expenses_header_row,MATCH(expenses_min_row,$C:$C,0), IF(header_row_id=Savings_header_row,MATCH(savings_min_row,$C:$C,0),""))), "")} | N26: {=IF(is_cat, IF(header_row_id=income_header_row, MATCH(income_max_row,$C:$C,0), IF(header_row_id=expenses_header_row,MATCH(expenses_max_row,$C:$C,0), IF(header_row_id=Savings_header_row,MATCH(savings_max_row,$C:$C,0),""))), "")} | O26: =IF(is_cat,ADDRESS(sort_min_row,COLUMN(tracked)) &":" & ADDRESS(sort_max_row,COLUMN(tracked)), "") | P26: =IF(is_cat,RANK(tracked,INDIRECT(tracked_range),0), "") | Q26: =IF(is_cat,ADDRESS(sort_min_row,COLUMN(budget)) & ":" &ADDRESS(sort_max_row,COLUMN(budget)), "") | R26: =IF(is_cat,RANK(budget,INDIRECT(budget_range),0),"") | S26: =IF(is_cat,_xlfn.NUMBERVALUE(tracked_rank& budget_rank),"") | T26: =IF(is_cat,ADDRESS(sort_min_row,COLUMN(comb_rank)) & ":" &ADDRESS(sort_max_row,COLUMN(comb_rank)), "") | U26: =IF(is_cat,RANK(comb_rank,INDIRECT(comb_rank_range),1),"") | V26: =IF(is_cat,ADDRESS(sort_min_row,COLUMN(comb_rank_norm)) & ":" &ADDRESS(ROW(),COLUMN(comb_rank_norm)), "") | W26: =IF(is_cat,comb_rank_norm+ COUNTIF(INDIRECT(comb_rank_norm_run_range),comb_rank_norm)-1,"") | X26: =IF(is_cat,header_row_id+comb_rank_unique,row_id) -> 33 | Y26: =IF(is_empty,"",INDEX($J:$J,MATCH(row_id,$X:$X,0))) -> Total | Z26: =IF(is_empty,"",IF(is_header,"Tracked",INDEX($K:$K, MATCH(row_id,$X:$X,0)))) -> 8270 | AA26: =IF(is_empty,"",IF(is_header,"Budget",INDEX($L:$L, MATCH(row_id,$X:$X,0)))) -> 37800 | AB26: =IF(is_empty,"",IF(is_header,"%Compl.",IFERROR(out_tracked/out_budget,"-"))) -> 0.21878307 | AC26: =IF(is_empty,"",IF(is_header,"Remaining",IF(out_budget-out_tracked > 0, out_budget-out_tracked,0))) -> 29530 | AD26: =IF(is_empty,"",IF(is_header,"Excess",IF(out_budget-out_tracked < 0, out_tracked-out_budget,0))) -> 0 | AI26: =Calculations!I36 -> Housing | AJ26: =Calculations!J36 -> 1800 | AP26: =Calculations!M36 -> Retirement Account | AQ26: =Calculations!N36 -> 850
C27: {=IF(C26=-1,-1, IF(C26<income_max_row,C26+1, IF(C26=income_max_row,income_total_row, IF(C26=income_total_row, "/1", IF(C26="/1",expenses_header_row, IF(C26<expenses_max_row, C26+1, IF(C26=expenses_max_row,expenses_total_row, IF(C26=expenses_total_row,"/2", IF(C26="/2",Savings_header_row, IF(C26<savings_max_row,C26+1, IF(C26=savings_max_row,savings_total_row, -1)))))))))))} -> /2 | D27: =IF(is_header,row_id, IF(NOT(is_empty),D26,-1)) -> -1 | E27: {=1*OR(row_id=income_header_row,row_id=expenses_header_row,row_id=Savings_header_row)} -> 0 | F27: =1*NOT(OR(is_header,is_total,is_empty)) -> 0 | G27: {=1*OR(row_id=income_total_row,row_id=expenses_total_row,row_id=savings_total_row)} -> 0 | H27: =1*OR(row_id="/1",row_id="/2",row_id=-1) -> 1 | I27: {=IFERROR(INDEX(Budget_Planning!$C:$C,header_row_id), " ")} | J27: {=IFERROR(INDEX(Budget_Planning!$C:$C,row_id), " ")} | K27: {=IF(OR(is_header,is_empty),"", IF(is_total, IF(Selected_period="Total Year", SUM(Tracking[Amount]*(Tracking[Type]=type)*(YEAR(Tracking[Effective Date])=Selected_Year) ), SUM(Tracking[Amount]*(Tracking[Type]=type)*(YEAR(Tracking[Effective Date])=Selected_Year) * (MONTH(Tracking[Effective Date])=Selected_period))), IF(Selected_period="Total Year", SUM(Tracking[Amount]*(Tracking[Type]=type)*(Tracking[Category]=item)*(YEAR(Tracking[Effective Date])=Selected_Year)), SUM(Tracking[Amount]*(Tracking[Type]=type)*(Tracking[Category]=item)*(YEAR(Tracking[Effective Date])=Selected_Year) * (MONTH(Tracking[Effective Date])=Selected_period)) )))} | L27: {=IF(OR(is_header,is_empty),"", INDEX(Budget_Planning!$E:$DY,row_id, MATCH(IF(Selected_period="Total Year",Selected_Year,DATE(Selected_Year,Selected_period,1)), Budget_Planning!$E$9:$DY$9, 0)))} | M27: {=IF(is_cat, IF(header_row_id=income_header_row, MATCH(income_min_row,$C:$C,0), IF(header_row_id=expenses_header_row,MATCH(expenses_min_row,$C:$C,0), IF(header_row_id=Savings_header_row,MATCH(savings_min_row,$C:$C,0),""))), "")} | N27: {=IF(is_cat, IF(header_row_id=income_header_row, MATCH(income_max_row,$C:$C,0), IF(header_row_id=expenses_header_row,MATCH(expenses_max_row,$C:$C,0), IF(header_row_id=Savings_header_row,MATCH(savings_max_row,$C:$C,0),""))), "")} | O27: =IF(is_cat,ADDRESS(sort_min_row,COLUMN(tracked)) &":" & ADDRESS(sort_max_row,COLUMN(tracked)), "") | P27: =IF(is_cat,RANK(tracked,INDIRECT(tracked_range),0), "") | Q27: =IF(is_cat,ADDRESS(sort_min_row,COLUMN(budget)) & ":" &ADDRESS(sort_max_row,COLUMN(budget)), "") | R27: =IF(is_cat,RANK(budget,INDIRECT(budget_range),0),"") | S27: =IF(is_cat,_xlfn.NUMBERVALUE(tracked_rank& budget_rank),"") | T27: =IF(is_cat,ADDRESS(sort_min_row,COLUMN(comb_rank)) & ":" &ADDRESS(sort_max_row,COLUMN(comb_rank)), "") | U27: =IF(is_cat,RANK(comb_rank,INDIRECT(comb_rank_range),1),"") | V27: =IF(is_cat,ADDRESS(sort_min_row,COLUMN(comb_rank_norm)) & ":" &ADDRESS(ROW(),COLUMN(comb_rank_norm)), "") | W27: =IF(is_cat,comb_rank_norm+ COUNTIF(INDIRECT(comb_rank_norm_run_range),comb_rank_norm)-1,"") | X27: =IF(is_cat,header_row_id+comb_rank_unique,row_id) -> /2 | Y27: =IF(is_empty,"",INDEX($J:$J,MATCH(row_id,$X:$X,0))) | Z27: =IF(is_empty,"",IF(is_header,"Tracked",INDEX($K:$K, MATCH(row_id,$X:$X,0)))) | AA27: =IF(is_empty,"",IF(is_header,"Budget",INDEX($L:$L, MATCH(row_id,$X:$X,0)))) | AB27: =IF(is_empty,"",IF(is_header,"%Compl.",IFERROR(out_tracked/out_budget,"-"))) | AC27: =IF(is_empty,"",IF(is_header,"Remaining",IF(out_budget-out_tracked > 0, out_budget-out_tracked,0))) | AD27: =IF(is_empty,"",IF(is_header,"Excess",IF(out_budget-out_tracked < 0, out_tracked-out_budget,0))) | AI27: =Calculations!I37 -> Utilities | AJ27: =Calculations!J37 -> 1400 | AP27: =Calculations!M37 -> Stock Portfolio | AQ27: =Calculations!N37 -> 300
C28: {=IF(C27=-1,-1, IF(C27<income_max_row,C27+1, IF(C27=income_max_row,income_total_row, IF(C27=income_total_row, "/1", IF(C27="/1",expenses_header_row, IF(C27<expenses_max_row, C27+1, IF(C27=expenses_max_row,expenses_total_row, IF(C27=expenses_total_row,"/2", IF(C27="/2",Savings_header_row, IF(C27<savings_max_row,C27+1, IF(C27=savings_max_row,savings_total_row, -1)))))))))))} -> 35 | D28: =IF(is_header,row_id, IF(NOT(is_empty),D27,-1)) -> 35 | E28: {=1*OR(row_id=income_header_row,row_id=expenses_header_row,row_id=Savings_header_row)} -> 1 | F28: =1*NOT(OR(is_header,is_total,is_empty)) -> 0 | G28: {=1*OR(row_id=income_total_row,row_id=expenses_total_row,row_id=savings_total_row)} -> 0 | H28: =1*OR(row_id="/1",row_id="/2",row_id=-1) -> 0 | I28: {=IFERROR(INDEX(Budget_Planning!$C:$C,header_row_id), " ")} -> Savings | J28: {=IFERROR(INDEX(Budget_Planning!$C:$C,row_id), " ")} -> Savings | K28: {=IF(OR(is_header,is_empty),"", IF(is_total, IF(Selected_period="Total Year", SUM(Tracking[Amount]*(Tracking[Type]=type)*(YEAR(Tracking[Effective Date])=Selected_Year) ), SUM(Tracking[Amount]*(Tracking[Type]=type)*(YEAR(Tracking[Effective Date])=Selected_Year) * (MONTH(Tracking[Effective Date])=Selected_period))), IF(Selected_period="Total Year", SUM(Tracking[Amount]*(Tracking[Type]=type)*(Tracking[Category]=item)*(YEAR(Tracking[Effective Date])=Selected_Year)), SUM(Tracking[Amount]*(Tracking[Type]=type)*(Tracking[Category]=item)*(YEAR(Tracking[Effective Date])=Selected_Year) * (MONTH(Tracking[Effective Date])=Selected_period)) )))} | L28: {=IF(OR(is_header,is_empty),"", INDEX(Budget_Planning!$E:$DY,row_id, MATCH(IF(Selected_period="Total Year",Selected_Year,DATE(Selected_Year,Selected_period,1)), Budget_Planning!$E$9:$DY$9, 0)))} | M28: {=IF(is_cat, IF(header_row_id=income_header_row, MATCH(income_min_row,$C:$C,0), IF(header_row_id=expenses_header_row,MATCH(expenses_min_row,$C:$C,0), IF(header_row_id=Savings_header_row,MATCH(savings_min_row,$C:$C,0),""))), "")} | N28: {=IF(is_cat, IF(header_row_id=income_header_row, MATCH(income_max_row,$C:$C,0), IF(header_row_id=expenses_header_row,MATCH(expenses_max_row,$C:$C,0), IF(header_row_id=Savings_header_row,MATCH(savings_max_row,$C:$C,0),""))), "")} | O28: =IF(is_cat,ADDRESS(sort_min_row,COLUMN(tracked)) &":" & ADDRESS(sort_max_row,COLUMN(tracked)), "") | P28: =IF(is_cat,RANK(tracked,INDIRECT(tracked_range),0), "") | Q28: =IF(is_cat,ADDRESS(sort_min_row,COLUMN(budget)) & ":" &ADDRESS(sort_max_row,COLUMN(budget)), "") | R28: =IF(is_cat,RANK(budget,INDIRECT(budget_range),0),"") | S28: =IF(is_cat,_xlfn.NUMBERVALUE(tracked_rank& budget_rank),"") | T28: =IF(is_cat,ADDRESS(sort_min_row,COLUMN(comb_rank)) & ":" &ADDRESS(sort_max_row,COLUMN(comb_rank)), "") | U28: =IF(is_cat,RANK(comb_rank,INDIRECT(comb_rank_range),1),"") | V28: =IF(is_cat,ADDRESS(sort_min_row,COLUMN(comb_rank_norm)) & ":" &ADDRESS(ROW(),COLUMN(comb_rank_norm)), "") | W28: =IF(is_cat,comb_rank_norm+ COUNTIF(INDIRECT(comb_rank_norm_run_range),comb_rank_norm)-1,"") | X28: =IF(is_cat,header_row_id+comb_rank_unique,row_id) -> 35 | Y28: =IF(is_empty,"",INDEX($J:$J,MATCH(row_id,$X:$X,0))) -> Savings | Z28: =IF(is_empty,"",IF(is_header,"Tracked",INDEX($K:$K, MATCH(row_id,$X:$X,0)))) -> Tracked | AA28: =IF(is_empty,"",IF(is_header,"Budget",INDEX($L:$L, MATCH(row_id,$X:$X,0)))) -> Budget | AB28: =IF(is_empty,"",IF(is_header,"%Compl.",IFERROR(out_tracked/out_budget,"-"))) -> %Compl. | AC28: =IF(is_empty,"",IF(is_header,"Remaining",IF(out_budget-out_tracked > 0, out_budget-out_tracked,0))) -> Remaining | AD28: =IF(is_empty,"",IF(is_header,"Excess",IF(out_budget-out_tracked < 0, out_tracked-out_budget,0))) -> Excess | AI28: =Calculations!I38 -> Body care | AJ28: =Calculations!J38 -> 970 | AP28: =Calculations!M38 -> Sinking Fund | AQ28: =Calculations!N38 -> 250
C29: {=IF(C28=-1,-1, IF(C28<income_max_row,C28+1, IF(C28=income_max_row,income_total_row, IF(C28=income_total_row, "/1", IF(C28="/1",expenses_header_row, IF(C28<expenses_max_row, C28+1, IF(C28=expenses_max_row,expenses_total_row, IF(C28=expenses_total_row,"/2", IF(C28="/2",Savings_header_row, IF(C28<savings_max_row,C28+1, IF(C28=savings_max_row,savings_total_row, -1)))))))))))} -> 36 | D29: =IF(is_header,row_id, IF(NOT(is_empty),D28,-1)) -> 35 | E29: {=1*OR(row_id=income_header_row,row_id=expenses_header_row,row_id=Savings_header_row)} -> 0 | F29: =1*NOT(OR(is_header,is_total,is_empty)) -> 1 | G29: {=1*OR(row_id=income_total_row,row_id=expenses_total_row,row_id=savings_total_row)} -> 0 | H29: =1*OR(row_id="/1",row_id="/2",row_id=-1) -> 0 | I29: {=IFERROR(INDEX(Budget_Planning!$C:$C,header_row_id), " ")} -> Savings | J29: {=IFERROR(INDEX(Budget_Planning!$C:$C,row_id), " ")} -> Emergency Fund | K29: {=IF(OR(is_header,is_empty),"", IF(is_total, IF(Selected_period="Total Year", SUM(Tracking[Amount]*(Tracking[Type]=type)*(YEAR(Tracking[Effective Date])=Selected_Year) ), SUM(Tracking[Amount]*(Tracking[Type]=type)*(YEAR(Tracking[Effective Date])=Selected_Year) * (MONTH(Tracking[Effective Date])=Selected_period))), IF(Selected_period="Total Year", SUM(Tracking[Amount]*(Tracking[Type]=type)*(Tracking[Category]=item)*(YEAR(Tracking[Effective Date])=Selected_Year)), SUM(Tracking[Amount]*(Tracking[Type]=type)*(Tracking[Category]=item)*(YEAR(Tracking[Effective Date])=Selected_Year) * (MONTH(Tracking[Effective Date])=Selected_period)) )))} -> 1100 | L29: {=IF(OR(is_header,is_empty),"", INDEX(Budget_Planning!$E:$DY,row_id, MATCH(IF(Selected_period="Total Year",Selected_Year,DATE(Selected_Year,Selected_period,1)), Budget_Planning!$E$9:$DY$9, 0)))} -> 3000 | M29: {=IF(is_cat, IF(header_row_id=income_header_row, MATCH(income_min_row,$C:$C,0), IF(header_row_id=expenses_header_row,MATCH(expenses_min_row,$C:$C,0), IF(header_row_id=Savings_header_row,MATCH(savings_min_row,$C:$C,0),""))), "")} -> 29 | N29: {=IF(is_cat, IF(header_row_id=income_header_row, MATCH(income_max_row,$C:$C,0), IF(header_row_id=expenses_header_row,MATCH(expenses_max_row,$C:$C,0), IF(header_row_id=Savings_header_row,MATCH(savings_max_row,$C:$C,0),""))), "")} -> 33 | O29: =IF(is_cat,ADDRESS(sort_min_row,COLUMN(tracked)) &":" & ADDRESS(sort_max_row,COLUMN(tracked)), "") -> $K$29:$K$33 | P29: =IF(is_cat,RANK(tracked,INDIRECT(tracked_range),0), "") -> 1 | Q29: =IF(is_cat,ADDRESS(sort_min_row,COLUMN(budget)) & ":" &ADDRESS(sort_max_row,COLUMN(budget)), "") -> $L$29:$L$33 | R29: =IF(is_cat,RANK(budget,INDIRECT(budget_range),0),"") -> 4 | S29: =IF(is_cat,_xlfn.NUMBERVALUE(tracked_rank& budget_rank),"") -> 14 | T29: =IF(is_cat,ADDRESS(sort_min_row,COLUMN(comb_rank)) & ":" &ADDRESS(sort_max_row,COLUMN(comb_rank)), "") -> $S$29:$S$33 | U29: =IF(is_cat,RANK(comb_rank,INDIRECT(comb_rank_range),1),"") -> 1 | V29: =IF(is_cat,ADDRESS(sort_min_row,COLUMN(comb_rank_norm)) & ":" &ADDRESS(ROW(),COLUMN(comb_rank_norm)), "") -> $U$29:$U$29 | W29: =IF(is_cat,comb_rank_norm+ COUNTIF(INDIRECT(comb_rank_norm_run_range),comb_rank_norm)-1,"") -> 1 | X29: =IF(is_cat,header_row_id+comb_rank_unique,row_id) -> 36 | Y29: =IF(is_empty,"",INDEX($J:$J,MATCH(row_id,$X:$X,0))) -> Emergency Fund | Z29: =IF(is_empty,"",IF(is_header,"Tracked",INDEX($K:$K, MATCH(row_id,$X:$X,0)))) -> 1100 | AA29: =IF(is_empty,"",IF(is_header,"Budget",INDEX($L:$L, MATCH(row_id,$X:$X,0)))) -> 3000 | AB29: =IF(is_empty,"",IF(is_header,"%Compl.",IFERROR(out_tracked/out_budget,"-"))) -> 0.36666667 | AC29: =IF(is_empty,"",IF(is_header,"Remaining",IF(out_budget-out_tracked > 0, out_budget-out_tracked,0))) -> 1900 | AD29: =IF(is_empty,"",IF(is_header,"Excess",IF(out_budget-out_tracked < 0, out_tracked-out_budget,0))) -> 0 | AI29: =Calculations!I39 -> Transport | AJ29: =Calculations!J39 -> 800 | AP29: =Calculations!M39 -> Sinking fund rest | AQ29: =Calculations!N39 -> 250
C30: {=IF(C29=-1,-1, IF(C29<income_max_row,C29+1, IF(C29=income_max_row,income_total_row, IF(C29=income_total_row, "/1", IF(C29="/1",expenses_header_row, IF(C29<expenses_max_row, C29+1, IF(C29=expenses_max_row,expenses_total_row, IF(C29=expenses_total_row,"/2", IF(C29="/2",Savings_header_row, IF(C29<savings_max_row,C29+1, IF(C29=savings_max_row,savings_total_row, -1)))))))))))} -> 37 | D30: =IF(is_header,row_id, IF(NOT(is_empty),D29,-1)) -> 35 | E30: {=1*OR(row_id=income_header_row,row_id=expenses_header_row,row_id=Savings_header_row)} -> 0 | F30: =1*NOT(OR(is_header,is_total,is_empty)) -> 1 | G30: {=1*OR(row_id=income_total_row,row_id=expenses_total_row,row_id=savings_total_row)} -> 0 | H30: =1*OR(row_id="/1",row_id="/2",row_id=-1) -> 0 | I30: {=IFERROR(INDEX(Budget_Planning!$C:$C,header_row_id), " ")} -> Savings | J30: {=IFERROR(INDEX(Budget_Planning!$C:$C,row_id), " ")} -> Retirement Account | K30: {=IF(OR(is_header,is_empty),"", IF(is_total, IF(Selected_period="Total Year", SUM(Tracking[Amount]*(Tracking[Type]=type)*(YEAR(Tracking[Effective Date])=Selected_Year) ), SUM(Tracking[Amount]*(Tracking[Type]=type)*(YEAR(Tracking[Effective Date])=Selected_Year) * (MONTH(Tracking[Effective Date])=Selected_period))), IF(Selected_period="Total Year", SUM(Tracking[Amount]*(Tracking[Type]=type)*(Tracking[Category]=item)*(YEAR(Tracking[Effective Date])=Selected_Year)), SUM(Tracking[Amount]*(Tracking[Type]=type)*(Tracking[Category]=item)*(YEAR(Tracking[Effective Date])=Selected_Year) * (MONTH(Tracking[Effective Date])=Selected_period)) )))} -> 850 | L30: {=IF(OR(is_header,is_empty),"", INDEX(Budget_Planning!$E:$DY,row_id, MATCH(IF(Selected_period="Total Year",Selected_Year,DATE(Selected_Year,Selected_period,1)), Budget_Planning!$E$9:$DY$9, 0)))} -> 4800 | M30: {=IF(is_cat, IF(header_row_id=income_header_row, MATCH(income_min_row,$C:$C,0), IF(header_row_id=expenses_header_row,MATCH(expenses_min_row,$C:$C,0), IF(header_row_id=Savings_header_row,MATCH(savings_min_row,$C:$C,0),""))), "")} -> 29 | N30: {=IF(is_cat, IF(header_row_id=income_header_row, MATCH(income_max_row,$C:$C,0), IF(header_row_id=expenses_header_row,MATCH(expenses_max_row,$C:$C,0), IF(header_row_id=Savings_header_row,MATCH(savings_max_row,$C:$C,0),""))), "")} -> 33 | O30: =IF(is_cat,ADDRESS(sort_min_row,COLUMN(tracked)) &":" & ADDRESS(sort_max_row,COLUMN(tracked)), "") -> $K$29:$K$33 | P30: =IF(is_cat,RANK(tracked,INDIRECT(tracked_range),0), "") -> 2 | Q30: =IF(is_cat,ADDRESS(sort_min_row,COLUMN(budget)) & ":" &ADDRESS(sort_max_row,COLUMN(budget)), "") -> $L$29:$L$33 | R30: =IF(is_cat,RANK(budget,INDIRECT(budget_range),0),"") -> 3 | S30: =IF(is_cat,_xlfn.NUMBERVALUE(tracked_rank& budget_rank),"") -> 23 | T30: =IF(is_cat,ADDRESS(sort_min_row,COLUMN(comb_rank)) & ":" &ADDRESS(sort_max_row,COLUMN(comb_rank)), "") -> $S$29:$S$33 | U30: =IF(is_cat,RANK(comb_rank,INDIRECT(comb_rank_range),1),"") -> 2 | V30: =IF(is_cat,ADDRESS(sort_min_row,COLUMN(comb_rank_norm)) & ":" &ADDRESS(ROW(),COLUMN(comb_rank_norm)), "") -> $U$29:$U$30 | W30: =IF(is_cat,comb_rank_norm+ COUNTIF(INDIRECT(comb_rank_norm_run_range),comb_rank_norm)-1,"") -> 2 | X30: =IF(is_cat,header_row_id+comb_rank_unique,row_id) -> 37 | Y30: =IF(is_empty,"",INDEX($J:$J,MATCH(row_id,$X:$X,0))) -> Retirement Account | Z30: =IF(is_empty,"",IF(is_header,"Tracked",INDEX($K:$K, MATCH(row_id,$X:$X,0)))) -> 850 | AA30: =IF(is_empty,"",IF(is_header,"Budget",INDEX($L:$L, MATCH(row_id,$X:$X,0)))) -> 4800 | AB30: =IF(is_empty,"",IF(is_header,"%Compl.",IFERROR(out_tracked/out_budget,"-"))) -> 0.17708333 | AC30: =IF(is_empty,"",IF(is_header,"Remaining",IF(out_budget-out_tracked > 0, out_budget-out_tracked,0))) -> 3950 | AD30: =IF(is_empty,"",IF(is_header,"Excess",IF(out_budget-out_tracked < 0, out_tracked-out_budget,0))) -> 0 | AI30: =Calculations!I40 -> 0 | AJ30: =Calculations!J40 -> 600 | AP30: =Calculations!M40 -> 0 | AQ30: =Calculations!N40
C31: {=IF(C30=-1,-1, IF(C30<income_max_row,C30+1, IF(C30=income_max_row,income_total_row, IF(C30=income_total_row, "/1", IF(C30="/1",expenses_header_row, IF(C30<expenses_max_row, C30+1, IF(C30=expenses_max_row,expenses_total_row, IF(C30=expenses_total_row,"/2", IF(C30="/2",Savings_header_row, IF(C30<savings_max_row,C30+1, IF(C30=savings_max_row,savings_total_row, -1)))))))))))} -> 38 | D31: =IF(is_header,row_id, IF(NOT(is_empty),D30,-1)) -> 35 | E31: {=1*OR(row_id=income_header_row,row_id=expenses_header_row,row_id=Savings_header_row)} -> 0 | F31: =1*NOT(OR(is_header,is_total,is_empty)) -> 1 | G31: {=1*OR(row_id=income_total_row,row_id=expenses_total_row,row_id=savings_total_row)} -> 0 | H31: =1*OR(row_id="/1",row_id="/2",row_id=-1) -> 0 | I31: {=IFERROR(INDEX(Budget_Planning!$C:$C,header_row_id), " ")} -> Savings | J31: {=IFERROR(INDEX(Budget_Planning!$C:$C,row_id), " ")} -> Stock Portfolio | K31: {=IF(OR(is_header,is_empty),"", IF(is_total, IF(Selected_period="Total Year", SUM(Tracking[Amount]*(Tracking[Type]=type)*(YEAR(Tracking[Effective Date])=Selected_Year) ), SUM(Tracking[Amount]*(Tracking[Type]=type)*(YEAR(Tracking[Effective Date])=Selected_Year) * (MONTH(Tracking[Effective Date])=Selected_period))), IF(Selected_period="Total Year", SUM(Tracking[Amount]*(Tracking[Type]=type)*(Tracking[Category]=item)*(YEAR(Tracking[Effective Date])=Selected_Year)), SUM(Tracking[Amount]*(Tracking[Type]=type)*(Tracking[Category]=item)*(YEAR(Tracking[Effective Date])=Selected_Year) * (MONTH(Tracking[Effective Date])=Selected_period)) )))} -> 300 | L31: {=IF(OR(is_header,is_empty),"", INDEX(Budget_Planning!$E:$DY,row_id, MATCH(IF(Selected_period="Total Year",Selected_Year,DATE(Selected_Year,Selected_period,1)), Budget_Planning!$E$9:$DY$9, 0)))} -> 7200 | M31: {=IF(is_cat, IF(header_row_id=income_header_row, MATCH(income_min_row,$C:$C,0), IF(header_row_id=expenses_header_row,MATCH(expenses_min_row,$C:$C,0), IF(header_row_id=Savings_header_row,MATCH(savings_min_row,$C:$C,0),""))), "")} -> 29 | N31: {=IF(is_cat, IF(header_row_id=income_header_row, MATCH(income_max_row,$C:$C,0), IF(header_row_id=expenses_header_row,MATCH(expenses_max_row,$C:$C,0), IF(header_row_id=Savings_header_row,MATCH(savings_max_row,$C:$C,0),""))), "")} -> 33 | O31: =IF(is_cat,ADDRESS(sort_min_row,COLUMN(tracked)) &":" & ADDRESS(sort_max_row,COLUMN(tracked)), "") -> $K$29:$K$33 | P31: =IF(is_cat,RANK(tracked,INDIRECT(tracked_range),0), "") -> 3 | Q31: =IF(is_cat,ADDRESS(sort_min_row,COLUMN(budget)) & ":" &ADDRESS(sort_max_row,COLUMN(budget)), "") -> $L$29:$L$33 | R31: =IF(is_cat,RANK(budget,INDIRECT(budget_range),0),"") -> 2 | S31: =IF(is_cat,_xlfn.NUMBERVALUE(tracked_rank& budget_rank),"") -> 32 | T31: =IF(is_cat,ADDRESS(sort_min_row,COLUMN(comb_rank)) & ":" &ADDRESS(sort_max_row,COLUMN(comb_rank)), "") -> $S$29:$S$33 | U31: =IF(is_cat,RANK(comb_rank,INDIRECT(comb_rank_range),1),"") -> 3 | V31: =IF(is_cat,ADDRESS(sort_min_row,COLUMN(comb_rank_norm)) & ":" &ADDRESS(ROW(),COLUMN(comb_rank_norm)), "") -> $U$29:$U$31 | W31: =IF(is_cat,comb_rank_norm+ COUNTIF(INDIRECT(comb_rank_norm_run_range),comb_rank_norm)-1,"") -> 3 | X31: =IF(is_cat,header_row_id+comb_rank_unique,row_id) -> 38 | Y31: =IF(is_empty,"",INDEX($J:$J,MATCH(row_id,$X:$X,0))) -> Stock Portfolio | Z31: =IF(is_empty,"",IF(is_header,"Tracked",INDEX($K:$K, MATCH(row_id,$X:$X,0)))) -> 300 | AA31: =IF(is_empty,"",IF(is_header,"Budget",INDEX($L:$L, MATCH(row_id,$X:$X,0)))) -> 7200 | AB31: =IF(is_empty,"",IF(is_header,"%Compl.",IFERROR(out_tracked/out_budget,"-"))) -> 0.041666667 | AC31: =IF(is_empty,"",IF(is_header,"Remaining",IF(out_budget-out_tracked > 0, out_budget-out_tracked,0))) -> 6900 | AD31: =IF(is_empty,"",IF(is_header,"Excess",IF(out_budget-out_tracked < 0, out_tracked-out_budget,0))) -> 0 | AI31: =Calculations!I41 -> Total | AJ31: =Calculations!J41 -> 8270 | AP31: =Calculations!M41 -> Total | AQ31: =Calculations!N41 -> 2750
C32: {=IF(C31=-1,-1, IF(C31<income_max_row,C31+1, IF(C31=income_max_row,income_total_row, IF(C31=income_total_row, "/1", IF(C31="/1",expenses_header_row, IF(C31<expenses_max_row, C31+1, IF(C31=expenses_max_row,expenses_total_row, IF(C31=expenses_total_row,"/2", IF(C31="/2",Savings_header_row, IF(C31<savings_max_row,C31+1, IF(C31=savings_max_row,savings_total_row, -1)))))))))))} -> 39 | D32: =IF(is_header,row_id, IF(NOT(is_empty),D31,-1)) -> 35 | E32: {=1*OR(row_id=income_header_row,row_id=expenses_header_row,row_id=Savings_header_row)} -> 0 | F32: =1*NOT(OR(is_header,is_total,is_empty)) -> 1 | G32: {=1*OR(row_id=income_total_row,row_id=expenses_total_row,row_id=savings_total_row)} -> 0 | H32: =1*OR(row_id="/1",row_id="/2",row_id=-1) -> 0 | I32: {=IFERROR(INDEX(Budget_Planning!$C:$C,header_row_id), " ")} -> Savings | J32: {=IFERROR(INDEX(Budget_Planning!$C:$C,row_id), " ")} -> Sinking Fund | K32: {=IF(OR(is_header,is_empty),"", IF(is_total, IF(Selected_period="Total Year", SUM(Tracking[Amount]*(Tracking[Type]=type)*(YEAR(Tracking[Effective Date])=Selected_Year) ), SUM(Tracking[Amount]*(Tracking[Type]=type)*(YEAR(Tracking[Effective Date])=Selected_Year) * (MONTH(Tracking[Effective Date])=Selected_period))), IF(Selected_period="Total Year", SUM(Tracking[Amount]*(Tracking[Type]=type)*(Tracking[Category]=item)*(YEAR(Tracking[Effective Date])=Selected_Year)), SUM(Tracking[Amount]*(Tracking[Type]=type)*(Tracking[Category]=item)*(YEAR(Tracking[Effective Date])=Selected_Year) * (MONTH(Tracking[Effective Date])=Selected_period)) )))} -> 250 | L32: {=IF(OR(is_header,is_empty),"", INDEX(Budget_Planning!$E:$DY,row_id, MATCH(IF(Selected_period="Total Year",Selected_Year,DATE(Selected_Year,Selected_period,1)), Budget_Planning!$E$9:$DY$9, 0)))} -> 10200 | M32: {=IF(is_cat, IF(header_row_id=income_header_row, MATCH(income_min_row,$C:$C,0), IF(header_row_id=expenses_header_row,MATCH(expenses_min_row,$C:$C,0), IF(header_row_id=Savings_header_row,MATCH(savings_min_row,$C:$C,0),""))), "")} -> 29 | N32: {=IF(is_cat, IF(header_row_id=income_header_row, MATCH(income_max_row,$C:$C,0), IF(header_row_id=expenses_header_row,MATCH(expenses_max_row,$C:$C,0), IF(header_row_id=Savings_header_row,MATCH(savings_max_row,$C:$C,0),""))), "")} -> 33 | O32: =IF(is_cat,ADDRESS(sort_min_row,COLUMN(tracked)) &":" & ADDRESS(sort_max_row,COLUMN(tracked)), "") -> $K$29:$K$33 | P32: =IF(is_cat,RANK(tracked,INDIRECT(tracked_range),0), "") -> 4 | Q32: =IF(is_cat,ADDRESS(sort_min_row,COLUMN(budget)) & ":" &ADDRESS(sort_max_row,COLUMN(budget)), "") -> $L$29:$L$33 | R32: =IF(is_cat,RANK(budget,INDIRECT(budget_range),0),"") -> 1 | S32: =IF(is_cat,_xlfn.NUMBERVALUE(tracked_rank& budget_rank),"") -> 41 | T32: =IF(is_cat,ADDRESS(sort_min_row,COLUMN(comb_rank)) & ":" &ADDRESS(sort_max_row,COLUMN(comb_rank)), "") -> $S$29:$S$33 | U32: =IF(is_cat,RANK(comb_rank,INDIRECT(comb_rank_range),1),"") -> 4 | V32: =IF(is_cat,ADDRESS(sort_min_row,COLUMN(comb_rank_norm)) & ":" &ADDRESS(ROW(),COLUMN(comb_rank_norm)), "") -> $U$29:$U$32 | W32: =IF(is_cat,comb_rank_norm+ COUNTIF(INDIRECT(comb_rank_norm_run_range),comb_rank_norm)-1,"") -> 4 | X32: =IF(is_cat,header_row_id+comb_rank_unique,row_id) -> 39 | Y32: =IF(is_empty,"",INDEX($J:$J,MATCH(row_id,$X:$X,0))) -> Sinking Fund | Z32: =IF(is_empty,"",IF(is_header,"Tracked",INDEX($K:$K, MATCH(row_id,$X:$X,0)))) -> 250 | AA32: =IF(is_empty,"",IF(is_header,"Budget",INDEX($L:$L, MATCH(row_id,$X:$X,0)))) -> 10200 | AB32: =IF(is_empty,"",IF(is_header,"%Compl.",IFERROR(out_tracked/out_budget,"-"))) -> 0.024509804 | AC32: =IF(is_empty,"",IF(is_header,"Remaining",IF(out_budget-out_tracked > 0, out_budget-out_tracked,0))) -> 9950 | AD32: =IF(is_empty,"",IF(is_header,"Excess",IF(out_budget-out_tracked < 0, out_tracked-out_budget,0))) -> 0
C33: {=IF(C32=-1,-1, IF(C32<income_max_row,C32+1, IF(C32=income_max_row,income_total_row, IF(C32=income_total_row, "/1", IF(C32="/1",expenses_header_row, IF(C32<expenses_max_row, C32+1, IF(C32=expenses_max_row,expenses_total_row, IF(C32=expenses_total_row,"/2", IF(C32="/2",Savings_header_row, IF(C32<savings_max_row,C32+1, IF(C32=savings_max_row,savings_total_row, -1)))))))))))} -> 40 | D33: =IF(is_header,row_id, IF(NOT(is_empty),D32,-1)) -> 35 | E33: {=1*OR(row_id=income_header_row,row_id=expenses_header_row,row_id=Savings_header_row)} -> 0 | F33: =1*NOT(OR(is_header,is_total,is_empty)) -> 1 | G33: {=1*OR(row_id=income_total_row,row_id=expenses_total_row,row_id=savings_total_row)} -> 0 | H33: =1*OR(row_id="/1",row_id="/2",row_id=-1) -> 0 | I33: {=IFERROR(INDEX(Budget_Planning!$C:$C,header_row_id), " ")} -> Savings | J33: {=IFERROR(INDEX(Budget_Planning!$C:$C,row_id), " ")} -> Sinking fund rest | K33: {=IF(OR(is_header,is_empty),"", IF(is_total, IF(Selected_period="Total Year", SUM(Tracking[Amount]*(Tracking[Type]=type)*(YEAR(Tracking[Effective Date])=Selected_Year) ), SUM(Tracking[Amount]*(Tracking[Type]=type)*(YEAR(Tracking[Effective Date])=Selected_Year) * (MONTH(Tracking[Effective Date])=Selected_period))), IF(Selected_period="Total Year", SUM(Tracking[Amount]*(Tracking[Type]=type)*(Tracking[Category]=item)*(YEAR(Tracking[Effective Date])=Selected_Year)), SUM(Tracking[Amount]*(Tracking[Type]=type)*(Tracking[Category]=item)*(YEAR(Tracking[Effective Date])=Selected_Year) * (MONTH(Tracking[Effective Date])=Selected_period)) )))} -> 250 | L33: {=IF(OR(is_header,is_empty),"", INDEX(Budget_Planning!$E:$DY,row_id, MATCH(IF(Selected_period="Total Year",Selected_Year,DATE(Selected_Year,Selected_period,1)), Budget_Planning!$E$9:$DY$9, 0)))} -> 1200 | M33: {=IF(is_cat, IF(header_row_id=income_header_row, MATCH(income_min_row,$C:$C,0), IF(header_row_id=expenses_header_row,MATCH(expenses_min_row,$C:$C,0), IF(header_row_id=Savings_header_row,MATCH(savings_min_row,$C:$C,0),""))), "")} -> 29 | N33: {=IF(is_cat, IF(header_row_id=income_header_row, MATCH(income_max_row,$C:$C,0), IF(header_row_id=expenses_header_row,MATCH(expenses_max_row,$C:$C,0), IF(header_row_id=Savings_header_row,MATCH(savings_max_row,$C:$C,0),""))), "")} -> 33 | O33: =IF(is_cat,ADDRESS(sort_min_row,COLUMN(tracked)) &":" & ADDRESS(sort_max_row,COLUMN(tracked)), "") -> $K$29:$K$33 | P33: =IF(is_cat,RANK(tracked,INDIRECT(tracked_range),0), "") -> 4 | Q33: =IF(is_cat,ADDRESS(sort_min_row,COLUMN(budget)) & ":" &ADDRESS(sort_max_row,COLUMN(budget)), "") -> $L$29:$L$33 | R33: =IF(is_cat,RANK(budget,INDIRECT(budget_range),0),"") -> 5 | S33: =IF(is_cat,_xlfn.NUMBERVALUE(tracked_rank& budget_rank),"") -> 45 | T33: =IF(is_cat,ADDRESS(sort_min_row,COLUMN(comb_rank)) & ":" &ADDRESS(sort_max_row,COLUMN(comb_rank)), "") -> $S$29:$S$33 | U33: =IF(is_cat,RANK(comb_rank,INDIRECT(comb_rank_range),1),"") -> 5 | V33: =IF(is_cat,ADDRESS(sort_min_row,COLUMN(comb_rank_norm)) & ":" &ADDRESS(ROW(),COLUMN(comb_rank_norm)), "") -> $U$29:$U$33 | W33: =IF(is_cat,comb_rank_norm+ COUNTIF(INDIRECT(comb_rank_norm_run_range),comb_rank_norm)-1,"") -> 5 | X33: =IF(is_cat,header_row_id+comb_rank_unique,row_id) -> 40 | Y33: =IF(is_empty,"",INDEX($J:$J,MATCH(row_id,$X:$X,0))) -> Sinking fund rest | Z33: =IF(is_empty,"",IF(is_header,"Tracked",INDEX($K:$K, MATCH(row_id,$X:$X,0)))) -> 250 | AA33: =IF(is_empty,"",IF(is_header,"Budget",INDEX($L:$L, MATCH(row_id,$X:$X,0)))) -> 1200 | AB33: =IF(is_empty,"",IF(is_header,"%Compl.",IFERROR(out_tracked/out_budget,"-"))) -> 0.20833333 | AC33: =IF(is_empty,"",IF(is_header,"Remaining",IF(out_budget-out_tracked > 0, out_budget-out_tracked,0))) -> 950 | AD33: =IF(is_empty,"",IF(is_header,"Excess",IF(out_budget-out_tracked < 0, out_tracked-out_budget,0))) -> 0
C34: {=IF(C33=-1,-1, IF(C33<income_max_row,C33+1, IF(C33=income_max_row,income_total_row, IF(C33=income_total_row, "/1", IF(C33="/1",expenses_header_row, IF(C33<expenses_max_row, C33+1, IF(C33=expenses_max_row,expenses_total_row, IF(C33=expenses_total_row,"/2", IF(C33="/2",Savings_header_row, IF(C33<savings_max_row,C33+1, IF(C33=savings_max_row,savings_total_row, -1)))))))))))} -> 46 | D34: =IF(is_header,row_id, IF(NOT(is_empty),D33,-1)) -> 35 | E34: {=1*OR(row_id=income_header_row,row_id=expenses_header_row,row_id=Savings_header_row)} -> 0 | F34: =1*NOT(OR(is_header,is_total,is_empty)) -> 0 | G34: {=1*OR(row_id=income_total_row,row_id=expenses_total_row,row_id=savings_total_row)} -> 1 | H34: =1*OR(row_id="/1",row_id="/2",row_id=-1) -> 0 | I34: {=IFERROR(INDEX(Budget_Planning!$C:$C,header_row_id), " ")} -> Savings | J34: {=IFERROR(INDEX(Budget_Planning!$C:$C,row_id), " ")} -> Total | K34: {=IF(OR(is_header,is_empty),"", IF(is_total, IF(Selected_period="Total Year", SUM(Tracking[Amount]*(Tracking[Type]=type)*(YEAR(Tracking[Effective Date])=Selected_Year) ), SUM(Tracking[Amount]*(Tracking[Type]=type)*(YEAR(Tracking[Effective Date])=Selected_Year) * (MONTH(Tracking[Effective Date])=Selected_period))), IF(Selected_period="Total Year", SUM(Tracking[Amount]*(Tracking[Type]=type)*(Tracking[Category]=item)*(YEAR(Tracking[Effective Date])=Selected_Year)), SUM(Tracking[Amount]*(Tracking[Type]=type)*(Tracking[Category]=item)*(YEAR(Tracking[Effective Date])=Selected_Year) * (MONTH(Tracking[Effective Date])=Selected_period)) )))} -> 2750 | L34: {=IF(OR(is_header,is_empty),"", INDEX(Budget_Planning!$E:$DY,row_id, MATCH(IF(Selected_period="Total Year",Selected_Year,DATE(Selected_Year,Selected_period,1)), Budget_Planning!$E$9:$DY$9, 0)))} -> 26400 | M34: {=IF(is_cat, IF(header_row_id=income_header_row, MATCH(income_min_row,$C:$C,0), IF(header_row_id=expenses_header_row,MATCH(expenses_min_row,$C:$C,0), IF(header_row_id=Savings_header_row,MATCH(savings_min_row,$C:$C,0),""))), "")} | N34: {=IF(is_cat, IF(header_row_id=income_header_row, MATCH(income_max_row,$C:$C,0), IF(header_row_id=expenses_header_row,MATCH(expenses_max_row,$C:$C,0), IF(header_row_id=Savings_header_row,MATCH(savings_max_row,$C:$C,0),""))), "")} | O34: =IF(is_cat,ADDRESS(sort_min_row,COLUMN(tracked)) &":" & ADDRESS(sort_max_row,COLUMN(tracked)), "") | P34: =IF(is_cat,RANK(tracked,INDIRECT(tracked_range),0), "") | Q34: =IF(is_cat,ADDRESS(sort_min_row,COLUMN(budget)) & ":" &ADDRESS(sort_max_row,COLUMN(budget)), "") | R34: =IF(is_cat,RANK(budget,INDIRECT(budget_range),0),"") | S34: =IF(is_cat,_xlfn.NUMBERVALUE(tracked_rank& budget_rank),"") | T34: =IF(is_cat,ADDRESS(sort_min_row,COLUMN(comb_rank)) & ":" &ADDRESS(sort_max_row,COLUMN(comb_rank)), "") | U34: =IF(is_cat,RANK(comb_rank,INDIRECT(comb_rank_range),1),"") | V34: =IF(is_cat,ADDRESS(sort_min_row,COLUMN(comb_rank_norm)) & ":" &ADDRESS(ROW(),COLUMN(comb_rank_norm)), "") | W34: =IF(is_cat,comb_rank_norm+ COUNTIF(INDIRECT(comb_rank_norm_run_range),comb_rank_norm)-1,"") | X34: =IF(is_cat,header_row_id+comb_rank_unique,row_id) -> 46 | Y34: =IF(is_empty,"",INDEX($J:$J,MATCH(row_id,$X:$X,0))) -> Total | Z34: =IF(is_empty,"",IF(is_header,"Tracked",INDEX($K:$K, MATCH(row_id,$X:$X,0)))) -> 2750 | AA34: =IF(is_empty,"",IF(is_header,"Budget",INDEX($L:$L, MATCH(row_id,$X:$X,0)))) -> 26400 | AB34: =IF(is_empty,"",IF(is_header,"%Compl.",IFERROR(out_tracked/out_budget,"-"))) -> 0.10416667 | AC34: =IF(is_empty,"",IF(is_header,"Remaining",IF(out_budget-out_tracked > 0, out_budget-out_tracked,0))) -> 23650 | AD34: =IF(is_empty,"",IF(is_header,"Excess",IF(out_budget-out_tracked < 0, out_tracked-out_budget,0))) -> 0
C35: {=IF(C34=-1,-1, IF(C34<income_max_row,C34+1, IF(C34=income_max_row,income_total_row, IF(C34=income_total_row, "/1", IF(C34="/1",expenses_header_row, IF(C34<expenses_max_row, C34+1, IF(C34=expenses_max_row,expenses_total_row, IF(C34=expenses_total_row,"/2", IF(C34="/2",Savings_header_row, IF(C34<savings_max_row,C34+1, IF(C34=savings_max_row,savings_total_row, -1)))))))))))} -> -1 | D35: =IF(is_header,row_id, IF(NOT(is_empty),D34,-1)) -> -1 | E35: {=1*OR(row_id=income_header_row,row_id=expenses_header_row,row_id=Savings_header_row)} -> 0 | F35: =1*NOT(OR(is_header,is_total,is_empty)) -> 0 | G35: {=1*OR(row_id=income_total_row,row_id=expenses_total_row,row_id=savings_total_row)} -> 0 | H35: =1*OR(row_id="/1",row_id="/2",row_id=-1) -> 1 | I35: {=IFERROR(INDEX(Budget_Planning!$C:$C,header_row_id), " ")} | J35: {=IFERROR(INDEX(Budget_Planning!$C:$C,row_id), " ")} | K35: {=IF(OR(is_header,is_empty),"", IF(is_total, IF(Selected_period="Total Year", SUM(Tracking[Amount]*(Tracking[Type]=type)*(YEAR(Tracking[Effective Date])=Selected_Year) ), SUM(Tracking[Amount]*(Tracking[Type]=type)*(YEAR(Tracking[Effective Date])=Selected_Year) * (MONTH(Tracking[Effective Date])=Selected_period))), IF(Selected_period="Total Year", SUM(Tracking[Amount]*(Tracking[Type]=type)*(Tracking[Category]=item)*(YEAR(Tracking[Effective Date])=Selected_Year)), SUM(Tracking[Amount]*(Tracking[Type]=type)*(Tracking[Category]=item)*(YEAR(Tracking[Effective Date])=Selected_Year) * (MONTH(Tracking[Effective Date])=Selected_period)) )))} | L35: {=IF(OR(is_header,is_empty),"", INDEX(Budget_Planning!$E:$DY,row_id, MATCH(IF(Selected_period="Total Year",Selected_Year,DATE(Selected_Year,Selected_period,1)), Budget_Planning!$E$9:$DY$9, 0)))} | M35: {=IF(is_cat, IF(header_row_id=income_header_row, MATCH(income_min_row,$C:$C,0), IF(header_row_id=expenses_header_row,MATCH(expenses_min_row,$C:$C,0), IF(header_row_id=Savings_header_row,MATCH(savings_min_row,$C:$C,0),""))), "")} | N35: {=IF(is_cat, IF(header_row_id=income_header_row, MATCH(income_max_row,$C:$C,0), IF(header_row_id=expenses_header_row,MATCH(expenses_max_row,$C:$C,0), IF(header_row_id=Savings_header_row,MATCH(savings_max_row,$C:$C,0),""))), "")} | O35: =IF(is_cat,ADDRESS(sort_min_row,COLUMN(tracked)) &":" & ADDRESS(sort_max_row,COLUMN(tracked)), "") | P35: =IF(is_cat,RANK(tracked,INDIRECT(tracked_range),0), "") | Q35: =IF(is_cat,ADDRESS(sort_min_row,COLUMN(budget)) & ":" &ADDRESS(sort_max_row,COLUMN(budget)), "") | R35: =IF(is_cat,RANK(budget,INDIRECT(budget_range),0),"") | S35: =IF(is_cat,_xlfn.NUMBERVALUE(tracked_rank& budget_rank),"") | T35: =IF(is_cat,ADDRESS(sort_min_row,COLUMN(comb_rank)) & ":" &ADDRESS(sort_max_row,COLUMN(comb_rank)), "") | U35: =IF(is_cat,RANK(comb_rank,INDIRECT(comb_rank_range),1),"") | V35: =IF(is_cat,ADDRESS(sort_min_row,COLUMN(comb_rank_norm)) & ":" &ADDRESS(ROW(),COLUMN(comb_rank_norm)), "") | W35: =IF(is_cat,comb_rank_norm+ COUNTIF(INDIRECT(comb_rank_norm_run_range),comb_rank_norm)-1,"") | X35: =IF(is_cat,header_row_id+comb_rank_unique,row_id) -> -1 | Y35: =IF(is_empty,"",INDEX($J:$J,MATCH(row_id,$X:$X,0))) | Z35: =IF(is_empty,"",IF(is_header,"Tracked",INDEX($K:$K, MATCH(row_id,$X:$X,0)))) | AA35: =IF(is_empty,"",IF(is_header,"Budget",INDEX($L:$L, MATCH(row_id,$X:$X,0)))) | AB35: =IF(is_empty,"",IF(is_header,"%Compl.",IFERROR(out_tracked/out_budget,"-"))) | AC35: =IF(is_empty,"",IF(is_header,"Remaining",IF(out_budget-out_tracked > 0, out_budget-out_tracked,0))) | AD35: =IF(is_empty,"",IF(is_header,"Excess",IF(out_budget-out_tracked < 0, out_tracked-out_budget,0)))
C36: {=IF(C35=-1,-1, IF(C35<income_max_row,C35+1, IF(C35=income_max_row,income_total_row, IF(C35=income_total_row, "/1", IF(C35="/1",expenses_header_row, IF(C35<expenses_max_row, C35+1, IF(C35=expenses_max_row,expenses_total_row, IF(C35=expenses_total_row,"/2", IF(C35="/2",Savings_header_row, IF(C35<savings_max_row,C35+1, IF(C35=savings_max_row,savings_total_row, -1)))))))))))} -> -1 | D36: =IF(is_header,row_id, IF(NOT(is_empty),D35,-1)) -> -1 | E36: {=1*OR(row_id=income_header_row,row_id=expenses_header_row,row_id=Savings_header_row)} -> 0 | F36: =1*NOT(OR(is_header,is_total,is_empty)) -> 0 | G36: {=1*OR(row_id=income_total_row,row_id=expenses_total_row,row_id=savings_total_row)} -> 0 | H36: =1*OR(row_id="/1",row_id="/2",row_id=-1) -> 1 | I36: {=IFERROR(INDEX(Budget_Planning!$C:$C,header_row_id), " ")} | J36: {=IFERROR(INDEX(Budget_Planning!$C:$C,row_id), " ")} | K36: {=IF(OR(is_header,is_empty),"", IF(is_total, IF(Selected_period="Total Year", SUM(Tracking[Amount]*(Tracking[Type]=type)*(YEAR(Tracking[Effective Date])=Selected_Year) ), SUM(Tracking[Amount]*(Tracking[Type]=type)*(YEAR(Tracking[Effective Date])=Selected_Year) * (MONTH(Tracking[Effective Date])=Selected_period))), IF(Selected_period="Total Year", SUM(Tracking[Amount]*(Tracking[Type]=type)*(Tracking[Category]=item)*(YEAR(Tracking[Effective Date])=Selected_Year)), SUM(Tracking[Amount]*(Tracking[Type]=type)*(Tracking[Category]=item)*(YEAR(Tracking[Effective Date])=Selected_Year) * (MONTH(Tracking[Effective Date])=Selected_period)) )))} | L36: {=IF(OR(is_header,is_empty),"", INDEX(Budget_Planning!$E:$DY,row_id, MATCH(IF(Selected_period="Total Year",Selected_Year,DATE(Selected_Year,Selected_period,1)), Budget_Planning!$E$9:$DY$9, 0)))} | M36: {=IF(is_cat, IF(header_row_id=income_header_row, MATCH(income_min_row,$C:$C,0), IF(header_row_id=expenses_header_row,MATCH(expenses_min_row,$C:$C,0), IF(header_row_id=Savings_header_row,MATCH(savings_min_row,$C:$C,0),""))), "")} | N36: {=IF(is_cat, IF(header_row_id=income_header_row, MATCH(income_max_row,$C:$C,0), IF(header_row_id=expenses_header_row,MATCH(expenses_max_row,$C:$C,0), IF(header_row_id=Savings_header_row,MATCH(savings_max_row,$C:$C,0),""))), "")} | O36: =IF(is_cat,ADDRESS(sort_min_row,COLUMN(tracked)) &":" & ADDRESS(sort_max_row,COLUMN(tracked)), "") | P36: =IF(is_cat,RANK(tracked,INDIRECT(tracked_range),0), "") | Q36: =IF(is_cat,ADDRESS(sort_min_row,COLUMN(budget)) & ":" &ADDRESS(sort_max_row,COLUMN(budget)), "") | R36: =IF(is_cat,RANK(budget,INDIRECT(budget_range),0),"") | S36: =IF(is_cat,_xlfn.NUMBERVALUE(tracked_rank& budget_rank),"") | T36: =IF(is_cat,ADDRESS(sort_min_row,COLUMN(comb_rank)) & ":" &ADDRESS(sort_max_row,COLUMN(comb_rank)), "") | U36: =IF(is_cat,RANK(comb_rank,INDIRECT(comb_rank_range),1),"") | V36: =IF(is_cat,ADDRESS(sort_min_row,COLUMN(comb_rank_norm)) & ":" &ADDRESS(ROW(),COLUMN(comb_rank_norm)), "") | W36: =IF(is_cat,comb_rank_norm+ COUNTIF(INDIRECT(comb_rank_norm_run_range),comb_rank_norm)-1,"") | X36: =IF(is_cat,header_row_id+comb_rank_unique,row_id) -> -1 | Y36: =IF(is_empty,"",INDEX($J:$J,MATCH(row_id,$X:$X,0))) | Z36: =IF(is_empty,"",IF(is_header,"Tracked",INDEX($K:$K, MATCH(row_id,$X:$X,0)))) | AA36: =IF(is_empty,"",IF(is_header,"Budget",INDEX($L:$L, MATCH(row_id,$X:$X,0)))) | AB36: =IF(is_empty,"",IF(is_header,"%Compl.",IFERROR(out_tracked/out_budget,"-"))) | AC36: =IF(is_empty,"",IF(is_header,"Remaining",IF(out_budget-out_tracked > 0, out_budget-out_tracked,0))) | AD36: =IF(is_empty,"",IF(is_header,"Excess",IF(out_budget-out_tracked < 0, out_tracked-out_budget,0)))
C37: {=IF(C36=-1,-1, IF(C36<income_max_row,C36+1, IF(C36=income_max_row,income_total_row, IF(C36=income_total_row, "/1", IF(C36="/1",expenses_header_row, IF(C36<expenses_max_row, C36+1, IF(C36=expenses_max_row,expenses_total_row, IF(C36=expenses_total_row,"/2", IF(C36="/2",Savings_header_row, IF(C36<savings_max_row,C36+1, IF(C36=savings_max_row,savings_total_row, -1)))))))))))} -> -1 | D37: =IF(is_header,row_id, IF(NOT(is_empty),D36,-1)) -> -1 | E37: {=1*OR(row_id=income_header_row,row_id=expenses_header_row,row_id=Savings_header_row)} -> 0 | F37: =1*NOT(OR(is_header,is_total,is_empty)) -> 0 | G37: {=1*OR(row_id=income_total_row,row_id=expenses_total_row,row_id=savings_total_row)} -> 0 | H37: =1*OR(row_id="/1",row_id="/2",row_id=-1) -> 1 | I37: {=IFERROR(INDEX(Budget_Planning!$C:$C,header_row_id), " ")} | J37: {=IFERROR(INDEX(Budget_Planning!$C:$C,row_id), " ")} | K37: {=IF(OR(is_header,is_empty),"", IF(is_total, IF(Selected_period="Total Year", SUM(Tracking[Amount]*(Tracking[Type]=type)*(YEAR(Tracking[Effective Date])=Selected_Year) ), SUM(Tracking[Amount]*(Tracking[Type]=type)*(YEAR(Tracking[Effective Date])=Selected_Year) * (MONTH(Tracking[Effective Date])=Selected_period))), IF(Selected_period="Total Year", SUM(Tracking[Amount]*(Tracking[Type]=type)*(Tracking[Category]=item)*(YEAR(Tracking[Effective Date])=Selected_Year)), SUM(Tracking[Amount]*(Tracking[Type]=type)*(Tracking[Category]=item)*(YEAR(Tracking[Effective Date])=Selected_Year) * (MONTH(Tracking[Effective Date])=Selected_period)) )))} | L37: {=IF(OR(is_header,is_empty),"", INDEX(Budget_Planning!$E:$DY,row_id, MATCH(IF(Selected_period="Total Year",Selected_Year,DATE(Selected_Year,Selected_period,1)), Budget_Planning!$E$9:$DY$9, 0)))} | M37: {=IF(is_cat, IF(header_row_id=income_header_row, MATCH(income_min_row,$C:$C,0), IF(header_row_id=expenses_header_row,MATCH(expenses_min_row,$C:$C,0), IF(header_row_id=Savings_header_row,MATCH(savings_min_row,$C:$C,0),""))), "")} | N37: {=IF(is_cat, IF(header_row_id=income_header_row, MATCH(income_max_row,$C:$C,0), IF(header_row_id=expenses_header_row,MATCH(expenses_max_row,$C:$C,0), IF(header_row_id=Savings_header_row,MATCH(savings_max_row,$C:$C,0),""))), "")} | O37: =IF(is_cat,ADDRESS(sort_min_row,COLUMN(tracked)) &":" & ADDRESS(sort_max_row,COLUMN(tracked)), "") | P37: =IF(is_cat,RANK(tracked,INDIRECT(tracked_range),0), "") | Q37: =IF(is_cat,ADDRESS(sort_min_row,COLUMN(budget)) & ":" &ADDRESS(sort_max_row,COLUMN(budget)), "") | R37: =IF(is_cat,RANK(budget,INDIRECT(budget_range),0),"") | S37: =IF(is_cat,_xlfn.NUMBERVALUE(tracked_rank& budget_rank),"") | T37: =IF(is_cat,ADDRESS(sort_min_row,COLUMN(comb_rank)) & ":" &ADDRESS(sort_max_row,COLUMN(comb_rank)), "") | U37: =IF(is_cat,RANK(comb_rank,INDIRECT(comb_rank_range),1),"") | V37: =IF(is_cat,ADDRESS(sort_min_row,COLUMN(comb_rank_norm)) & ":" &ADDRESS(ROW(),COLUMN(comb_rank_norm)), "") | W37: =IF(is_cat,comb_rank_norm+ COUNTIF(INDIRECT(comb_rank_norm_run_range),comb_rank_norm)-1,"") | X37: =IF(is_cat,header_row_id+comb_rank_unique,row_id) -> -1 | Y37: =IF(is_empty,"",INDEX($J:$J,MATCH(row_id,$X:$X,0))) | Z37: =IF(is_empty,"",IF(is_header,"Tracked",INDEX($K:$K, MATCH(row_id,$X:$X,0)))) | AA37: =IF(is_empty,"",IF(is_header,"Budget",INDEX($L:$L, MATCH(row_id,$X:$X,0)))) | AB37: =IF(is_empty,"",IF(is_header,"%Compl.",IFERROR(out_tracked/out_budget,"-"))) | AC37: =IF(is_empty,"",IF(is_header,"Remaining",IF(out_budget-out_tracked > 0, out_budget-out_tracked,0))) | AD37: =IF(is_empty,"",IF(is_header,"Excess",IF(out_budget-out_tracked < 0, out_tracked-out_budget,0)))
C38: {=IF(C37=-1,-1, IF(C37<income_max_row,C37+1, IF(C37=income_max_row,income_total_row, IF(C37=income_total_row, "/1", IF(C37="/1",expenses_header_row, IF(C37<expenses_max_row, C37+1, IF(C37=expenses_max_row,expenses_total_row, IF(C37=expenses_total_row,"/2", IF(C37="/2",Savings_header_row, IF(C37<savings_max_row,C37+1, IF(C37=savings_max_row,savings_total_row, -1)))))))))))} -> -1 | D38: =IF(is_header,row_id, IF(NOT(is_empty),D37,-1)) -> -1 | E38: {=1*OR(row_id=income_header_row,row_id=expenses_header_row,row_id=Savings_header_row)} -> 0 | F38: =1*NOT(OR(is_header,is_total,is_empty)) -> 0 | G38: {=1*OR(row_id=income_total_row,row_id=expenses_total_row,row_id=savings_total_row)} -> 0 | H38: =1*OR(row_id="/1",row_id="/2",row_id=-1) -> 1 | I38: {=IFERROR(INDEX(Budget_Planning!$C:$C,header_row_id), " ")} | J38: {=IFERROR(INDEX(Budget_Planning!$C:$C,row_id), " ")} | K38: {=IF(OR(is_header,is_empty),"", IF(is_total, IF(Selected_period="Total Year", SUM(Tracking[Amount]*(Tracking[Type]=type)*(YEAR(Tracking[Effective Date])=Selected_Year) ), SUM(Tracking[Amount]*(Tracking[Type]=type)*(YEAR(Tracking[Effective Date])=Selected_Year) * (MONTH(Tracking[Effective Date])=Selected_period))), IF(Selected_period="Total Year", SUM(Tracking[Amount]*(Tracking[Type]=type)*(Tracking[Category]=item)*(YEAR(Tracking[Effective Date])=Selected_Year)), SUM(Tracking[Amount]*(Tracking[Type]=type)*(Tracking[Category]=item)*(YEAR(Tracking[Effective Date])=Selected_Year) * (MONTH(Tracking[Effective Date])=Selected_period)) )))} | L38: {=IF(OR(is_header,is_empty),"", INDEX(Budget_Planning!$E:$DY,row_id, MATCH(IF(Selected_period="Total Year",Selected_Year,DATE(Selected_Year,Selected_period,1)), Budget_Planning!$E$9:$DY$9, 0)))} | M38: {=IF(is_cat, IF(header_row_id=income_header_row, MATCH(income_min_row,$C:$C,0), IF(header_row_id=expenses_header_row,MATCH(expenses_min_row,$C:$C,0), IF(header_row_id=Savings_header_row,MATCH(savings_min_row,$C:$C,0),""))), "")} | N38: {=IF(is_cat, IF(header_row_id=income_header_row, MATCH(income_max_row,$C:$C,0), IF(header_row_id=expenses_header_row,MATCH(expenses_max_row,$C:$C,0), IF(header_row_id=Savings_header_row,MATCH(savings_max_row,$C:$C,0),""))), "")} | O38: =IF(is_cat,ADDRESS(sort_min_row,COLUMN(tracked)) &":" & ADDRESS(sort_max_row,COLUMN(tracked)), "") | P38: =IF(is_cat,RANK(tracked,INDIRECT(tracked_range),0), "") | Q38: =IF(is_cat,ADDRESS(sort_min_row,COLUMN(budget)) & ":" &ADDRESS(sort_max_row,COLUMN(budget)), "") | R38: =IF(is_cat,RANK(budget,INDIRECT(budget_range),0),"") | S38: =IF(is_cat,_xlfn.NUMBERVALUE(tracked_rank& budget_rank),"") | T38: =IF(is_cat,ADDRESS(sort_min_row,COLUMN(comb_rank)) & ":" &ADDRESS(sort_max_row,COLUMN(comb_rank)), "") | U38: =IF(is_cat,RANK(comb_rank,INDIRECT(comb_rank_range),1),"") | V38: =IF(is_cat,ADDRESS(sort_min_row,COLUMN(comb_rank_norm)) & ":" &ADDRESS(ROW(),COLUMN(comb_rank_norm)), "") | W38: =IF(is_cat,comb_rank_norm+ COUNTIF(INDIRECT(comb_rank_norm_run_range),comb_rank_norm)-1,"") | X38: =IF(is_cat,header_row_id+comb_rank_unique,row_id) -> -1 | Y38: =IF(is_empty,"",INDEX($J:$J,MATCH(row_id,$X:$X,0))) | Z38: =IF(is_empty,"",IF(is_header,"Tracked",INDEX($K:$K, MATCH(row_id,$X:$X,0)))) | AA38: =IF(is_empty,"",IF(is_header,"Budget",INDEX($L:$L, MATCH(row_id,$X:$X,0)))) | AB38: =IF(is_empty,"",IF(is_header,"%Compl.",IFERROR(out_tracked/out_budget,"-"))) | AC38: =IF(is_empty,"",IF(is_header,"Remaining",IF(out_budget-out_tracked > 0, out_budget-out_tracked,0))) | AD38: =IF(is_empty,"",IF(is_header,"Excess",IF(out_budget-out_tracked < 0, out_tracked-out_budget,0)))
C39: {=IF(C38=-1,-1, IF(C38<income_max_row,C38+1, IF(C38=income_max_row,income_total_row, IF(C38=income_total_row, "/1", IF(C38="/1",expenses_header_row, IF(C38<expenses_max_row, C38+1, IF(C38=expenses_max_row,expenses_total_row, IF(C38=expenses_total_row,"/2", IF(C38="/2",Savings_header_row, IF(C38<savings_max_row,C38+1, IF(C38=savings_max_row,savings_total_row, -1)))))))))))} -> -1 | D39: =IF(is_header,row_id, IF(NOT(is_empty),D38,-1)) -> -1 | E39: {=1*OR(row_id=income_header_row,row_id=expenses_header_row,row_id=Savings_header_row)} -> 0 | F39: =1*NOT(OR(is_header,is_total,is_empty)) -> 0 | G39: {=1*OR(row_id=income_total_row,row_id=expenses_total_row,row_id=savings_total_row)} -> 0 | H39: =1*OR(row_id="/1",row_id="/2",row_id=-1) -> 1 | I39: {=IFERROR(INDEX(Budget_Planning!$C:$C,header_row_id), " ")} | J39: {=IFERROR(INDEX(Budget_Planning!$C:$C,row_id), " ")} | K39: {=IF(OR(is_header,is_empty),"", IF(is_total, IF(Selected_period="Total Year", SUM(Tracking[Amount]*(Tracking[Type]=type)*(YEAR(Tracking[Effective Date])=Selected_Year) ), SUM(Tracking[Amount]*(Tracking[Type]=type)*(YEAR(Tracking[Effective Date])=Selected_Year) * (MONTH(Tracking[Effective Date])=Selected_period))), IF(Selected_period="Total Year", SUM(Tracking[Amount]*(Tracking[Type]=type)*(Tracking[Category]=item)*(YEAR(Tracking[Effective Date])=Selected_Year)), SUM(Tracking[Amount]*(Tracking[Type]=type)*(Tracking[Category]=item)*(YEAR(Tracking[Effective Date])=Selected_Year) * (MONTH(Tracking[Effective Date])=Selected_period)) )))} | L39: {=IF(OR(is_header,is_empty),"", INDEX(Budget_Planning!$E:$DY,row_id, MATCH(IF(Selected_period="Total Year",Selected_Year,DATE(Selected_Year,Selected_period,1)), Budget_Planning!$E$9:$DY$9, 0)))} | M39: {=IF(is_cat, IF(header_row_id=income_header_row, MATCH(income_min_row,$C:$C,0), IF(header_row_id=expenses_header_row,MATCH(expenses_min_row,$C:$C,0), IF(header_row_id=Savings_header_row,MATCH(savings_min_row,$C:$C,0),""))), "")} | N39: {=IF(is_cat, IF(header_row_id=income_header_row, MATCH(income_max_row,$C:$C,0), IF(header_row_id=expenses_header_row,MATCH(expenses_max_row,$C:$C,0), IF(header_row_id=Savings_header_row,MATCH(savings_max_row,$C:$C,0),""))), "")} | O39: =IF(is_cat,ADDRESS(sort_min_row,COLUMN(tracked)) &":" & ADDRESS(sort_max_row,COLUMN(tracked)), "") | P39: =IF(is_cat,RANK(tracked,INDIRECT(tracked_range),0), "") | Q39: =IF(is_cat,ADDRESS(sort_min_row,COLUMN(budget)) & ":" &ADDRESS(sort_max_row,COLUMN(budget)), "") | R39: =IF(is_cat,RANK(budget,INDIRECT(budget_range),0),"") | S39: =IF(is_cat,_xlfn.NUMBERVALUE(tracked_rank& budget_rank),"") | T39: =IF(is_cat,ADDRESS(sort_min_row,COLUMN(comb_rank)) & ":" &ADDRESS(sort_max_row,COLUMN(comb_rank)), "") | U39: =IF(is_cat,RANK(comb_rank,INDIRECT(comb_rank_range),1),"") | V39: =IF(is_cat,ADDRESS(sort_min_row,COLUMN(comb_rank_norm)) & ":" &ADDRESS(ROW(),COLUMN(comb_rank_norm)), "") | W39: =IF(is_cat,comb_rank_norm+ COUNTIF(INDIRECT(comb_rank_norm_run_range),comb_rank_norm)-1,"") | X39: =IF(is_cat,header_row_id+comb_rank_unique,row_id) -> -1 | Y39: =IF(is_empty,"",INDEX($J:$J,MATCH(row_id,$X:$X,0))) | Z39: =IF(is_empty,"",IF(is_header,"Tracked",INDEX($K:$K, MATCH(row_id,$X:$X,0)))) | AA39: =IF(is_empty,"",IF(is_header,"Budget",INDEX($L:$L, MATCH(row_id,$X:$X,0)))) | AB39: =IF(is_empty,"",IF(is_header,"%Compl.",IFERROR(out_tracked/out_budget,"-"))) | AC39: =IF(is_empty,"",IF(is_header,"Remaining",IF(out_budget-out_tracked > 0, out_budget-out_tracked,0))) | AD39: =IF(is_empty,"",IF(is_header,"Excess",IF(out_budget-out_tracked < 0, out_tracked-out_budget,0)))
C40: {=IF(C39=-1,-1, IF(C39<income_max_row,C39+1, IF(C39=income_max_row,income_total_row, IF(C39=income_total_row, "/1", IF(C39="/1",expenses_header_row, IF(C39<expenses_max_row, C39+1, IF(C39=expenses_max_row,expenses_total_row, IF(C39=expenses_total_row,"/2", IF(C39="/2",Savings_header_row, IF(C39<savings_max_row,C39+1, IF(C39=savings_max_row,savings_total_row, -1)))))))))))} -> -1 | D40: =IF(is_header,row_id, IF(NOT(is_empty),D39,-1)) -> -1 | E40: {=1*OR(row_id=income_header_row,row_id=expenses_header_row,row_id=Savings_header_row)} -> 0 | F40: =1*NOT(OR(is_header,is_total,is_empty)) -> 0 | G40: {=1*OR(row_id=income_total_row,row_id=expenses_total_row,row_id=savings_total_row)} -> 0 | H40: =1*OR(row_id="/1",row_id="/2",row_id=-1) -> 1 | I40: {=IFERROR(INDEX(Budget_Planning!$C:$C,header_row_id), " ")} | J40: {=IFERROR(INDEX(Budget_Planning!$C:$C,row_id), " ")} | K40: {=IF(OR(is_header,is_empty),"", IF(is_total, IF(Selected_period="Total Year", SUM(Tracking[Amount]*(Tracking[Type]=type)*(YEAR(Tracking[Effective Date])=Selected_Year) ), SUM(Tracking[Amount]*(Tracking[Type]=type)*(YEAR(Tracking[Effective Date])=Selected_Year) * (MONTH(Tracking[Effective Date])=Selected_period))), IF(Selected_period="Total Year", SUM(Tracking[Amount]*(Tracking[Type]=type)*(Tracking[Category]=item)*(YEAR(Tracking[Effective Date])=Selected_Year)), SUM(Tracking[Amount]*(Tracking[Type]=type)*(Tracking[Category]=item)*(YEAR(Tracking[Effective Date])=Selected_Year) * (MONTH(Tracking[Effective Date])=Selected_period)) )))} | L40: {=IF(OR(is_header,is_empty),"", INDEX(Budget_Planning!$E:$DY,row_id, MATCH(IF(Selected_period="Total Year",Selected_Year,DATE(Selected_Year,Selected_period,1)), Budget_Planning!$E$9:$DY$9, 0)))} | M40: {=IF(is_cat, IF(header_row_id=income_header_row, MATCH(income_min_row,$C:$C,0), IF(header_row_id=expenses_header_row,MATCH(expenses_min_row,$C:$C,0), IF(header_row_id=Savings_header_row,MATCH(savings_min_row,$C:$C,0),""))), "")} | N40: {=IF(is_cat, IF(header_row_id=income_header_row, MATCH(income_max_row,$C:$C,0), IF(header_row_id=expenses_header_row,MATCH(expenses_max_row,$C:$C,0), IF(header_row_id=Savings_header_row,MATCH(savings_max_row,$C:$C,0),""))), "")} | O40: =IF(is_cat,ADDRESS(sort_min_row,COLUMN(tracked)) &":" & ADDRESS(sort_max_row,COLUMN(tracked)), "") | P40: =IF(is_cat,RANK(tracked,INDIRECT(tracked_range),0), "") | Q40: =IF(is_cat,ADDRESS(sort_min_row,COLUMN(budget)) & ":" &ADDRESS(sort_max_row,COLUMN(budget)), "") | R40: =IF(is_cat,RANK(budget,INDIRECT(budget_range),0),"") | S40: =IF(is_cat,_xlfn.NUMBERVALUE(tracked_rank& budget_rank),"") | T40: =IF(is_cat,ADDRESS(sort_min_row,COLUMN(comb_rank)) & ":" &ADDRESS(sort_max_row,COLUMN(comb_rank)), "") | U40: =IF(is_cat,RANK(comb_rank,INDIRECT(comb_rank_range),1),"") | V40: =IF(is_cat,ADDRESS(sort_min_row,COLUMN(comb_rank_norm)) & ":" &ADDRESS(ROW(),COLUMN(comb_rank_norm)), "") | W40: =IF(is_cat,comb_rank_norm+ COUNTIF(INDIRECT(comb_rank_norm_run_range),comb_rank_norm)-1,"") | X40: =IF(is_cat,header_row_id+comb_rank_unique,row_id) -> -1 | Y40: =IF(is_empty,"",INDEX($J:$J,MATCH(row_id,$X:$X,0))) | Z40: =IF(is_empty,"",IF(is_header,"Tracked",INDEX($K:$K, MATCH(row_id,$X:$X,0)))) | AA40: =IF(is_empty,"",IF(is_header,"Budget",INDEX($L:$L, MATCH(row_id,$X:$X,0)))) | AB40: =IF(is_empty,"",IF(is_header,"%Compl.",IFERROR(out_tracked/out_budget,"-"))) | AC40: =IF(is_empty,"",IF(is_header,"Remaining",IF(out_budget-out_tracked > 0, out_budget-out_tracked,0))) | AD40: =IF(is_empty,"",IF(is_header,"Excess",IF(out_budget-out_tracked < 0, out_tracked-out_budget,0)))
C41: {=IF(C40=-1,-1, IF(C40<income_max_row,C40+1, IF(C40=income_max_row,income_total_row, IF(C40=income_total_row, "/1", IF(C40="/1",expenses_header_row, IF(C40<expenses_max_row, C40+1, IF(C40=expenses_max_row,expenses_total_row, IF(C40=expenses_total_row,"/2", IF(C40="/2",Savings_header_row, IF(C40<savings_max_row,C40+1, IF(C40=savings_max_row,savings_total_row, -1)))))))))))} -> -1 | D41: =IF(is_header,row_id, IF(NOT(is_empty),D40,-1)) -> -1 | E41: {=1*OR(row_id=income_header_row,row_id=expenses_header_row,row_id=Savings_header_row)} -> 0 | F41: =1*NOT(OR(is_header,is_total,is_empty)) -> 0 | G41: {=1*OR(row_id=income_total_row,row_id=expenses_total_row,row_id=savings_total_row)} -> 0 | H41: =1*OR(row_id="/1",row_id="/2",row_id=-1) -> 1 | I41: {=IFERROR(INDEX(Budget_Planning!$C:$C,header_row_id), " ")} | J41: {=IFERROR(INDEX(Budget_Planning!$C:$C,row_id), " ")} | K41: {=IF(OR(is_header,is_empty),"", IF(is_total, IF(Selected_period="Total Year", SUM(Tracking[Amount]*(Tracking[Type]=type)*(YEAR(Tracking[Effective Date])=Selected_Year) ), SUM(Tracking[Amount]*(Tracking[Type]=type)*(YEAR(Tracking[Effective Date])=Selected_Year) * (MONTH(Tracking[Effective Date])=Selected_period))), IF(Selected_period="Total Year", SUM(Tracking[Amount]*(Tracking[Type]=type)*(Tracking[Category]=item)*(YEAR(Tracking[Effective Date])=Selected_Year)), SUM(Tracking[Amount]*(Tracking[Type]=type)*(Tracking[Category]=item)*(YEAR(Tracking[Effective Date])=Selected_Year) * (MONTH(Tracking[Effective Date])=Selected_period)) )))} | L41: {=IF(OR(is_header,is_empty),"", INDEX(Budget_Planning!$E:$DY,row_id, MATCH(IF(Selected_period="Total Year",Selected_Year,DATE(Selected_Year,Selected_period,1)), Budget_Planning!$E$9:$DY$9, 0)))} | M41: {=IF(is_cat, IF(header_row_id=income_header_row, MATCH(income_min_row,$C:$C,0), IF(header_row_id=expenses_header_row,MATCH(expenses_min_row,$C:$C,0), IF(header_row_id=Savings_header_row,MATCH(savings_min_row,$C:$C,0),""))), "")} | N41: {=IF(is_cat, IF(header_row_id=income_header_row, MATCH(income_max_row,$C:$C,0), IF(header_row_id=expenses_header_row,MATCH(expenses_max_row,$C:$C,0), IF(header_row_id=Savings_header_row,MATCH(savings_max_row,$C:$C,0),""))), "")} | O41: =IF(is_cat,ADDRESS(sort_min_row,COLUMN(tracked)) &":" & ADDRESS(sort_max_row,COLUMN(tracked)), "") | P41: =IF(is_cat,RANK(tracked,INDIRECT(tracked_range),0), "") | Q41: =IF(is_cat,ADDRESS(sort_min_row,COLUMN(budget)) & ":" &ADDRESS(sort_max_row,COLUMN(budget)), "") | R41: =IF(is_cat,RANK(budget,INDIRECT(budget_range),0),"") | S41: =IF(is_cat,_xlfn.NUMBERVALUE(tracked_rank& budget_rank),"") | T41: =IF(is_cat,ADDRESS(sort_min_row,COLUMN(comb_rank)) & ":" &ADDRESS(sort_max_row,COLUMN(comb_rank)), "") | U41: =IF(is_cat,RANK(comb_rank,INDIRECT(comb_rank_range),1),"") | V41: =IF(is_cat,ADDRESS(sort_min_row,COLUMN(comb_rank_norm)) & ":" &ADDRESS(ROW(),COLUMN(comb_rank_norm)), "") | W41: =IF(is_cat,comb_rank_norm+ COUNTIF(INDIRECT(comb_rank_norm_run_range),comb_rank_norm)-1,"") | X41: =IF(is_cat,header_row_id+comb_rank_unique,row_id) -> -1 | Y41: =IF(is_empty,"",INDEX($J:$J,MATCH(row_id,$X:$X,0))) | Z41: =IF(is_empty,"",IF(is_header,"Tracked",INDEX($K:$K, MATCH(row_id,$X:$X,0)))) | AA41: =IF(is_empty,"",IF(is_header,"Budget",INDEX($L:$L, MATCH(row_id,$X:$X,0)))) | AB41: =IF(is_empty,"",IF(is_header,"%Compl.",IFERROR(out_tracked/out_budget,"-"))) | AC41: =IF(is_empty,"",IF(is_header,"Remaining",IF(out_budget-out_tracked > 0, out_budget-out_tracked,0))) | AD41: =IF(is_empty,"",IF(is_header,"Excess",IF(out_budget-out_tracked < 0, out_tracked-out_budget,0)))
C42: {=IF(C41=-1,-1, IF(C41<income_max_row,C41+1, IF(C41=income_max_row,income_total_row, IF(C41=income_total_row, "/1", IF(C41="/1",expenses_header_row, IF(C41<expenses_max_row, C41+1, IF(C41=expenses_max_row,expenses_total_row, IF(C41=expenses_total_row,"/2", IF(C41="/2",Savings_header_row, IF(C41<savings_max_row,C41+1, IF(C41=savings_max_row,savings_total_row, -1)))))))))))} -> -1 | D42: =IF(is_header,row_id, IF(NOT(is_empty),D41,-1)) -> -1 | E42: {=1*OR(row_id=income_header_row,row_id=expenses_header_row,row_id=Savings_header_row)} -> 0 | F42: =1*NOT(OR(is_header,is_total,is_empty)) -> 0 | G42: {=1*OR(row_id=income_total_row,row_id=expenses_total_row,row_id=savings_total_row)} -> 0 | H42: =1*OR(row_id="/1",row_id="/2",row_id=-1) -> 1 | I42: {=IFERROR(INDEX(Budget_Planning!$C:$C,header_row_id), " ")} | J42: {=IFERROR(INDEX(Budget_Planning!$C:$C,row_id), " ")} | K42: {=IF(OR(is_header,is_empty),"", IF(is_total, IF(Selected_period="Total Year", SUM(Tracking[Amount]*(Tracking[Type]=type)*(YEAR(Tracking[Effective Date])=Selected_Year) ), SUM(Tracking[Amount]*(Tracking[Type]=type)*(YEAR(Tracking[Effective Date])=Selected_Year) * (MONTH(Tracking[Effective Date])=Selected_period))), IF(Selected_period="Total Year", SUM(Tracking[Amount]*(Tracking[Type]=type)*(Tracking[Category]=item)*(YEAR(Tracking[Effective Date])=Selected_Year)), SUM(Tracking[Amount]*(Tracking[Type]=type)*(Tracking[Category]=item)*(YEAR(Tracking[Effective Date])=Selected_Year) * (MONTH(Tracking[Effective Date])=Selected_period)) )))} | L42: {=IF(OR(is_header,is_empty),"", INDEX(Budget_Planning!$E:$DY,row_id, MATCH(IF(Selected_period="Total Year",Selected_Year,DATE(Selected_Year,Selected_period,1)), Budget_Planning!$E$9:$DY$9, 0)))} | M42: {=IF(is_cat, IF(header_row_id=income_header_row, MATCH(income_min_row,$C:$C,0), IF(header_row_id=expenses_header_row,MATCH(expenses_min_row,$C:$C,0), IF(header_row_id=Savings_header_row,MATCH(savings_min_row,$C:$C,0),""))), "")} | N42: {=IF(is_cat, IF(header_row_id=income_header_row, MATCH(income_max_row,$C:$C,0), IF(header_row_id=expenses_header_row,MATCH(expenses_max_row,$C:$C,0), IF(header_row_id=Savings_header_row,MATCH(savings_max_row,$C:$C,0),""))), "")} | O42: =IF(is_cat,ADDRESS(sort_min_row,COLUMN(tracked)) &":" & ADDRESS(sort_max_row,COLUMN(tracked)), "") | P42: =IF(is_cat,RANK(tracked,INDIRECT(tracked_range),0), "") | Q42: =IF(is_cat,ADDRESS(sort_min_row,COLUMN(budget)) & ":" &ADDRESS(sort_max_row,COLUMN(budget)), "") | R42: =IF(is_cat,RANK(budget,INDIRECT(budget_range),0),"") | S42: =IF(is_cat,_xlfn.NUMBERVALUE(tracked_rank& budget_rank),"") | T42: =IF(is_cat,ADDRESS(sort_min_row,COLUMN(comb_rank)) & ":" &ADDRESS(sort_max_row,COLUMN(comb_rank)), "") | U42: =IF(is_cat,RANK(comb_rank,INDIRECT(comb_rank_range),1),"") | V42: =IF(is_cat,ADDRESS(sort_min_row,COLUMN(comb_rank_norm)) & ":" &ADDRESS(ROW(),COLUMN(comb_rank_norm)), "") | W42: =IF(is_cat,comb_rank_norm+ COUNTIF(INDIRECT(comb_rank_norm_run_range),comb_rank_norm)-1,"") | X42: =IF(is_cat,header_row_id+comb_rank_unique,row_id) -> -1 | Y42: =IF(is_empty,"",INDEX($J:$J,MATCH(row_id,$X:$X,0))) | Z42: =IF(is_empty,"",IF(is_header,"Tracked",INDEX($K:$K, MATCH(row_id,$X:$X,0)))) | AA42: =IF(is_empty,"",IF(is_header,"Budget",INDEX($L:$L, MATCH(row_id,$X:$X,0)))) | AB42: =IF(is_empty,"",IF(is_header,"%Compl.",IFERROR(out_tracked/out_budget,"-"))) | AC42: =IF(is_empty,"",IF(is_header,"Remaining",IF(out_budget-out_tracked > 0, out_budget-out_tracked,0))) | AD42: =IF(is_empty,"",IF(is_header,"Excess",IF(out_budget-out_tracked < 0, out_tracked-out_budget,0)))
C43: {=IF(C42=-1,-1, IF(C42<income_max_row,C42+1, IF(C42=income_max_row,income_total_row, IF(C42=income_total_row, "/1", IF(C42="/1",expenses_header_row, IF(C42<expenses_max_row, C42+1, IF(C42=expenses_max_row,expenses_total_row, IF(C42=expenses_total_row,"/2", IF(C42="/2",Savings_header_row, IF(C42<savings_max_row,C42+1, IF(C42=savings_max_row,savings_total_row, -1)))))))))))} -> -1 | D43: =IF(is_header,row_id, IF(NOT(is_empty),D42,-1)) -> -1 | E43: {=1*OR(row_id=income_header_row,row_id=expenses_header_row,row_id=Savings_header_row)} -> 0 | F43: =1*NOT(OR(is_header,is_total,is_empty)) -> 0 | G43: {=1*OR(row_id=income_total_row,row_id=expenses_total_row,row_id=savings_total_row)} -> 0 | H43: =1*OR(row_id="/1",row_id="/2",row_id=-1) -> 1 | I43: {=IFERROR(INDEX(Budget_Planning!$C:$C,header_row_id), " ")} | J43: {=IFERROR(INDEX(Budget_Planning!$C:$C,row_id), " ")} | K43: {=IF(OR(is_header,is_empty),"", IF(is_total, IF(Selected_period="Total Year", SUM(Tracking[Amount]*(Tracking[Type]=type)*(YEAR(Tracking[Effective Date])=Selected_Year) ), SUM(Tracking[Amount]*(Tracking[Type]=type)*(YEAR(Tracking[Effective Date])=Selected_Year) * (MONTH(Tracking[Effective Date])=Selected_period))), IF(Selected_period="Total Year", SUM(Tracking[Amount]*(Tracking[Type]=type)*(Tracking[Category]=item)*(YEAR(Tracking[Effective Date])=Selected_Year)), SUM(Tracking[Amount]*(Tracking[Type]=type)*(Tracking[Category]=item)*(YEAR(Tracking[Effective Date])=Selected_Year) * (MONTH(Tracking[Effective Date])=Selected_period)) )))} | L43: {=IF(OR(is_header,is_empty),"", INDEX(Budget_Planning!$E:$DY,row_id, MATCH(IF(Selected_period="Total Year",Selected_Year,DATE(Selected_Year,Selected_period,1)), Budget_Planning!$E$9:$DY$9, 0)))} | M43: {=IF(is_cat, IF(header_row_id=income_header_row, MATCH(income_min_row,$C:$C,0), IF(header_row_id=expenses_header_row,MATCH(expenses_min_row,$C:$C,0), IF(header_row_id=Savings_header_row,MATCH(savings_min_row,$C:$C,0),""))), "")} | N43: {=IF(is_cat, IF(header_row_id=income_header_row, MATCH(income_max_row,$C:$C,0), IF(header_row_id=expenses_header_row,MATCH(expenses_max_row,$C:$C,0), IF(header_row_id=Savings_header_row,MATCH(savings_max_row,$C:$C,0),""))), "")} | O43: =IF(is_cat,ADDRESS(sort_min_row,COLUMN(tracked)) &":" & ADDRESS(sort_max_row,COLUMN(tracked)), "") | P43: =IF(is_cat,RANK(tracked,INDIRECT(tracked_range),0), "") | Q43: =IF(is_cat,ADDRESS(sort_min_row,COLUMN(budget)) & ":" &ADDRESS(sort_max_row,COLUMN(budget)), "") | R43: =IF(is_cat,RANK(budget,INDIRECT(budget_range),0),"") | S43: =IF(is_cat,_xlfn.NUMBERVALUE(tracked_rank& budget_rank),"") | T43: =IF(is_cat,ADDRESS(sort_min_row,COLUMN(comb_rank)) & ":" &ADDRESS(sort_max_row,COLUMN(comb_rank)), "") | U43: =IF(is_cat,RANK(comb_rank,INDIRECT(comb_rank_range),1),"") | V43: =IF(is_cat,ADDRESS(sort_min_row,COLUMN(comb_rank_norm)) & ":" &ADDRESS(ROW(),COLUMN(comb_rank_norm)), "") | W43: =IF(is_cat,comb_rank_norm+ COUNTIF(INDIRECT(comb_rank_norm_run_range),comb_rank_norm)-1,"") | X43: =IF(is_cat,header_row_id+comb_rank_unique,row_id) -> -1 | Y43: =IF(is_empty,"",INDEX($J:$J,MATCH(row_id,$X:$X,0))) | Z43: =IF(is_empty,"",IF(is_header,"Tracked",INDEX($K:$K, MATCH(row_id,$X:$X,0)))) | AA43: =IF(is_empty,"",IF(is_header,"Budget",INDEX($L:$L, MATCH(row_id,$X:$X,0)))) | AB43: =IF(is_empty,"",IF(is_header,"%Compl.",IFERROR(out_tracked/out_budget,"-"))) | AC43: =IF(is_empty,"",IF(is_header,"Remaining",IF(out_budget-out_tracked > 0, out_budget-out_tracked,0))) | AD43: =IF(is_empty,"",IF(is_header,"Excess",IF(out_budget-out_tracked < 0, out_tracked-out_budget,0)))
... C47: {=IF(C46=-1,-1, IF(C46<income_max_row,C46+1, IF(C46=income_max_row,income_total_row, IF(C46=income_total_row, "/1", IF(C46="/1",expenses_header_row, IF(C46<expenses_max_row, C46+1, IF(C46=expenses_max_row,expenses_total_row, IF(C46=expenses_total_row,"/2", IF(C46="/2",Savings_header_row, IF(C46<savings_max_row,C46+1, IF(C46=savings_max_row,savings_total_row, -1)))))))))))} -> -1 | D47: =IF(is_header,row_id, IF(NOT(is_empty),D46,-1)) -> -1 | E47: {=1*OR(row_id=income_header_row,row_id=expenses_header_row,row_id=Savings_header_row)} -> 0 | F47: =1*NOT(OR(is_header,is_total,is_empty)) -> 0 | G47: {=1*OR(row_id=income_total_row,row_id=expenses_total_row,row_id=savings_total_row)} -> 0 | H47: =1*OR(row_id="/1",row_id="/2",row_id=-1) -> 1 | I47: {=IFERROR(INDEX(Budget_Planning!$C:$C,header_row_id), " ")} | J47: {=IFERROR(INDEX(Budget_Planning!$C:$C,row_id), " ")} | K47: {=IF(OR(is_header,is_empty),"", IF(is_total, IF(Selected_period="Total Year", SUM(Tracking[Amount]*(Tracking[Type]=type)*(YEAR(Tracking[Effective Date])=Selected_Year) ), SUM(Tracking[Amount]*(Tracking[Type]=type)*(YEAR(Tracking[Effective Date])=Selected_Year) * (MONTH(Tracking[Effective Date])=Selected_period))), IF(Selected_period="Total Year", SUM(Tracking[Amount]*(Tracking[Type]=type)*(Tracking[Category]=item)*(YEAR(Tracking[Effective Date])=Selected_Year)), SUM(Tracking[Amount]*(Tracking[Type]=type)*(Tracking[Category]=item)*(YEAR(Tracking[Effective Date])=Selected_Year) * (MONTH(Tracking[Effective Date])=Selected_period)) )))} | L47: {=IF(OR(is_header,is_empty),"", INDEX(Budget_Planning!$E:$DY,row_id, MATCH(IF(Selected_period="Total Year",Selected_Year,DATE(Selected_Year,Selected_period,1)), Budget_Planning!$E$9:$DY$9, 0)))} | M47: {=IF(is_cat, IF(header_row_id=income_header_row, MATCH(income_min_row,$C:$C,0), IF(header_row_id=expenses_header_row,MATCH(expenses_min_row,$C:$C,0), IF(header_row_id=Savings_header_row,MATCH(savings_min_row,$C:$C,0),""))), "")} | N47: {=IF(is_cat, IF(header_row_id=income_header_row, MATCH(income_max_row,$C:$C,0), IF(header_row_id=expenses_header_row,MATCH(expenses_max_row,$C:$C,0), IF(header_row_id=Savings_header_row,MATCH(savings_max_row,$C:$C,0),""))), "")} | O47: =IF(is_cat,ADDRESS(sort_min_row,COLUMN(tracked)) &":" & ADDRESS(sort_max_row,COLUMN(tracked)), "") | P47: =IF(is_cat,RANK(tracked,INDIRECT(tracked_range),0), "") | Q47: =IF(is_cat,ADDRESS(sort_min_row,COLUMN(budget)) & ":" &ADDRESS(sort_max_row,COLUMN(budget)), "") | R47: =IF(is_cat,RANK(budget,INDIRECT(budget_range),0),"") | S47: =IF(is_cat,_xlfn.NUMBERVALUE(tracked_rank& budget_rank),"") | T47: =IF(is_cat,ADDRESS(sort_min_row,COLUMN(comb_rank)) & ":" &ADDRESS(sort_max_row,COLUMN(comb_rank)), "") | U47: =IF(is_cat,RANK(comb_rank,INDIRECT(comb_rank_range),1),"") | V47: =IF(is_cat,ADDRESS(sort_min_row,COLUMN(comb_rank_norm)) & ":" &ADDRESS(ROW(),COLUMN(comb_rank_norm)), "") | W47: =IF(is_cat,comb_rank_norm+ COUNTIF(INDIRECT(comb_rank_norm_run_range),comb_rank_norm)-1,"") | X47: =IF(is_cat,header_row_id+comb_rank_unique,row_id) -> -1 | Y47: =IF(is_empty,"",INDEX($J:$J,MATCH(row_id,$X:$X,0))) | Z47: =IF(is_empty,"",IF(is_header,"Tracked",INDEX($K:$K, MATCH(row_id,$X:$X,0)))) | AA47: =IF(is_empty,"",IF(is_header,"Budget",INDEX($L:$L, MATCH(row_id,$X:$X,0)))) | AB47: =IF(is_empty,"",IF(is_header,"%Compl.",IFERROR(out_tracked/out_budget,"-"))) | AC47: =IF(is_empty,"",IF(is_header,"Remaining",IF(out_budget-out_tracked > 0, out_budget-out_tracked,0))) | AD47: =IF(is_empty,"",IF(is_header,"Excess",IF(out_budget-out_tracked < 0, out_tracked-out_budget,0)))
E48: TRUE

Sheet LookUpData
B2: Dropdown Data
C7: Year Dropdown | E7: Period Dropdown
C8: Current Year | E8: Total Year
C9: =starting_year -> 2022 | E9: Current Month
C10: =C9+1 -> 2023 | E10: 36526
C11: =C10+1 -> 2024 | E11: 36557
C12: =C11+1 -> 2025 | E12: 36586
C13: =C12+1 -> 2026 | E13: 36617
C14: =C13+1 -> 2027 | E14: 36647
C15: =C14+1 -> 2028 | E15: 36678
C16: =C15+1 -> 2029 | E16: 36708
C17: =C16+1 -> 2030 | E17: 36739
C18: =C17+1 -> 2031 | E18: 36770
E19: 36800
E20: 36831
E21: 36861

Sheet Calculations
B2: Calculations
C6: worksheet: Budget Tracking
D8: Today: | E8: {=current_date} -> 46163
D9: Last Record: | E9: =MAX(Tracking[Date]) -> 44635
D10: Date of a last record: | E10: =IF(D9=0, "","("&_xlfn.DAYS(E8,E9)& " Days ago)") -> (1528 Days ago)
D11: #Records : | E11: =COUNT(Tracking[Date]) -> 45
D12: #Records this year : | E12: {="(" &SUMPRODUCT(--(YEAR(Tracking[Date])=YEAR(current_date))) &" this year)"} -> (0 this year)
D13: Total tracking balance: | E13: =_xlfn.IFNA(INDEX(Tracking[Balance],MATCH(Calculations!E9,Tracking[Date],0)), "-") -> 130
D14: Balance Analysis Text: | E14: =IF(E13>=0, "off tracked income left to be allocated", "allocated not covered by income") -> off tracked income left to be allocated
D17: worksheet: Budget Dashboard
D19: Selected Year: | E19: {=IF(Budget_Dashboard!$AL$6="Current Year",YEAR(current_date),Budget_Dashboard!$AL$6)} -> 2022
D20: Selected Period: | E20: {=IF(Budget_Dashboard!$AQ$6="Total Year","Total Year",IF(Budget_Dashboard!$AQ$6="Current Month", MONTH(current_date),MONTH(Budget_Dashboard!$AQ$6)))} -> Total Year
D21: Selected Period(Display): | E21: =IF(Selected_period="Total Year", "Total Year",TEXT(DATE(Selected_Year, Selected_period,1), "mmmm")) -> Total Year
D22: Days in Period: | E22: =IF(Selected_period="TOTAL Year",DATE(Selected_Year,12,31) - DATE(Selected_Year - 1,12,31),DAY(EOMONTH(DATE(Selected_Year,Selected_period,1),0))) -> 365
